Workbook
Name a: #REF!
Name a: #REF!
Name a: #REF!
Name a: #REF!
Name a: #REF!
Name bn: #REF!
Name bn: #REF!
Name bn: #REF!
Name bn: #REF!
Name bn: #REF!
Name CATEGORIE: #REF!
Name CATEGORIE: #REF!
Name CATEGORIE: #REF!
Name CATEGORIE: #REF!
Name CATEGORIE: #REF!
Name CERTIFICATS: #REF!
Name CERTIFICATS: #REF!
Name CERTIFICATS: #REF!
Name CERTIFICATS: #REF!
Name CERTIFICATS: #REF!
Name customer: '[1]BASE DE DONNEES'!$O$4:$O$55
Name H: #REF!
Name H: #REF!
Name H: #REF!
Name H: #REF!
Name H: #REF!
Name INDEX: '[1]BASE DE DONNEES'!$AE$4:$AE$14
Name NUANCE: #REF!
Name NUANCE: #REF!
Name NUANCE: #REF!
Name NUANCE: #REF!
Name NUANCE: #REF!
Name PI: #REF!
Name PI: #REF!
Name PI: #REF!
Name PI: #REF!
Name PI: #REF!
Name PIPI: #REF!
Name PIPI: #REF!
Name PIPI: #REF!
Name PIPI: #REF!
Name PIPI: #REF!
Name POPO: #REF!
Name POPO: #REF!
Name POPO: #REF!
Name POPO: #REF!
Name POPO: #REF!
Name PROFILS: #REF!
Name PROFILS: #REF!
Name PROFILS: #REF!
Name PROFILS: #REF!
Name PROFILS: #REF!
Name SD: #REF!
Name SD: #REF!
Name SD: #REF!
Name SD: #REF!
Name SD: #REF!
Name tsm: '[1]BASE DE DONNEES'!$G$4:$G$8
Name UI: #REF!
Name UI: #REF!

Sheet FC-REDRESSAGE
G1: =PREVI!C10 -> CIMOLAI | K1: =PREVI!C11 -> PASSERELLE DE BELVAL
M2: =PREVI!A11 -> Z128
A3: ArcelorMittal Belval & Differdange S.A. | H3: Parachèvement spécial
A4: Site de Differdange
A5: FICHE DE CONTRÔLE / Kontrollblatt | J5: REDRESSAGE / Nachrichten
A6: Check sheet / Protokół Kontroli | J6: Redress / Geomteria
A7: CDE | B7: =PREVI!A10 -> 1100633635-636 | G7: Plan n° | H7: =PREVI!A24 -> 0 | J7: Tolérance visée: | L7: EN 10034 : 1993 | N7: (h > 360)
A8: Auftrag n° | G8: Zeichen n° | J8: Toleranz visiert
A9: Order n° | G9: Plan n° | J9: Tolerance referred
A10: Zlecenie n° | G10: Rys nr | J10: Tolerancja
A19: Date | B19: Pos | C19: Rep | D19: Profil | E19: Longueur | F19: N°laminage | G19: Larg aile | H19: K+K' max | I19: K+K' relevé | J19: F-W maxi | K19: F relevé | L19: W relevé | M19: Def.Ame | N19: Contrôleur | P19: EN 10034 : 1993 | V19: (h ≤ 360)
A20: Datum | B20: Pos | C20: Pos | D20: Profil | E20: Länge | F20: Walznummer | G20: Flanschbreite | H20: K+K' max | I20: K+K' ist | J20: =IF($L$7=$P$19,T20,IF($L$7=$P$21,S20,IF($L$7=$P$20,U20,""))) -> 1mm pro m | K20: F ist | L20: W ist | M20: Stegverform | N20: Prüfer | P20: 50% EN 10034 : 1993 | S20: 0.7mm pro m | T20: 1mm pro m | U20: 0,5mm pro m | V20: (h > 360)
A21: Date | B21: Pos | C21: Mark | D21: Section | E21: Length | F21: rolling number | G21: Width flange | H21: K+K' max | I21: K+K' is | J21: =IF($L$7=$P$19,T21,IF($L$7=$P$21,S21,IF($L$7=$P$20,U21,""))) -> 1mm / m | K21: F is | L21: W is | M21: Web déf. | N21: Controller | P21: 2/3 EN 10034 : 1993 | S21: 0.7mm / m | T21: 1mm / m | U21: 0,5mm / m
A22: Data | B22: Poz | C22: Element | D22: Profil | E22: Długość | F22: Nr walcowania | G22: Szerokość | H22: K+K' max | I22: K+K' są | J22: =IF($L$7=$P$19,T22,IF($L$7=$P$21,S22,IF($L$7=$P$20,U22,""))) -> 1mm na m | K22: Fs ą | L22: W są | M22: Ugięcie | N22: Kontroler | S22: 0.7mm na m | T22: 1mm na m | U22: 0,5mm na m
B23: =SUIVI!E9 -> 1 | D23: =SUIVI!H9 -> HL1100A | E23: =SUIVI!I9 -> 11100 | F23: =SUIVI!M9 -> CZ6 | G23: 400 | H23: =IF($L$7=$P$19,IF(0.02*G23>6.5,6.5,0.02*G23),IF($L$7=$P$20,IF(0.02*G23/2>6.5,6.5,0.02*G23/2),IF($L$7=$P$21,IF(0.02*G23*2/3>6.5,6.5,0.02*G23*2/3)))) -> 6.5 | J23: =IF($N$7=$V$20,IF($L$7=$P$19,E23/1000,IF($L$7=$P$20,E23/2000,IF($L$7=$P$21,E23*2/3000))),IF($L$7=$P$19,E23*0.0015,IF($L$7=$P$20,E23*0.00075,IF($L$7=$P$21,E23*0.001)))) -> 11.1 | O23: 1
B24: =SUIVI!E10 -> 1 | D24: =SUIVI!H10 -> HL1100A | E24: =SUIVI!I10 -> 11100 | F24: =SUIVI!M10 -> CZ7 | G24: 400 | H24: =IF($L$7=$P$19,IF(0.02*G24>6.5,6.5,0.02*G24),IF($L$7=$P$20,IF(0.02*G24/2>6.5,6.5,0.02*G24/2),IF($L$7=$P$21,IF(0.02*G24*2/3>6.5,6.5,0.02*G24*2/3)))) -> 6.5 | J24: =IF($N$7=$V$20,IF($L$7=$P$19,E24/1000,IF($L$7=$P$20,E24/2000,IF($L$7=$P$21,E24*2/3000))),IF($L$7=$P$19,E24*0.0015,IF($L$7=$P$20,E24*0.00075,IF($L$7=$P$21,E24*0.001)))) -> 11.1 | O24: 2
B25: =SUIVI!E11 -> 9 | D25: =SUIVI!H11 -> HL1100A | E25: =SUIVI!I11 -> 11300 | F25: =SUIVI!M11 -> CZ52 | G25: 400 | H25: =IF($L$7=$P$19,IF(0.02*G25>6.5,6.5,0.02*G25),IF($L$7=$P$20,IF(0.02*G25/2>6.5,6.5,0.02*G25/2),IF($L$7=$P$21,IF(0.02*G25*2/3>6.5,6.5,0.02*G25*2/3)))) -> 6.5 | J25: =IF($N$7=$V$20,IF($L$7=$P$19,E25/1000,IF($L$7=$P$20,E25/2000,IF($L$7=$P$21,E25*2/3000))),IF($L$7=$P$19,E25*0.0015,IF($L$7=$P$20,E25*0.00075,IF($L$7=$P$21,E25*0.001)))) -> 11.3 | O25: 3
B26: =SUIVI!E12 -> 10 | D26: =SUIVI!H12 -> HL1100A | E26: =SUIVI!I12 -> 9200 | F26: =SUIVI!M12 -> EA15 | G26: 400 | H26: =IF($L$7=$P$19,IF(0.02*G26>6.5,6.5,0.02*G26),IF($L$7=$P$20,IF(0.02*G26/2>6.5,6.5,0.02*G26/2),IF($L$7=$P$21,IF(0.02*G26*2/3>6.5,6.5,0.02*G26*2/3)))) -> 6.5 | J26: =IF($N$7=$V$20,IF($L$7=$P$19,E26/1000,IF($L$7=$P$20,E26/2000,IF($L$7=$P$21,E26*2/3000))),IF($L$7=$P$19,E26*0.0015,IF($L$7=$P$20,E26*0.00075,IF($L$7=$P$21,E26*0.001)))) -> 9.2 | O26: 4
B27: =SUIVI!E13 -> 2 | D27: =SUIVI!H13 -> HL1100A | E27: =SUIVI!I13 -> 10700 | F27: =SUIVI!M13 -> CZ9 oder10 | G27: 400 | H27: =IF($L$7=$P$19,IF(0.02*G27>6.5,6.5,0.02*G27),IF($L$7=$P$20,IF(0.02*G27/2>6.5,6.5,0.02*G27/2),IF($L$7=$P$21,IF(0.02*G27*2/3>6.5,6.5,0.02*G27*2/3)))) -> 6.5 | J27: =IF($N$7=$V$20,IF($L$7=$P$19,E27/1000,IF($L$7=$P$20,E27/2000,IF($L$7=$P$21,E27*2/3000))),IF($L$7=$P$19,E27*0.0015,IF($L$7=$P$20,E27*0.00075,IF($L$7=$P$21,E27*0.001)))) -> 10.7 | O27: 5
B28: =SUIVI!E14 -> 38 | D28: =SUIVI!H14 -> HL1100A | E28: =SUIVI!I14 -> 10600 | F28: =SUIVI!M14 -> EC48 | G28: 400 | H28: =IF($L$7=$P$19,IF(0.02*G28>6.5,6.5,0.02*G28),IF($L$7=$P$20,IF(0.02*G28/2>6.5,6.5,0.02*G28/2),IF($L$7=$P$21,IF(0.02*G28*2/3>6.5,6.5,0.02*G28*2/3)))) -> 6.5 | J28: =IF($N$7=$V$20,IF($L$7=$P$19,E28/1000,IF($L$7=$P$20,E28/2000,IF($L$7=$P$21,E28*2/3000))),IF($L$7=$P$19,E28*0.0015,IF($L$7=$P$20,E28*0.00075,IF($L$7=$P$21,E28*0.001)))) -> 10.6 | O28: 6
B29: =SUIVI!E15 -> 38 | D29: =SUIVI!H15 -> HL1100A | E29: =SUIVI!I15 -> 10600 | F29: =SUIVI!M15 -> EC49 | G29: 400 | H29: =IF($L$7=$P$19,IF(0.02*G29>6.5,6.5,0.02*G29),IF($L$7=$P$20,IF(0.02*G29/2>6.5,6.5,0.02*G29/2),IF($L$7=$P$21,IF(0.02*G29*2/3>6.5,6.5,0.02*G29*2/3)))) -> 6.5 | J29: =IF($N$7=$V$20,IF($L$7=$P$19,E29/1000,IF($L$7=$P$20,E29/2000,IF($L$7=$P$21,E29*2/3000))),IF($L$7=$P$19,E29*0.0015,IF($L$7=$P$20,E29*0.00075,IF($L$7=$P$21,E29*0.001)))) -> 10.6 | O29: 7
B30: =SUIVI!E16 -> 38 | D30: =SUIVI!H16 -> HL1100A | E30: =SUIVI!I16 -> 10600 | F30: =SUIVI!M16 -> EC50 | G30: 400 | H30: =IF($L$7=$P$19,IF(0.02*G30>6.5,6.5,0.02*G30),IF($L$7=$P$20,IF(0.02*G30/2>6.5,6.5,0.02*G30/2),IF($L$7=$P$21,IF(0.02*G30*2/3>6.5,6.5,0.02*G30*2/3)))) -> 6.5 | J30: =IF($N$7=$V$20,IF($L$7=$P$19,E30/1000,IF($L$7=$P$20,E30/2000,IF($L$7=$P$21,E30*2/3000))),IF($L$7=$P$19,E30*0.0015,IF($L$7=$P$20,E30*0.00075,IF($L$7=$P$21,E30*0.001)))) -> 10.6 | O30: 8
B31: =SUIVI!E17 -> 38 | D31: =SUIVI!H17 -> HL1100A | E31: =SUIVI!I17 -> 10600 | F31: =SUIVI!M17 -> EC51 | G31: 400 | H31: =IF($L$7=$P$19,IF(0.02*G31>6.5,6.5,0.02*G31),IF($L$7=$P$20,IF(0.02*G31/2>6.5,6.5,0.02*G31/2),IF($L$7=$P$21,IF(0.02*G31*2/3>6.5,6.5,0.02*G31*2/3)))) -> 6.5 | J31: =IF($N$7=$V$20,IF($L$7=$P$19,E31/1000,IF($L$7=$P$20,E31/2000,IF($L$7=$P$21,E31*2/3000))),IF($L$7=$P$19,E31*0.0015,IF($L$7=$P$20,E31*0.00075,IF($L$7=$P$21,E31*0.001)))) -> 10.6 | O31: 9
B32: =SUIVI!E18 -> 27 | D32: =SUIVI!H18 -> HL1100B | E32: =SUIVI!I18 -> 15800 | F32: =SUIVI!M18 -> EC406 oder 407 | G32: 400 | H32: =IF($L$7=$P$19,IF(0.02*G32>6.5,6.5,0.02*G32),IF($L$7=$P$20,IF(0.02*G32/2>6.5,6.5,0.02*G32/2),IF($L$7=$P$21,IF(0.02*G32*2/3>6.5,6.5,0.02*G32*2/3)))) -> 6.5 | J32: =IF($N$7=$V$20,IF($L$7=$P$19,E32/1000,IF($L$7=$P$20,E32/2000,IF($L$7=$P$21,E32*2/3000))),IF($L$7=$P$19,E32*0.0015,IF($L$7=$P$20,E32*0.00075,IF($L$7=$P$21,E32*0.001)))) -> 15.8 | O32: 10
O33: 200 | P33: RECOPIE MAXIMUM
A34: Rectitude selon EN 10034:1993 | E34: hauteur (h) | F34: tolérance EN 10034 | H34: tol. 2/3 EN 10034 | J34: tol. 50% EN 10035
A35: Geradheit | E35: Höhe / height | F35: Toleranz | G35: Tolerance | H35: Toleranz | I35: Tolerance | J35: Toleranz | K35: Tolerance
A36: Staightness | E36: Wysokość | F36: tolerancja | H36: tolerancja | J36: tolerancja
A37: Rktyfikacja | E37: 80<h≤180 | F37: +/- 0.0030 x L | H37: +/- 0.0020 x L | J37: +/- 0.0015 x L
E38: 180<h≤360 | F38: +/- 0.0015 x L | H38: +/- 0.0010 x L | J38: +/- 0.0008 x L
E39: h>360 | F39: +/- 0.0010 x L | H39: +/- 0.0007 x L | J39: +/- 0.0005 x L

Sheet FC-1 BIAIS
E1: =PREVI!C10 -> CIMOLAI | I1: =PREVI!C11 -> PASSERELLE DE BELVAL
A3: ArcelorMittal Belval & Differdange S.A. | F3: FICHE DE CONTRÔLE / Kontrollblatt / Check sheet | L3: SCIE / Säge / Saw | O3: 0/+2mm
A4: Site de Differdange | I4: Protokół Kontroli | L4: Cięcie | O4: -2/+0mm
A6: Parachèvement spécial | G6: Tol. longueur visée: | I6: +/-2mm | J6: Critère d'acceptation EN 1090-2 Tab. B.6 | O6: +/-2mm
G7: Längentoleranz visiert +/- mm. | J7: Akzeptanzkriterien nach EN 1090-2 Tab. B.6 | O7: +/-3mm
G8: Length tolerance referred +/- mm | J8: Acceptance according to EN1090-2 Tab. B.6 | O8: +/-4mm
G9: Tolerancja długości +/- mm | J9: Przyjęcie wg EN 1090-2 stół B.6 | O9: +/-5mm
G11: Commande: | H11: =PREVI!$A$10 -> 1100633635-636 | I11: =PREVI!$A$11 -> Z128 | J11: =PREVI!$A$12 -> 1900015151-15087
G12: Auftrag n° /Order n° / Ziecenie n°
G14: L = | H14: A = | I14: B =
D15: H= | G15: =E20 -> 10300 | H15: =G15-I15 -> 10300 | J15: =IF(E15,DEGREES(L15),"") | L15: =IF(E15,ATAN(I15/E15),"")
A16: Date | B16: Pos | C16: Rep | D16: Profil | E16: Longueur | F16: N°laminage | G16: Longueur | H16: Longueur | I16: Biais | J16: Angle 1 (°) | K16: Contrôleur | L16: C.E.
A17: Datum | B17: Pos | C17: Pos | D17: Profil | E17: Länge Soll | F17: Walznummer | G17: Länge Ist | H17: Länge Ist | I17: Schrag | J17: Winkel 1 | K17: Prüfer | L17: S.L.
A18: Date | B18: Pos | C18: Mark | D18: Section | E18: Length | F18: rolling number | G18: Length | H18: Length | I18: Slant | J18: Angle 1 | K18: Controller | L18: Overseer
A19: Data | B19: Poz | C19: Element | D19: Profil | E19: Długość | F19: Nr walcowania | G19: Długość | H19: Długość | I19: Ukos | J19: Kat 1 | K19: Kontroler | L19: C.E.
B20: =SUIVI!Q9 -> 0 | C20: =SUIVI!R9 -> 0 | D20: =SUIVI!H9 -> HL1100A | E20: =SUIVI!J9 -> 10300 | F20: =SUIVI!S9 -> CZ6
B21: =SUIVI!Q10 -> 0 | C21: =SUIVI!R10 -> 0 | D21: =SUIVI!H10 -> HL1100A | E21: =SUIVI!J10 -> 10300 | F21: =SUIVI!S10 -> CZ7
B22: =SUIVI!Q11 -> 0 | C22: =SUIVI!R11 -> 0 | D22: =SUIVI!H11 -> HL1100A | E22: =SUIVI!J11 -> 10400 | F22: =SUIVI!S11 -> CZ52
B23: =SUIVI!Q12 -> 0 | C23: =SUIVI!R12 -> 0 | D23: =SUIVI!H12 -> HL1100A | E23: =SUIVI!J12 -> 9000 | F23: =SUIVI!S12 -> EA15
A65: Tol d'équer. EN 1090-2 D.2.7cl1 | E65: haut/larg. | F65: tolérance | H65: haut/larg. | I65: tolérance | K65: haut/larg. | L65: tolérance
A66: ausser Winkel | E66: Höhe/Breite | F66: Toleranz | H66: Höhe/Breite | I66: Toleranz | K66: Höhe/Breite | L66: Toleranz
A67: tolerance squarring | E67: wys./szer. | F67: tolerancja | H67: wys./szer. | I67: tolerancja | K67: wys./szer. | L67: tolerancja
A68: tolerancja skośności | E68: 200 | F68: 2 | H68: 600 | I68: 6 | K68: 1000 | L68: 10
E69: 300 | F69: 3 | H69: 700 | I69: 7 | K69: 1100 | L69: 11
E70: 400 | F70: 4 | H70: 800 | I70: 8
E71: 500 | F71: 5 | H71: 900 | I71: 9
A72: Tol d'équer. EN 1090-2 D.2.7cl2 | E72: haut/larg. | F72: tolérance | H72: haut/larg. | I72: tolérance | K72: haut/larg. | L72: tolérance
A73: ausser Winkel | E73: Höhe/Breite | F73: Toleranz | H73: Höhe/Breite | I73: Toleranz | K73: Höhe/Breite | L73: Toleranz
A74: tolerance squarring | E74: wys./szer. | F74: tolerancja | H74: wys./szer. | I74: tolerancja | K74: wys./szer. | L74: tolerancja
A75: tolerancja skośności | E75: 200 | F75: 0.7 | H75: 600 | I75: 2 | K75: 1000 | L75: 3.3
E76: 300 | F76: 1 | H76: 700 | I76: 2.3 | K76: 1100 | L76: 3.7
E77: 400 | F77: 1.3 | H77: 800 | I77: 2.7
E78: 500 | F78: 1.7 | H78: 900 | I78: 3
A79: Tol.d'équerre:+/-20' (0,33°) | E79: haut/larg. | F79: tolérance | H79: haut/larg. | I79: tolérance | K79: haut/larg. | L79: tolérance
A80: ausser Winkel | E80: Höhe/Breite | F80: Toleranz | H80: Höhe/Breite | I80: Toleranz | K80: Höhe/Breite | L80: Toleranz
A81: tolerance squarring | E81: wys./szer. | F81: tolerancja | H81: wys./szer. | I81: tolerancja | K81: wys./szer. | L81: tolerancja
A82: tolerancja skośności | E82: 200 | F82: 1.2 | H82: 600 | I82: 3.5 | K82: 1000 | L82: 5.8
E83: 300 | F83: 1.7 | H83: 700 | I83: 4.1 | K83: 1100 | L83: 6.4
E84: 400 | F84: 2.3 | H84: 800 | I84: 4.7
E85: 500 | F85: 2.9 | H85: 900 | I85: 5.2
A87: Remarques/Bermekungen/Remarks/Uwagi

Sheet FC-2 BIAIS
F1: =PREVI!C10 -> CIMOLAI | J1: =PREVI!C11 -> PASSERELLE DE BELVAL
A3: ArcelorMittal Belval & Differdange S.A. | F3: FICHE DE CONTRÔLE / Kontrollblatt / Check sheet | L3: SCIE / Säge / Saw | Q3: 0/+2mm
A4: Site de Differdange | I4: Protokół Kontroli | L4: Cięcie | Q4: -2/+0mm
A6: Parachèvement spécial | G6: Tol. longueur visée: | I6: +/-2mm | K6: Critère d'acceptation EN 1090-2 Tab. B.6 | Q6: +/-2mm
G7: Längentoleranz visiert +/- mm. | K7: Akzeptanzkriterien nach EN 1090-2 Tab. B.6 | Q7: +/-3mm
G8: Length tolerance referred +/-mm | K8: Acceptance according to EN1090-2 Tab. B.6 | Q8: +/-4mm
G9: Tolerancja długości +/- mm | K9: Przyjęcie wg EN 1090-2 stół B.6 | Q9: +/-5mm
G11: Commande: | I11: =PREVI!$A$10 -> 1100633635-636 | K11: =PREVI!$A$11 -> Z128 | M11: =PREVI!$A$12 -> 1900015151-15087
G12: Auftrag n° /Order n° / Ziecenie n°
G14: L = | H14: A = | I14: a = | K14: B = | L14: b = | O14: =IF(E15,ATAN(L15/E15),"")
D15: H= | G15: =E20 -> 10300 | H15: =G15-I15 -> 10300 | J15: =IF(E15,DEGREES(O15),"") | K15: =G15-L15 -> 10300 | M15: =IF(E15,DEGREES(O14),"") | O15: =IF(E15,ATAN(I15/E15),"")
A16: Date | B16: Pos | C16: Rep | D16: Profil | E16: Longueur | F16: N°laminage | G16: Longueur | H16: Longueur | I16: Biais | J16: Angle 1 (°) | K16: Longueur | L16: Biais | M16: Angle 2 (°) | N16: Contrôleur | O16: C.E.
A17: Datum | B17: Pos | C17: Pos | D17: Profil | E17: Länge Soll | F17: Walznummer | G17: Länge Ist | H17: Länge Ist | I17: Schrag | J17: Winkel 1 | K17: Länge Ist | L17: Schrag | M17: Winkel 1 | N17: Prüfer | O17: S.L.
A18: Date | B18: Pos | C18: Mark | D18: Section | E18: Length | F18: rolling number | G18: Length | H18: Length | I18: Slant | J18: Angle 1 | K18: Length | L18: Slant | M18: Angle | N18: Controller | O18: Overseer
A19: Data | B19: Poz | C19: Element | D19: Profil | E19: Długość | F19: Nr walcowania | G19: Długość | H19: Długość | I19: Ukos | J19: Kat 1 | K19: Długość | L19: Ukos | M19: Kat 1 | N19: Kontroler | O19: C.E.
B20: =SUIVI!Q9 -> 0 | C20: =SUIVI!R9 -> 0 | D20: =SUIVI!H9 -> HL1100A | E20: =SUIVI!J9 -> 10300 | F20: =SUIVI!S9 -> CZ6
B21: =SUIVI!Q10 -> 0 | C21: =SUIVI!R10 -> 0 | D21: =SUIVI!H10 -> HL1100A | E21: =SUIVI!J10 -> 10300 | F21: =SUIVI!S10 -> CZ7
B22: =SUIVI!Q11 -> 0 | C22: =SUIVI!R11 -> 0 | D22: =SUIVI!H11 -> HL1100A | E22: =SUIVI!J11 -> 10400 | F22: =SUIVI!S11 -> CZ52
B23: =SUIVI!Q12 -> 0 | C23: =SUIVI!R12 -> 0 | D23: =SUIVI!H12 -> HL1100A | E23: =SUIVI!J12 -> 9000 | F23: =SUIVI!S12 -> EA15
A65: Tol d'équer. EN 1090-2 D.2.7cl1 | E65: haut/larg. | F65: tolérance | H65: haut/larg. | I65: tolérance | K65: haut/larg. | L65: tolérance
A66: ausser Winkel | E66: Höhe/Breite | F66: Toleranz | H66: Höhe/Breite | I66: Toleranz | K66: Höhe/Breite | L66: Toleranz
A67: tolerance squarring | E67: wys./szer. | F67: tolerancja | H67: wys./szer. | I67: tolerancja | K67: wys./szer. | L67: tolerancja
A68: tolerancja skośności | E68: 200 | F68: 2 | H68: 600 | I68: 6 | K68: 1000 | L68: 10
E69: 300 | F69: 3 | H69: 700 | I69: 7 | K69: 1100 | L69: 11
E70: 400 | F70: 4 | H70: 800 | I70: 8
E71: 500 | F71: 5 | H71: 900 | I71: 9
A72: Tol d'équer. EN 1090-2 D.2.7cl2 | E72: haut/larg. | F72: tolérance | H72: haut/larg. | I72: tolérance | K72: haut/larg. | L72: tolérance
A73: ausser Winkel | E73: Höhe/Breite | F73: Toleranz | H73: Höhe/Breite | I73: Toleranz | K73: Höhe/Breite | L73: Toleranz
A74: tolerance squarring | E74: wys./szer. | F74: tolerancja | H74: wys./szer. | I74: tolerancja | K74: wys./szer. | L74: tolerancja
A75: tolerancja skośności | E75: 200 | F75: 0.7 | H75: 600 | I75: 2 | K75: 1000 | L75: 3.3
E76: 300 | F76: 1 | H76: 700 | I76: 2.3 | K76: 1100 | L76: 3.7
E77: 400 | F77: 1.3 | H77: 800 | I77: 2.7
E78: 500 | F78: 1.7 | H78: 900 | I78: 3
A79: Tol.d'équerre:+/-20' (0,33°) | E79: haut/larg. | F79: tolérance | H79: haut/larg. | I79: tolérance | K79: haut/larg. | L79: tolérance
A80: ausser Winkel | E80: Höhe/Breite | F80: Toleranz | H80: Höhe/Breite | I80: Toleranz | K80: Höhe/Breite | L80: Toleranz
A81: tolerance squarring | E81: wys./szer. | F81: tolerancja | H81: wys./szer. | I81: tolerancja | K81: wys./szer. | L81: tolerancja
A82: tolerancja skośności | E82: 200 | F82: 1.2 | H82: 600 | I82: 3.5 | K82: 1000 | L82: 5.8
E83: 300 | F83: 1.7 | H83: 700 | I83: 4.1 | K83: 1100 | L83: 6.4
E84: 400 | F84: 2.3 | H84: 800 | I84: 4.7
E85: 500 | F85: 2.9 | H85: 900 | I85: 5.2
A87: Remarques/Bermekungen/Remarks/Uwagi

Sheet FC-2 BIAIS VÉ
F1: =PREVI!C10 -> CIMOLAI | J1: =PREVI!C11 -> PASSERELLE DE BELVAL
A3: ArcelorMittal Belval & Differdange S.A. | F3: FICHE DE CONTRÔLE / Kontrollblatt / Check sheet | L3: SCIE / Säge / Saw | Q3: 0/+2mm
A4: Site de Differdange | I4: Protokół Kontroli | L4: Cięcie | Q4: -2/+0mm
A6: Parachèvement spécial | G6: Tol. longueur visée: | I6: +/-2mm | K6: Critère d'acceptation EN 1090-2 Tab. B.6 | Q6: +/-2mm
G7: Längentoleranz visiert +/- mm. | K7: Akzeptanzkriterien nach EN 1090-2 Tab. B.6 | Q7: +/-3mm
G8: Length tolerance refer. +/-mm | K8: Acceptance according to EN1090-2 Tab. B.6 | Q8: +/-4mm
G9: Tolerancja długości +/- mm | K9: Przyjęcie wg EN 1090-2 stół B.6 | Q9: +/-5mm
G11: Commande: | I11: =PREVI!$A$10 -> 1100633635-636 | K11: =PREVI!$A$11 -> Z128 | M11: =PREVI!$A$12 -> 1900015151-15087 | Q11: ENTRER H= LA LARGEUR DU PROFILÉ
G12: Auftrag n° /Order n° / Ziecenie n° | Q12: POUR COUPE DANS L'AILE
G14: L = | H14: A = | I14: a = | K14: b = | N14: =IF(E15,ATAN(K15/E15),"")
D15: H= | G15: =E20 -> 10300 | H15: =G15-(I15+K15) -> 10300 | J15: =IF(E15,DEGREES(N15),"") | L15: =IF(E15,DEGREES(N14),"") | N15: =IF(E15,ATAN(I15/E15),"")
A16: Date | B16: Pos | C16: Rep | D16: Profil | E16: Longueur | F16: N°laminage | G16: Longueur | H16: Longueur | I16: Biais | J16: Angle 1 (°) | K16: Biais | L16: Angle 2 (°) | M16: Contrôleur | N16: C.E.
A17: Datum | B17: Pos | C17: Pos | D17: Profil | E17: Länge Soll | F17: Walznummer | G17: Länge Ist | H17: Länge Ist | I17: Schrag | J17: Winkel 1 | K17: Schrag | L17: Winkel 1 | M17: Prüfer | N17: S.L.
A18: Date | B18: Pos | C18: Mark | D18: Section | E18: Length | F18: rolling number | G18: Length | H18: Length | I18: Slant | J18: Angle 1 | K18: Slant | L18: Angle | M18: Controller | N18: Overseer
A19: Data | B19: Poz | C19: Element | D19: Profil | E19: Długość | F19: Nr walcowania | G19: Długość | H19: Długość | I19: Ukos | J19: Kat 1 | K19: Ukos | L19: Kat 1 | M19: Kontroler | N19: C.E.
B20: =SUIVI!Q9 -> 0 | C20: =SUIVI!R9 -> 0 | D20: =SUIVI!H9 -> HL1100A | E20: =SUIVI!J9 -> 10300 | F20: =SUIVI!S9 -> CZ6
B21: =SUIVI!Q10 -> 0 | C21: =SUIVI!R10 -> 0 | D21: =SUIVI!H10 -> HL1100A | E21: =SUIVI!J10 -> 10300 | F21: =SUIVI!S10 -> CZ7
B22: =SUIVI!Q11 -> 0 | C22: =SUIVI!R11 -> 0 | D22: =SUIVI!H11 -> HL1100A | E22: =SUIVI!J11 -> 10400 | F22: =SUIVI!S11 -> CZ52
B23: =SUIVI!Q12 -> 0 | C23: =SUIVI!R12 -> 0 | D23: =SUIVI!H12 -> HL1100A | E23: =SUIVI!J12 -> 9000 | F23: =SUIVI!S12 -> EA15
A65: Tol d'équer. EN 1090-2 D.2.7cl1 | E65: haut/larg. | F65: tolérance | H65: haut/larg. | I65: tolérance | K65: haut/larg. | L65: tolérance
A66: ausser Winkel | E66: Höhe/Breite | F66: Toleranz | H66: Höhe/Breite | I66: Toleranz | K66: Höhe/Breite | L66: Toleranz
A67: tolerance squarring | E67: wys./szer. | F67: tolerancja | H67: wys./szer. | I67: tolerancja | K67: wys./szer. | L67: tolerancja
A68: tolerancja skośności | E68: 200 | F68: 2 | H68: 600 | I68: 6 | K68: 1000 | L68: 10
E69: 300 | F69: 3 | H69: 700 | I69: 7 | K69: 1100 | L69: 11
E70: 400 | F70: 4 | H70: 800 | I70: 8
E71: 500 | F71: 5 | H71: 900 | I71: 9
A72: Tol d'équer. EN 1090-2 D.2.7cl2 | E72: haut/larg. | F72: tolérance | H72: haut/larg. | I72: tolérance | K72: haut/larg. | L72: tolérance
A73: ausser Winkel | E73: Höhe/Breite | F73: Toleranz | H73: Höhe/Breite | I73: Toleranz | K73: Höhe/Breite | L73: Toleranz
A74: tolerance squarring | E74: wys./szer. | F74: tolerancja | H74: wys./szer. | I74: tolerancja | K74: wys./szer. | L74: tolerancja
A75: tolerancja skośności | E75: 200 | F75: 0.7 | H75: 600 | I75: 2 | K75: 1000 | L75: 3.3
E76: 300 | F76: 1 | H76: 700 | I76: 2.3 | K76: 1100 | L76: 3.7
E77: 400 | F77: 1.3 | H77: 800 | I77: 2.7
E78: 500 | F78: 1.7 | H78: 900 | I78: 3
A79: Tol.d'équerre:+/-20' (0,33°) | E79: haut/larg. | F79: tolérance | H79: haut/larg. | I79: tolérance | K79: haut/larg. | L79: tolérance
A80: ausser Winkel | E80: Höhe/Breite | F80: Toleranz | H80: Höhe/Breite | I80: Toleranz | K80: Höhe/Breite | L80: Toleranz
A81: tolerance squarring | E81: wys./szer. | F81: tolerancja | H81: wys./szer. | I81: tolerancja | K81: wys./szer. | L81: tolerancja
A82: tolerancja skośności | E82: 200 | F82: 1.2 | H82: 600 | I82: 3.5 | K82: 1000 | L82: 5.8
E83: 300 | F83: 1.7 | H83: 700 | I83: 4.1 | K83: 1100 | L83: 6.4
E84: 400 | F84: 2.3 | H84: 800 | I84: 4.7
E85: 500 | F85: 2.9 | H85: 900 | I85: 5.2
A87: Remarques/Bermekungen/Remarks/Uwagi

Sheet FC-2 BIAIS VÉ LG DIFFÉRENTES
F1: FICHE DE CONTRÔLE / Kontrollblatt / Check sheet | N1: SCIE / Säge / Saw
A2: ArcelorMittal Belval & Differdange S.A. | J2: Protokół Kontroli | K2: Protokół Kontroli | N2: Cięcie | R2: 0/+2mm
A3: Site de Differdange | R3: -2/+0mm
A4: Parachèvement spécial | G4: Tol. longueur visée: | J4: +/-2mm | L4: Critère d'acceptation EN 1090-2 Tab. B.6 | R4: +/-2mm
G5: Längentoleranz visiert +/- mm. | L5: Akzeptanzkriterien nach EN 1090-2 Tab. B.6 | R5: +/-3mm
G6: Length tolerance refer. +/-mm | L6: Acceptance according to EN1090-2 Tab. B.6 | R6: +/-4mm
G7: Tolerancja długości +/- mm | L7: Przyjęcie wg EN 1090-2 stół B.6 | R7: +/-5mm
G9: Commande: | J9: =PREVI!$A$10 -> 1100633635-636 | K9: =PREVI!$A$10 -> 1100633635-636 | M9: =PREVI!$A$11 -> Z128 | N9: =PREVI!A11 -> Z128 | P9: =PREVI!A12 -> 1900015151-15087 | R9: ENTRER H= LA LARGEUR DU PROFILÉ
G10: Auftrag n° /Order n° / Ziecenie n° | R10: POUR COUPE DANS L'AILE
E13: L = | G13: L = | H13: A = | I13: A = | J13: a = | K13: a = | M13: b = | N13: b =
A14: Date | B14: Pos | C14: Rep | D14: Profil | E14: Longueur | F14: N°laminage | G14: Longueur | H14: Longueur | I14: Longueur | J14: Biais | K14: Biais | L14: Angle 1 (°) | M14: Biais | N14: Biais | O14: Angle 2 (°) | P14: Contrôleur
A15: Datum | B15: Pos | C15: Pos | D15: Profil | E15: Länge Soll | F15: Walznummer | G15: Länge Ist | H15: Länge Ist | I15: Länge Soll | J15: Schrag soll | K15: Schrag ist | L15: Winkel 1 | M15: Schrag soll | N15: Schrag ist | O15: Winkel 1 | P15: Prüfer
A16: Date | B16: Pos | C16: Mark | D16: Section | E16: Length | F16: rolling number | G16: Length | H16: Length | I16: Length | J16: Slant | K16: Slant | L16: Angle 1 | M16: Slant | N16: Slant | O16: Angle | P16: Controller
A17: Data | B17: Poz | C17: Element | D17: Profil | E17: Długość | F17: Nr walcowania | G17: Długość | H17: Długość | I17: Długość | J17: Ukos | K17: Ukos | L17: Kat 1 | M17: Ukos | N17: Ukos | O17: Kat 1 | P17: Kontroler | Q17: H = | R17: FORMULE | S17: FORMULE | T17: FORMULE | U17: FORMULE
B18: =SUIVI!Q9 -> 0 | C18: =SUIVI!R9 -> 0 | D18: =SUIVI!H9 -> HL1100A | E18: =SUIVI!J9 -> 10300 | F18: =SUIVI!S9 -> CZ6 | H18: =E18-(J18+M18) -> 10000 | J18: 200 | L18: =S18 -> 11.309932 | M18: 100 | O18: =U18 -> 5.7105931 | Q18: 1000 | R18: =IF(E18,ATAN(J18/Q18),"") -> 0.19739556 | S18: =IF(E18,DEGREES(R18),"") -> 11.309932 | T18: =IF(E18,ATAN(M18/Q18),"") -> 0.099668652 | U18: =IF(E18,DEGREES(T18),"") -> 5.7105931
B19: =SUIVI!Q10 -> 0 | C19: =SUIVI!R10 -> 0 | D19: =SUIVI!H10 -> HL1100A | E19: =SUIVI!J10 -> 10300 | F19: =SUIVI!S10 -> CZ7 | H19: =E19-(J19+M19) -> 9950 | J19: 200 | L19: =S19 -> 11.309932 | M19: 150 | O19: =U19 -> 8.5307656 | Q19: 1000 | R19: =IF(E19,ATAN(J19/Q19),"") -> 0.19739556 | S19: =IF(E19,DEGREES(R19),"") -> 11.309932 | T19: =IF(E19,ATAN(M19/Q19),"") -> 0.14888995 | U19: =IF(E19,DEGREES(T19),"") -> 8.5307656
B20: =SUIVI!Q11 -> 0 | C20: =SUIVI!R11 -> 0 | D20: =SUIVI!H11 -> HL1100A | E20: =SUIVI!J11 -> 10400 | F20: =SUIVI!S11 -> CZ52 | H20: =E20-(J20+M20) -> 10050 | J20: 200 | L20: =S20 -> 11.309932 | M20: 150 | O20: =U20 -> 8.5307656 | Q20: 1000 | R20: =IF(E20,ATAN(J20/Q20),"") -> 0.19739556 | S20: =IF(E20,DEGREES(R20),"") -> 11.309932 | T20: =IF(E20,ATAN(M20/Q20),"") -> 0.14888995 | U20: =IF(E20,DEGREES(T20),"") -> 8.5307656
B21: =SUIVI!Q12 -> 0 | C21: =SUIVI!R12 -> 0 | D21: =SUIVI!H12 -> HL1100A | E21: =SUIVI!J12 -> 9000 | F21: =SUIVI!S12 -> EA15 | H21: =E21-(J21+M21) -> 8650 | J21: 200 | L21: =S21 -> 11.309932 | M21: 150 | O21: =U21 -> 8.5307656 | Q21: 1000 | R21: =IF(E21,ATAN(J21/Q21),"") -> 0.19739556 | S21: =IF(E21,DEGREES(R21),"") -> 11.309932 | T21: =IF(E21,ATAN(M21/Q21),"") -> 0.14888995 | U21: =IF(E21,DEGREES(T21),"") -> 8.5307656
B22: 0 | C22: 0 | D22: 0 | E22: 0 | H22: =E22-(J22+M22) -> -350 | J22: 200 | L22: =S22 | M22: 150 | O22: =U22 | Q22: 1000 | R22: =IF(E22,ATAN(J22/Q22),"") | S22: =IF(E22,DEGREES(R22),"") | T22: =IF(E22,ATAN(M22/Q22),"") | U22: =IF(E22,DEGREES(T22),"")
B23: 0 | C23: 0 | D23: 0 | E23: 0 | F23: 0 | H23: =E23-(J23+M23) -> -350 | J23: 200 | L23: =S23 | M23: 150 | O23: =U23 | Q23: 1000 | R23: =IF(E23,ATAN(J23/Q23),"") | S23: =IF(E23,DEGREES(R23),"") | T23: =IF(E23,ATAN(M23/Q23),"") | U23: =IF(E23,DEGREES(T23),"")
B24: 0 | C24: 0 | D24: 0 | E24: 0 | F24: 0 | H24: =E24-(J24+M24) -> 0 | L24: =S24 | O24: =U24 | Q24: 1000 | R24: =IF(E24,ATAN(J24/Q24),"") | S24: =IF(E24,DEGREES(R24),"") | T24: =IF(E24,ATAN(M24/Q24),"") | U24: =IF(E24,DEGREES(T24),"")
B25: 0 | C25: 0 | D25: 0 | E25: 0 | F25: 0 | H25: =E25-(J25+M25) -> 0 | L25: =S25 | O25: =U25 | Q25: 1000 | R25: =IF(E25,ATAN(J25/Q25),"") | S25: =IF(E25,DEGREES(R25),"") | T25: =IF(E25,ATAN(M25/Q25),"") | U25: =IF(E25,DEGREES(T25),"")
B26: 0 | C26: 0 | D26: 0 | E26: 0 | F26: 0 | H26: =E26-(J26+M26) -> 0 | L26: =S26 | O26: =U26 | Q26: 1000 | R26: =IF(E26,ATAN(J26/Q26),"") | S26: =IF(E26,DEGREES(R26),"") | T26: =IF(E26,ATAN(M26/Q26),"") | U26: =IF(E26,DEGREES(T26),"")
B27: 0 | C27: 0 | D27: 0 | E27: 0 | F27: 0 | H27: =E27-(J27+M27) -> 0 | L27: =S27 | O27: =U27 | Q27: 1000 | R27: =IF(E27,ATAN(J27/Q27),"") | S27: =IF(E27,DEGREES(R27),"") | T27: =IF(E27,ATAN(M27/Q27),"") | U27: =IF(E27,DEGREES(T27),"")
B28: 0 | C28: 0 | D28: 0 | E28: 0 | F28: 0 | H28: =E28-(J28+M28) -> 0 | L28: =S28 | O28: =U28 | Q28: 1000 | R28: =IF(E28,ATAN(J28/Q28),"") | S28: =IF(E28,DEGREES(R28),"") | T28: =IF(E28,ATAN(M28/Q28),"") | U28: =IF(E28,DEGREES(T28),"")
B29: 0 | C29: 0 | D29: 0 | E29: 0 | F29: 0 | H29: =E29-(J29+M29) -> 0 | L29: =S29 | O29: =U29 | Q29: 1000 | R29: =IF(E29,ATAN(J29/Q29),"") | S29: =IF(E29,DEGREES(R29),"") | T29: =IF(E29,ATAN(M29/Q29),"") | U29: =IF(E29,DEGREES(T29),"")
B30: 0 | C30: 0 | D30: 0 | E30: 0 | F30: 0 | H30: =E30-(J30+M30) -> 0 | L30: =S30 | O30: =U30 | Q30: 1000 | R30: =IF(E30,ATAN(J30/Q30),"") | S30: =IF(E30,DEGREES(R30),"") | T30: =IF(E30,ATAN(M30/Q30),"") | U30: =IF(E30,DEGREES(T30),"")
B31: 0 | C31: 0 | D31: 0 | E31: 0 | F31: 0 | H31: =E31-(J31+M31) -> 0 | L31: =S31 | O31: =U31 | Q31: 1000 | R31: =IF(E31,ATAN(J31/Q31),"") | S31: =IF(E31,DEGREES(R31),"") | T31: =IF(E31,ATAN(M31/Q31),"") | U31: =IF(E31,DEGREES(T31),"")
B32: 0 | C32: 0 | D32: 0 | E32: 0 | F32: 0 | H32: =E32-(J32+M32) -> 0 | L32: =S32 | O32: =U32 | Q32: 1000 | R32: =IF(E32,ATAN(J32/Q32),"") | S32: =IF(E32,DEGREES(R32),"") | T32: =IF(E32,ATAN(M32/Q32),"") | U32: =IF(E32,DEGREES(T32),"")
B33: 0 | C33: 0 | D33: 0 | E33: 0 | F33: 0 | H33: =E33-(J33+M33) -> 0 | L33: =S33 | O33: =U33 | Q33: 1000 | R33: =IF(E33,ATAN(J33/Q33),"") | S33: =IF(E33,DEGREES(R33),"") | T33: =IF(E33,ATAN(M33/Q33),"") | U33: =IF(E33,DEGREES(T33),"")
B34: 0 | C34: 0 | D34: 0 | E34: 0 | F34: 0 | H34: =E34-(J34+M34) -> 0 | L34: =S34 | O34: =U34 | Q34: 1000 | R34: =IF(E34,ATAN(J34/Q34),"") | S34: =IF(E34,DEGREES(R34),"") | T34: =IF(E34,ATAN(M34/Q34),"") | U34: =IF(E34,DEGREES(T34),"")
B35: 0 | C35: 0 | D35: 0 | E35: 0 | F35: 0 | H35: =E35-(J35+M35) -> 0 | L35: =S35 | O35: =U35 | Q35: 1000 | R35: =IF(E35,ATAN(J35/Q35),"") | S35: =IF(E35,DEGREES(R35),"") | T35: =IF(E35,ATAN(M35/Q35),"") | U35: =IF(E35,DEGREES(T35),"")
... B217: 0 | C217: 0 | D217: 0 | E217: 0 | F217: 0 | H217: =E217-(J217+M217) -> 0 | L217: =S217 | O217: =U217 | Q217: 1000 | R217: =IF(E217,ATAN(J217/Q217),"") | S217: =IF(E217,DEGREES(R217),"") | T217: =IF(E217,ATAN(M217/Q217),"") | U217: =IF(E217,DEGREES(T217),"")
E218: 0
A219: Tol d'équer. EN 1090-2 D.2.7cl1 | E219: haut/larg. | F219: tolérance | H219: haut/larg. | J219: tolérance | K219: tolérance | M219: haut/larg. | N219: haut/larg. | O219: tolérance
A220: ausser Winkel | E220: Höhe/Breite | F220: Toleranz | H220: Höhe/Breite | J220: Toleranz | K220: Toleranz | M220: Höhe/Breite | N220: Höhe/Breite | O220: Toleranz
A221: tolerance squarring | E221: wys./szer. | F221: tolerancja | H221: wys./szer. | J221: tolerancja | K221: tolerancja | M221: wys./szer. | N221: wys./szer. | O221: tolerancja
A222: tolerancja skośności | E222: 200 | F222: 2 | H222: 600 | J222: 6 | K222: 6 | M222: 1000 | N222: 1000 | O222: 10
E223: 300 | F223: 3 | H223: 700 | J223: 7 | K223: 7 | M223: 1100 | N223: 1100 | O223: 11
E224: 400 | F224: 4 | H224: 800 | J224: 8 | K224: 8
E225: 500 | F225: 5 | H225: 900 | J225: 9 | K225: 9
A226: Tol d'équer. EN 1090-2 D.2.7cl2 | E226: haut/larg. | F226: tolérance | H226: haut/larg. | J226: tolérance | K226: tolérance | M226: haut/larg. | N226: haut/larg. | O226: tolérance
A227: ausser Winkel | E227: Höhe/Breite | F227: Toleranz | H227: Höhe/Breite | J227: Toleranz | K227: Toleranz | M227: Höhe/Breite | N227: Höhe/Breite | O227: Toleranz
A228: tolerance squarring | E228: wys./szer. | F228: tolerancja | H228: wys./szer. | J228: tolerancja | K228: tolerancja | M228: wys./szer. | N228: wys./szer. | O228: tolerancja
A229: tolerancja skośności | E229: 200 | F229: 0.7 | H229: 600 | J229: 2 | K229: 2 | M229: 1000 | N229: 1000 | O229: 3.3
E230: 300 | F230: 1 | H230: 700 | J230: 2.3 | K230: 2.3 | M230: 1100 | N230: 1100 | O230: 3.7
E231: 400 | F231: 1.3 | H231: 800 | J231: 2.7 | K231: 2.7
E232: 500 | F232: 1.7 | H232: 900 | J232: 3 | K232: 3
A233: Tol.d'équerre:+/-20' (0,33°) | E233: haut/larg. | F233: tolérance | H233: haut/larg. | J233: tolérance | K233: tolérance | M233: haut/larg. | N233: haut/larg. | O233: tolérance
A234: ausser Winkel | E234: Höhe/Breite | F234: Toleranz | H234: Höhe/Breite | J234: Toleranz | K234: Toleranz | M234: Höhe/Breite | N234: Höhe/Breite | O234: Toleranz
A235: tolerance squarring | E235: wys./szer. | F235: tolerancja | H235: wys./szer. | J235: tolerancja | K235: tolerancja | M235: wys./szer. | N235: wys./szer. | O235: tolerancja
A236: tolerancja skośności | E236: 200 | F236: 1.2 | H236: 600 | J236: 3.5 | K236: 3.5 | M236: 1000 | N236: 1000 | O236: 5.8
E237: 300 | F237: 1.7 | H237: 700 | J237: 4.1 | K237: 4.1 | M237: 1100 | N237: 1100 | O237: 6.4
E238: 400 | F238: 2.3 | H238: 800 | J238: 4.7 | K238: 4.7
E239: 500 | F239: 2.9 | H239: 900 | J239: 5.2 | K239: 5.2
A241: Remarques/Bermekungen/Remarks/Uwagi

Sheet FC-ROBOT
F2: =PREVI!C10 -> CIMOLAI | J2: =PREVI!C11 -> PASSERELLE DE BELVAL
A3: ArcelorMittal Belval & Differdange S.A. | G3: Parachèvement spécial
A4: Site de Differdange
A5: FICHE DE CONTRÔLE / Kontrollblatt / Check sheet | J5: ROBOT /Roboter/Robot | P5: Règlement : DBS 918005
E6: Protokół Kontroli | K6: Robot
A7: CDE | B7: =PREVI!A10 -> 1100633635-636 | E7: =PREVI!A11 -> Z128 | G7: Plan n° | H7: =PREVI!A24 -> 0 | J7: Spécification | N7: 0/+10mm
A8: Auftrag n° | G8: Zeichen n° | J8: Vorschrift | N8: -2/+0mm | P8: +/-20' (0,33°)
A9: Order n° | G9: Plan n° | J9: Specification | N9: +/-2mm | P9: EN 1090-2 D2.7 classe 1
A10: Zlecenie n° | G10: Rys nr | J10: Specyfikacja wg | N10: +/-3mm | P10: EN 1090-2 D2.7 classe 2
A11: Tol. longueur visée: | E11: 0/+10mm | G11: Critère d'acceptation EN 1090-2 Tab. B.6 | N11: +/-4mm
A12: Längentoleranz visiert +/- mm. | G12: Akzeptanzkriterien nach EN 1090-2 Tab. B.6 | N12: +/-5mm | P12: Fascicule 66
A13: Length tolerance referred +/- mm | G13: Acceptance according to EN1090-2 Tab. B.6 | N13: 0/+100mm | P13: Livret 2.32
A14: Tolerancja długości +/- mm | G14: Przyjęcie wg EN 1090-2 stół B.6 | P14: DBS 918005
A15: Tolérance d'équerrage | E15: +/-20' (0,33°) | I15: Réception | J15: =PREVI!E8 -> 0 | P15: Exigence client
A16: Winkligkeitstol. | I16: Abnahme
A17: Tolerance squaring | I17: Receipt
A18: Tolerancja skośności | I18: Odbiór
F22: L +/-
F27: Différences/Abweichungen/difference/różnice
H28: H : Hauteur/Höhe
G29: L | H29: H : Height/wysokość
A30: Date | B30: Pos | C30: Rep | D30: Profil | E30: Longueur | F30: N°laminage | G30: longueur | H30: Parc | I30: Bureau | J30: Contrôleur | K30: C.E. | L30: Remarques
A31: Datum | B31: Pos | C31: Pos | D31: Profil | E31: Länge Soll | F31: Walznummer | G31: Länge Ist | H31: Left | I31: Right | J31: Prüfer | K31: S.L. | L31: Bemerk.
A32: Date | B32: Pos | C32: Mark | D32: Section | E32: Length | F32: rolling number | G32: Length | H32: Links | I32: Recht | J32: Controller | K32: Overseer | L32: Remarks
A33: Data | B33: Poz | C33: Element | D33: Profil | E33: Długość | F33: Nr walcowania | G33: Długość | H33: Lewo | I33: Prawo | J33: Kontroler | K33: C.E. | L33: Uwagi
B34: =SUIVI!E9 -> 1 | C34: =SUIVI!R9 -> 0 | D34: =SUIVI!H9 -> HL1100A | E34: =SUIVI!J9 -> 10300 | F34: =SUIVI!S9 -> CZ6 | M34: 1
B35: =SUIVI!E10 -> 1 | C35: =SUIVI!R10 -> 0 | D35: =SUIVI!H10 -> HL1100A | E35: =SUIVI!J10 -> 10300 | F35: =SUIVI!S10 -> CZ7 | M35: 2
B36: =SUIVI!E11 -> 9 | C36: =SUIVI!R11 -> 0 | D36: =SUIVI!H11 -> HL1100A | E36: =SUIVI!J11 -> 10400 | F36: =SUIVI!S11 -> CZ52 | M36: 3
B37: =SUIVI!E12 -> 10 | C37: =SUIVI!R12 -> 0 | D37: =SUIVI!H12 -> HL1100A | E37: =SUIVI!J12 -> 9000 | F37: =SUIVI!S12 -> EA15 | M37: 4
B38: =SUIVI!E13 -> 2 | C38: =SUIVI!R13 -> 0 | D38: =SUIVI!H13 -> HL1100A | E38: =SUIVI!J13 -> 10100 | F38: =SUIVI!S13 -> CZ9 | M38: 5
B39: =SUIVI!E14 -> 38 | C39: =SUIVI!R14 -> 0 | D39: =SUIVI!H14 -> HL1100A | E39: =SUIVI!J14 -> 10400 | F39: =SUIVI!S14 -> EC48 | M39: 6
B40: =SUIVI!E15 -> 38 | C40: =SUIVI!R15 -> 0 | D40: =SUIVI!H15 -> HL1100A | E40: =SUIVI!J15 -> 10400 | F40: =SUIVI!S15 -> EC49 | M40: 7
B41: =SUIVI!E16 -> 38 | C41: =SUIVI!R16 -> 0 | D41: =SUIVI!H16 -> HL1100A | E41: =SUIVI!J16 -> 10400 | F41: =SUIVI!S16 -> EC50 | M41: 8
B42: =SUIVI!E17 -> 38 | C42: =SUIVI!R17 -> 0 | D42: =SUIVI!H17 -> HL1100A | E42: =SUIVI!J17 -> 10400 | F42: =SUIVI!S17 -> EC51 | M42: 9
B43: =SUIVI!E18 -> 27 | C43: =SUIVI!R18 -> 0 | D43: =SUIVI!H18 -> HL1100B | E43: =SUIVI!J18 -> 5300 | F43: =SUIVI!S18 -> EC407 | M43: 10
M44: 200 | N44: RECOPIE MAXIMUM
A45: Tol.d'équerre:+/-20' (0,33°) | E45: haut/larg. | F45: tolérance | G45: haut/larg. | H45: tolérance | J45: haut/larg. | K45: tolérance
A46: ausser Winkel | E46: Höhe/Breite | F46: Toleranz | G46: Höhe/Breite | H46: Toleranz | J46: Höhe/Breite | K46: Toleranz
A47: tolerance squarring | E47: wys./szer. | F47: tolerancja | G47: wys./szer. | H47: tolerancja | J47: wys./szer. | K47: tolerancja
A48: tolerancja skośności | E48: 200 | F48: 1.2 | G48: 600 | H48: 3.5 | J48: 1000 | K48: 5.8
E49: 300 | F49: 1.7 | G49: 700 | H49: 4.1 | J49: 1100 | K49: 6.4
E50: 400 | F50: 2.3 | G50: 800 | H50: 4.7
E51: 500 | F51: 2.9 | G51: 900 | H51: 5.2
A53: Remarques/Bermekungen/Remarks/Uwagi
A56: Tol d'équer. EN 1090-2 D.2.7cl1 | E56: haut/larg. | F56: tolérance | G56: haut/larg. | H56: tolérance | J56: haut/larg. | K56: tolérance
A57: ausser Winkel | E57: Höhe/Breite | F57: Toleranz | G57: Höhe/Breite | H57: Toleranz | J57: Höhe/Breite | K57: Toleranz
A58: tolerance squarring | E58: wys./szer. | F58: tolerancja | G58: wys./szer. | H58: tolerancja | J58: wys./szer. | K58: tolerancja
A59: tolerancja skośności | E59: 200 | F59: 2 | G59: 600 | H59: 6 | J59: 1000 | K59: 10
E60: 300 | F60: 3 | G60: 700 | H60: 7 | J60: 1100 | K60: 11
E61: 400 | F61: 4 | G61: 800 | H61: 8
E62: 500 | F62: 5 | G62: 900 | H62: 9
A63: Tol d'équer. EN 1090-2 D.2.7cl2 | E63: haut/larg. | F63: tolérance | G63: haut/larg. | H63: tolérance | J63: haut/larg. | K63: tolérance
A64: ausser Winkel | E64: Höhe/Breite | F64: Toleranz | G64: Höhe/Breite | H64: Toleranz | J64: Höhe/Breite | K64: Toleranz
A65: tolerance squarring | E65: wys./szer. | F65: tolerancja | G65: wys./szer. | H65: tolerancja | J65: wys./szer. | K65: tolerancja
A66: tolerancja skośności | E66: 200 | F66: 0.7 | G66: 600 | H66: 2 | J66: 1000 | K66: 3.3
E67: 300 | F67: 1 | G67: 700 | H67: 2.3 | J67: 1100 | K67: 3.7
E68: 400 | F68: 1.3 | G68: 800 | H68: 2.7
E69: 500 | F69: 1.7 | G69: 900 | H69: 3

Sheet FT-NR  AUTO
U1: DOUBLE DRESSAGE + ÉQUERRAGE
U2: TOLÉRANCES RÉDUITES 0.7MM/M
A3: ArcelorMittal Belval & Differdange S.A. | E3: Parachèvement spécial
A4: Site de Differdange
D5: MACHINE: PRESSE NR | U5: POINÇONNER LE N° DE COULÉE
A6: Nom: | D6: Date: | I6: Poste: | L6: CE:
A7: Commande | B7: Profil | C7: Longueur | D7: Descriptif du travail | F7: Tronçon | G7: REP | H7: Nbre | I7: Nbre | J7: Numero | K7: Poste | L7: Poste | M7: Proven. | N7: Destin. | O7: L-LAM | W7: TOL -2 / + 0mm
C8: finie | H8: prévu | I8: réalisé | J8: laminage | K8: Asia | L8: R 3
A9: =PREVI!$A$10 -> 1100633635-636 | B9: =SUIVI!H9 -> HL1100A | C9: =SUIVI!J9 -> 10300 | D9: DOUBLE | H9: =IF(C9,1,0) -> 1 | I9: =IF(SUIVI!O9,1,0) -> 0 | J9: =SUIVI!M9 -> CZ6 | K9: =SUIVI!E9 -> 1 | L9: =SUIVI!G9 -> 10 | M9: Parc | N9: Scie | O9: =SUIVI!I9 -> 11100 | P9: 1 | T9: OPERATEUR | U9: CE | W9: TOL -0 / +2mm
A10: =PREVI!$A$11 -> Z128 | B10: =SUIVI!H10 -> HL1100A | C10: =SUIVI!J10 -> 10300 | D10: DRESSAGE | H10: =IF(C10,1,0) -> 1 | I10: =IF(SUIVI!O10,1,0) -> 0 | J10: =SUIVI!M10 -> CZ7 | K10: =SUIVI!E10 -> 1 | L10: =SUIVI!G10 -> 10 | M10: Parc | N10: Scie | O10: =SUIVI!I10 -> 11100 | P10: 2 | T10: GLODT | U10: VALLE
A11: =PREVI!$A$12 -> 1900015151-15087 | B11: =SUIVI!H11 -> HL1100A | C11: =SUIVI!J11 -> 10400 | D11: + | H11: =IF(C11,1,0) -> 1 | I11: =IF(SUIVI!O11,1,0) -> 0 | J11: =SUIVI!M11 -> CZ52 | K11: =SUIVI!E11 -> 9 | L11: =SUIVI!G11 -> 20 | M11: Parc | N11: Scie | O11: =SUIVI!I11 -> 11300 | P11: 3 | T11: SCHMISSER | U11: WELSCHER | W11: TOL + / - 2 mm
A12: =PREVI!$C$10 -> CIMOLAI | B12: =SUIVI!H12 -> HL1100A | C12: =SUIVI!J12 -> 9000 | D12: ÉQUERRAGE | H12: =IF(C12,1,0) -> 1 | I12: =IF(SUIVI!O12,1,0) -> 0 | J12: =SUIVI!M12 -> EA15 | K12: =SUIVI!E12 -> 10 | L12: =SUIVI!G12 -> 10 | M12: Parc | N12: Scie | O12: =SUIVI!I12 -> 9200 | P12: 4 | T12: NICOLI
A13: =PREVI!$C$11 -> PASSERELLE DE BELVAL | B13: =SUIVI!H13 -> HL1100A | C13: =SUIVI!J13 -> 10100 | H13: =IF(C13,1,0) -> 1 | I13: =IF(SUIVI!O13,1,0) -> 0 | J13: =SUIVI!M13 -> CZ9 oder10 | K13: =SUIVI!E13 -> 2 | L13: =SUIVI!G13 -> 20 | M13: Parc | N13: Scie | O13: =SUIVI!I13 -> 10700 | P13: 5 | W13: TOL -0 / +50mm
A14: N° de plans | B14: =SUIVI!H14 -> HL1100A | C14: =SUIVI!J14 -> 10400 | H14: =IF(C14,1,0) -> 1 | I14: =IF(SUIVI!O14,1,0) -> 0 | J14: =SUIVI!M14 -> EC48 | K14: =SUIVI!E14 -> 38 | L14: =SUIVI!G14 -> 20 | M14: Parc | N14: Scie | O14: =SUIVI!I14 -> 10600 | P14: 6 | U14: POSTE
A15: =PREVI!$A$24 -> 0 | B15: =SUIVI!H15 -> HL1100A | C15: =SUIVI!J15 -> 10400 | D15: DOUBLE | H15: =IF(C15,1,0) -> 1 | I15: =IF(SUIVI!O15,1,0) -> 0 | J15: =SUIVI!M15 -> EC49 | K15: =SUIVI!E15 -> 38 | L15: =SUIVI!G15 -> 20 | M15: Parc | N15: Scie | O15: =SUIVI!I15 -> 10600 | P15: 7 | U15: 06-14
A16: =PREVI!$A$25 -> 0 | B16: =SUIVI!H16 -> HL1100A | C16: =SUIVI!J16 -> 10400 | D16: DRESSAGE | H16: =IF(C16,1,0) -> 1 | I16: =IF(SUIVI!O16,1,0) -> 0 | J16: =SUIVI!M16 -> EC50 | K16: =SUIVI!E16 -> 38 | L16: =SUIVI!G16 -> 30 | M16: Parc | N16: Scie | O16: =SUIVI!I16 -> 10600 | P16: 8 | U16: 14-22
A17: =PREVI!$A$26 -> 0 | B17: =SUIVI!H17 -> HL1100A | C17: =SUIVI!J17 -> 10400 | D17: + | H17: =IF(C17,1,0) -> 1 | I17: =IF(SUIVI!O17,1,0) -> 0 | J17: =SUIVI!M17 -> EC51 | K17: =SUIVI!E17 -> 38 | L17: =SUIVI!G17 -> 30 | M17: Parc | N17: Scie | O17: =SUIVI!I17 -> 10600 | P17: 9 | U17: 22-06
A18: =$A$9 -> 1100633635-636 | B18: =SUIVI!H18 -> HL1100B | C18: =SUIVI!J18 -> 5300 | D18: ÉQUERRAGE | H18: =IF(C18,1,0) -> 1 | I18: =IF(SUIVI!O18,1,0) -> 0 | J18: =SUIVI!M18 -> EC406 oder 407 | K18: =SUIVI!E18 -> 27 | L18: =SUIVI!G18 -> 40 | M18: Parc | N18: Scie | O18: =SUIVI!I18 -> 15800 | P18: 10
A19: =$A$10 -> Z128 | P19: 11
A20: =$A$11 -> 1900015151-15087 | P20: 12
A21: =$A$12 -> CIMOLAI | P21: 13
A22: =$A$13 -> PASSERELLE DE BELVAL | P22: 14
A23: N° de plans | P23: 15 | R23: DOUBLE DRESSAGE + ÉQUERRAGE
A24: =$A$15 -> 0 | P24: 16 | R24: TOLÉRANCES RÉDUITES 0.7MM/M
A25: =$A$16 -> 0 | P25: 17
A26: =$A$17 -> 0 | P26: 18
A27: =$A$9 -> 1100633635-636 | P27: 19
A28: =$A$10 -> Z128 | B28: =SUIVI!#REF! -> #REF! | C28: =SUIVI!#REF! -> #REF! | D28: DRESSAGE | H28: =IF(C28,1,0) -> #REF! | I28: =IF(SUIVI!#REF!,1,0) -> #REF! | J28: =SUIVI!#REF! -> #REF! | K28: =SUIVI!#REF! -> #REF! | L28: =SUIVI!#REF! -> #REF! | M28: Parc | N28: Scie | O28: =SUIVI!#REF! -> #REF! | P28: 20
A29: =$A$11 -> 1900015151-15087 | B29: =SUIVI!#REF! -> #REF! | C29: =SUIVI!#REF! -> #REF! | D29: + | H29: =IF(C29,1,0) -> #REF! | I29: =IF(SUIVI!#REF!,1,0) -> #REF! | J29: =SUIVI!#REF! -> #REF! | K29: =SUIVI!#REF! -> #REF! | L29: =SUIVI!#REF! -> #REF! | M29: Parc | N29: Scie | O29: =SUIVI!#REF! -> #REF! | P29: 21
A30: =$A$12 -> CIMOLAI | B30: =SUIVI!#REF! -> #REF! | C30: =SUIVI!#REF! -> #REF! | D30: ÉQUERRAGE | H30: =IF(C30,1,0) -> #REF! | I30: =IF(SUIVI!#REF!,1,0) -> #REF! | J30: =SUIVI!#REF! -> #REF! | K30: =SUIVI!#REF! -> #REF! | L30: =SUIVI!#REF! -> #REF! | M30: Parc | N30: Scie | O30: =SUIVI!#REF! -> #REF! | P30: 22
A31: =$A$13 -> PASSERELLE DE BELVAL | B31: =SUIVI!#REF! -> #REF! | C31: =SUIVI!#REF! -> #REF! | H31: =IF(C31,1,0) -> #REF! | I31: =IF(SUIVI!#REF!,1,0) -> #REF! | J31: =SUIVI!#REF! -> #REF! | K31: =SUIVI!#REF! -> #REF! | L31: =SUIVI!#REF! -> #REF! | M31: Parc | N31: Scie | O31: =SUIVI!#REF! -> #REF! | P31: 23
A32: N° de plans | B32: =SUIVI!#REF! -> #REF! | C32: =SUIVI!#REF! -> #REF! | H32: =IF(C32,1,0) -> #REF! | I32: =IF(SUIVI!#REF!,1,0) -> #REF! | J32: =SUIVI!#REF! -> #REF! | K32: =SUIVI!#REF! -> #REF! | L32: =SUIVI!#REF! -> #REF! | M32: Parc | N32: Scie | O32: =SUIVI!#REF! -> #REF! | P32: 24
A33: =$A$15 -> 0 | B33: =SUIVI!#REF! -> #REF! | C33: =SUIVI!#REF! -> #REF! | D33: DOUBLE | H33: =IF(C33,1,0) -> #REF! | I33: =IF(SUIVI!#REF!,1,0) -> #REF! | J33: =SUIVI!#REF! -> #REF! | K33: =SUIVI!#REF! -> #REF! | L33: =SUIVI!#REF! -> #REF! | M33: Parc | N33: Scie | O33: =SUIVI!#REF! -> #REF! | P33: 25
A34: =$A$16 -> 0 | B34: =SUIVI!#REF! -> #REF! | C34: =SUIVI!#REF! -> #REF! | D34: DRESSAGE | H34: =IF(C34,1,0) -> #REF! | I34: =IF(SUIVI!#REF!,1,0) -> #REF! | J34: =SUIVI!#REF! -> #REF! | K34: =SUIVI!#REF! -> #REF! | L34: =SUIVI!#REF! -> #REF! | M34: Parc | N34: Scie | O34: =SUIVI!#REF! -> #REF! | P34: 26
A35: =$A$17 -> 0 | B35: =SUIVI!#REF! -> #REF! | C35: =SUIVI!#REF! -> #REF! | D35: + | H35: =IF(C35,1,0) -> #REF! | I35: =IF(SUIVI!#REF!,1,0) -> #REF! | J35: =SUIVI!#REF! -> #REF! | K35: =SUIVI!#REF! -> #REF! | L35: =SUIVI!#REF! -> #REF! | M35: Parc | N35: Scie | O35: =SUIVI!#REF! -> #REF! | P35: 27
A36: =$A$9 -> 1100633635-636 | B36: =SUIVI!#REF! -> #REF! | C36: =SUIVI!#REF! -> #REF! | D36: ÉQUERRAGE | H36: =IF(C36,1,0) -> #REF! | I36: =IF(SUIVI!#REF!,1,0) -> #REF! | J36: =SUIVI!#REF! -> #REF! | K36: =SUIVI!#REF! -> #REF! | L36: =SUIVI!#REF! -> #REF! | M36: Parc | N36: Scie | O36: =SUIVI!#REF! -> #REF! | P36: 28
A37: =$A$10 -> Z128 | B37: =SUIVI!#REF! -> #REF! | C37: =SUIVI!#REF! -> #REF! | H37: =IF(C37,1,0) -> #REF! | I37: =IF(SUIVI!#REF!,1,0) -> #REF! | J37: =SUIVI!#REF! -> #REF! | K37: =SUIVI!#REF! -> #REF! | L37: =SUIVI!#REF! -> #REF! | M37: Parc | N37: Scie | O37: =SUIVI!#REF! -> #REF! | P37: 29
A38: =$A$11 -> 1900015151-15087 | B38: =SUIVI!#REF! -> #REF! | C38: =SUIVI!#REF! -> #REF! | H38: =IF(C38,1,0) -> #REF! | I38: =IF(SUIVI!#REF!,1,0) -> #REF! | J38: =SUIVI!#REF! -> #REF! | K38: =SUIVI!#REF! -> #REF! | L38: =SUIVI!#REF! -> #REF! | M38: Parc | N38: Scie | O38: =SUIVI!#REF! -> #REF! | P38: 30
A39: =$A$12 -> CIMOLAI | B39: =SUIVI!#REF! -> #REF! | C39: =SUIVI!#REF! -> #REF! | D39: DOUBLE | H39: =IF(C39,1,0) -> #REF! | I39: =IF(SUIVI!#REF!,1,0) -> #REF! | J39: =SUIVI!#REF! -> #REF! | K39: =SUIVI!#REF! -> #REF! | L39: =SUIVI!#REF! -> #REF! | M39: Parc | N39: Scie | O39: =SUIVI!#REF! -> #REF! | P39: 31
A40: =$A$13 -> PASSERELLE DE BELVAL | B40: =SUIVI!#REF! -> #REF! | C40: =SUIVI!#REF! -> #REF! | D40: DRESSAGE | H40: =IF(C40,1,0) -> #REF! | I40: =IF(SUIVI!#REF!,1,0) -> #REF! | J40: =SUIVI!#REF! -> #REF! | K40: =SUIVI!#REF! -> #REF! | L40: =SUIVI!#REF! -> #REF! | M40: Parc | N40: Scie | O40: =SUIVI!#REF! -> #REF! | P40: 32
A41: N° de plans | B41: =SUIVI!#REF! -> #REF! | C41: =SUIVI!#REF! -> #REF! | D41: + | H41: =IF(C41,1,0) -> #REF! | I41: =IF(SUIVI!#REF!,1,0) -> #REF! | J41: =SUIVI!#REF! -> #REF! | K41: =SUIVI!#REF! -> #REF! | L41: =SUIVI!#REF! -> #REF! | M41: Parc | N41: Scie | O41: =SUIVI!#REF! -> #REF! | P41: 33
A42: =$A$15 -> 0 | B42: =SUIVI!#REF! -> #REF! | C42: =SUIVI!#REF! -> #REF! | D42: ÉQUERRAGE | H42: =IF(C42,1,0) -> #REF! | I42: =IF(SUIVI!#REF!,1,0) -> #REF! | J42: =SUIVI!#REF! -> #REF! | K42: =SUIVI!#REF! -> #REF! | L42: =SUIVI!#REF! -> #REF! | M42: Parc | N42: Scie | O42: =SUIVI!#REF! -> #REF! | P42: 34
A43: =$A$16 -> 0 | B43: =SUIVI!#REF! -> #REF! | C43: =SUIVI!#REF! -> #REF! | H43: =IF(C43,1,0) -> #REF! | I43: =IF(SUIVI!#REF!,1,0) -> #REF! | J43: =SUIVI!#REF! -> #REF! | K43: =SUIVI!#REF! -> #REF! | L43: =SUIVI!#REF! -> #REF! | M43: Parc | N43: Scie | O43: =SUIVI!#REF! -> #REF! | P43: 35
A44: =$A$17 -> 0 | B44: =SUIVI!#REF! -> #REF! | C44: =SUIVI!#REF! -> #REF! | H44: =IF(C44,1,0) -> #REF! | I44: =IF(SUIVI!#REF!,1,0) -> #REF! | J44: =SUIVI!#REF! -> #REF! | K44: =SUIVI!#REF! -> #REF! | L44: =SUIVI!#REF! -> #REF! | M44: Parc | N44: Scie | O44: =SUIVI!#REF! -> #REF! | P44: 36
A45: =$A$9 -> 1100633635-636 | B45: =SUIVI!#REF! -> #REF! | C45: =SUIVI!#REF! -> #REF! | D45: DOUBLE | H45: =IF(C45,1,0) -> #REF! | I45: =IF(SUIVI!#REF!,1,0) -> #REF! | J45: =SUIVI!#REF! -> #REF! | K45: =SUIVI!#REF! -> #REF! | L45: =SUIVI!#REF! -> #REF! | M45: Parc | N45: Scie | O45: =SUIVI!#REF! -> #REF! | P45: 37
A46: =$A$10 -> Z128 | B46: =SUIVI!#REF! -> #REF! | C46: =SUIVI!#REF! -> #REF! | D46: DRESSAGE | H46: =IF(C46,1,0) -> #REF! | I46: =IF(SUIVI!#REF!,1,0) -> #REF! | J46: =SUIVI!#REF! -> #REF! | K46: =SUIVI!#REF! -> #REF! | L46: =SUIVI!#REF! -> #REF! | M46: Parc | N46: Scie | O46: =SUIVI!#REF! -> #REF! | P46: 38
A47: =$A$11 -> 1900015151-15087 | B47: =SUIVI!#REF! -> #REF! | C47: =SUIVI!#REF! -> #REF! | D47: + | H47: =IF(C47,1,0) -> #REF! | I47: =IF(SUIVI!#REF!,1,0) -> #REF! | J47: =SUIVI!#REF! -> #REF! | K47: =SUIVI!#REF! -> #REF! | L47: =SUIVI!#REF! -> #REF! | M47: Parc | N47: Scie | O47: =SUIVI!#REF! -> #REF! | P47: 39
A48: =$A$12 -> CIMOLAI | B48: =SUIVI!#REF! -> #REF! | C48: =SUIVI!#REF! -> #REF! | D48: ÉQUERRAGE | H48: =IF(C48,1,0) -> #REF! | I48: =IF(SUIVI!#REF!,1,0) -> #REF! | J48: =SUIVI!#REF! -> #REF! | K48: =SUIVI!#REF! -> #REF! | L48: =SUIVI!#REF! -> #REF! | M48: Parc | N48: Scie | O48: =SUIVI!#REF! -> #REF! | P48: 40
A49: =$A$13 -> PASSERELLE DE BELVAL | B49: =SUIVI!#REF! -> #REF! | C49: =SUIVI!#REF! -> #REF! | H49: =IF(C49,1,0) -> #REF! | I49: =IF(SUIVI!#REF!,1,0) -> #REF! | J49: =SUIVI!#REF! -> #REF! | K49: =SUIVI!#REF! -> #REF! | L49: =SUIVI!#REF! -> #REF! | M49: Parc | N49: Scie | O49: =SUIVI!#REF! -> #REF! | P49: 41
A50: N° de plans | B50: =SUIVI!#REF! -> #REF! | C50: =SUIVI!#REF! -> #REF! | H50: =IF(C50,1,0) -> #REF! | I50: =IF(SUIVI!#REF!,1,0) -> #REF! | J50: =SUIVI!#REF! -> #REF! | K50: =SUIVI!#REF! -> #REF! | L50: =SUIVI!#REF! -> #REF! | M50: Parc | N50: Scie | O50: =SUIVI!#REF! -> #REF! | P50: 42
A51: =$A$15 -> 0 | B51: =SUIVI!#REF! -> #REF! | C51: =SUIVI!#REF! -> #REF! | D51: DOUBLE | H51: =IF(C51,1,0) -> #REF! | I51: =IF(SUIVI!#REF!,1,0) -> #REF! | J51: =SUIVI!#REF! -> #REF! | K51: =SUIVI!#REF! -> #REF! | L51: =SUIVI!#REF! -> #REF! | M51: Parc | N51: Scie | O51: =SUIVI!#REF! -> #REF! | P51: 43
A52: =$A$16 -> 0 | B52: =SUIVI!#REF! -> #REF! | C52: =SUIVI!#REF! -> #REF! | D52: DRESSAGE | H52: =IF(C52,1,0) -> #REF! | I52: =IF(SUIVI!#REF!,1,0) -> #REF! | J52: =SUIVI!#REF! -> #REF! | K52: =SUIVI!#REF! -> #REF! | L52: =SUIVI!#REF! -> #REF! | M52: Parc | N52: Scie | O52: =SUIVI!#REF! -> #REF! | P52: 44
A53: =$A$17 -> 0 | B53: =SUIVI!#REF! -> #REF! | C53: =SUIVI!#REF! -> #REF! | D53: + | H53: =IF(C53,1,0) -> #REF! | I53: =IF(SUIVI!#REF!,1,0) -> #REF! | J53: =SUIVI!#REF! -> #REF! | K53: =SUIVI!#REF! -> #REF! | L53: =SUIVI!#REF! -> #REF! | M53: Parc | N53: Scie | O53: =SUIVI!#REF! -> #REF! | P53: 45
A54: =$A$9 -> 1100633635-636 | B54: =SUIVI!#REF! -> #REF! | C54: =SUIVI!#REF! -> #REF! | D54: ÉQUERRAGE | H54: =IF(C54,1,0) -> #REF! | I54: =IF(SUIVI!#REF!,1,0) -> #REF! | J54: =SUIVI!#REF! -> #REF! | K54: =SUIVI!#REF! -> #REF! | L54: =SUIVI!#REF! -> #REF! | M54: Parc | N54: Scie | O54: =SUIVI!#REF! -> #REF! | P54: 46
A55: =$A$10 -> Z128 | B55: =SUIVI!#REF! -> #REF! | C55: =SUIVI!#REF! -> #REF! | H55: =IF(C55,1,0) -> #REF! | I55: =IF(SUIVI!#REF!,1,0) -> #REF! | J55: =SUIVI!#REF! -> #REF! | K55: =SUIVI!#REF! -> #REF! | L55: =SUIVI!#REF! -> #REF! | M55: Parc | N55: Scie | O55: =SUIVI!#REF! -> #REF! | P55: 47
A56: =$A$11 -> 1900015151-15087 | B56: =SUIVI!#REF! -> #REF! | C56: =SUIVI!#REF! -> #REF! | H56: =IF(C56,1,0) -> #REF! | I56: =IF(SUIVI!#REF!,1,0) -> #REF! | J56: =SUIVI!#REF! -> #REF! | K56: =SUIVI!#REF! -> #REF! | L56: =SUIVI!#REF! -> #REF! | M56: Parc | N56: Scie | O56: =SUIVI!#REF! -> #REF! | P56: 48
A57: =$A$12 -> CIMOLAI | B57: =SUIVI!#REF! -> #REF! | C57: =SUIVI!#REF! -> #REF! | D57: DOUBLE | H57: =IF(C57,1,0) -> #REF! | I57: =IF(SUIVI!#REF!,1,0) -> #REF! | J57: =SUIVI!#REF! -> #REF! | K57: =SUIVI!#REF! -> #REF! | L57: =SUIVI!#REF! -> #REF! | M57: Parc | N57: Scie | O57: =SUIVI!#REF! -> #REF! | P57: 49
A58: =$A$13 -> PASSERELLE DE BELVAL | B58: =SUIVI!#REF! -> #REF! | C58: =SUIVI!#REF! -> #REF! | D58: DRESSAGE | H58: =IF(C58,1,0) -> #REF! | I58: =IF(SUIVI!#REF!,1,0) -> #REF! | J58: =SUIVI!#REF! -> #REF! | K58: =SUIVI!#REF! -> #REF! | L58: =SUIVI!#REF! -> #REF! | M58: Parc | N58: Scie | O58: =SUIVI!#REF! -> #REF! | P58: 50
A59: N° de plans | B59: =SUIVI!#REF! -> #REF! | C59: =SUIVI!#REF! -> #REF! | D59: + | H59: =IF(C59,1,0) -> #REF! | I59: =IF(SUIVI!#REF!,1,0) -> #REF! | J59: =SUIVI!#REF! -> #REF! | K59: =SUIVI!#REF! -> #REF! | L59: =SUIVI!#REF! -> #REF! | M59: Parc | N59: Scie | O59: =SUIVI!#REF! -> #REF! | P59: 51
A60: =$A$15 -> 0 | B60: =SUIVI!#REF! -> #REF! | C60: =SUIVI!#REF! -> #REF! | D60: ÉQUERRAGE | H60: =IF(C60,1,0) -> #REF! | I60: =IF(SUIVI!#REF!,1,0) -> #REF! | J60: =SUIVI!#REF! -> #REF! | K60: =SUIVI!#REF! -> #REF! | L60: =SUIVI!#REF! -> #REF! | M60: Parc | N60: Scie | O60: =SUIVI!#REF! -> #REF! | P60: 52
A61: =$A$16 -> 0 | B61: =SUIVI!#REF! -> #REF! | C61: =SUIVI!#REF! -> #REF! | H61: =IF(C61,1,0) -> #REF! | I61: =IF(SUIVI!#REF!,1,0) -> #REF! | J61: =SUIVI!#REF! -> #REF! | K61: =SUIVI!#REF! -> #REF! | L61: =SUIVI!#REF! -> #REF! | M61: Parc | N61: Scie | O61: =SUIVI!#REF! -> #REF! | P61: 53
A62: =$A$17 -> 0 | B62: =SUIVI!#REF! -> #REF! | C62: =SUIVI!#REF! -> #REF! | H62: =IF(C62,1,0) -> #REF! | I62: =IF(SUIVI!#REF!,1,0) -> #REF! | J62: =SUIVI!#REF! -> #REF! | K62: =SUIVI!#REF! -> #REF! | L62: =SUIVI!#REF! -> #REF! | M62: Parc | N62: Scie | O62: =SUIVI!#REF! -> #REF! | P62: 54
A63: =$A$9 -> 1100633635-636 | B63: =SUIVI!#REF! -> #REF! | C63: =SUIVI!#REF! -> #REF! | D63: DOUBLE | H63: =IF(C63,1,0) -> #REF! | I63: =IF(SUIVI!#REF!,1,0) -> #REF! | J63: =SUIVI!#REF! -> #REF! | K63: =SUIVI!#REF! -> #REF! | L63: =SUIVI!#REF! -> #REF! | M63: Parc | N63: Scie | O63: =SUIVI!#REF! -> #REF! | P63: 55
A64: =$A$10 -> Z128 | B64: =SUIVI!#REF! -> #REF! | C64: =SUIVI!#REF! -> #REF! | D64: DRESSAGE | H64: =IF(C64,1,0) -> #REF! | I64: =IF(SUIVI!#REF!,1,0) -> #REF! | J64: =SUIVI!#REF! -> #REF! | K64: =SUIVI!#REF! -> #REF! | L64: =SUIVI!#REF! -> #REF! | M64: Parc | N64: Scie | O64: =SUIVI!#REF! -> #REF! | P64: 56
A65: =$A$11 -> 1900015151-15087 | B65: =SUIVI!#REF! -> #REF! | C65: =SUIVI!#REF! -> #REF! | D65: + | H65: =IF(C65,1,0) -> #REF! | I65: =IF(SUIVI!#REF!,1,0) -> #REF! | J65: =SUIVI!#REF! -> #REF! | K65: =SUIVI!#REF! -> #REF! | L65: =SUIVI!#REF! -> #REF! | M65: Parc | N65: Scie | O65: =SUIVI!#REF! -> #REF! | P65: 57
A66: =$A$12 -> CIMOLAI | B66: =SUIVI!#REF! -> #REF! | C66: =SUIVI!#REF! -> #REF! | D66: ÉQUERRAGE | H66: =IF(C66,1,0) -> #REF! | I66: =IF(SUIVI!#REF!,1,0) -> #REF! | J66: =SUIVI!#REF! -> #REF! | K66: =SUIVI!#REF! -> #REF! | L66: =SUIVI!#REF! -> #REF! | M66: Parc | N66: Scie | O66: =SUIVI!#REF! -> #REF! | P66: 58
A67: =$A$13 -> PASSERELLE DE BELVAL | B67: =SUIVI!#REF! -> #REF! | C67: =SUIVI!#REF! -> #REF! | H67: =IF(C67,1,0) -> #REF! | I67: =IF(SUIVI!#REF!,1,0) -> #REF! | J67: =SUIVI!#REF! -> #REF! | K67: =SUIVI!#REF! -> #REF! | L67: =SUIVI!#REF! -> #REF! | M67: Parc | N67: Scie | O67: =SUIVI!#REF! -> #REF! | P67: 59
A68: N° de plans | B68: =SUIVI!#REF! -> #REF! | C68: =SUIVI!#REF! -> #REF! | H68: =IF(C68,1,0) -> #REF! | I68: =IF(SUIVI!#REF!,1,0) -> #REF! | J68: =SUIVI!#REF! -> #REF! | K68: =SUIVI!#REF! -> #REF! | L68: =SUIVI!#REF! -> #REF! | M68: Parc | N68: Scie | O68: =SUIVI!#REF! -> #REF! | P68: 60
A69: =$A$15 -> 0 | B69: =SUIVI!#REF! -> #REF! | C69: =SUIVI!#REF! -> #REF! | D69: DOUBLE | H69: =IF(C69,1,0) -> #REF! | I69: =IF(SUIVI!#REF!,1,0) -> #REF! | J69: =SUIVI!#REF! -> #REF! | K69: =SUIVI!#REF! -> #REF! | L69: =SUIVI!#REF! -> #REF! | M69: Parc | N69: Scie | O69: =SUIVI!#REF! -> #REF! | P69: 61
A70: =$A$16 -> 0 | B70: =SUIVI!#REF! -> #REF! | C70: =SUIVI!#REF! -> #REF! | D70: DRESSAGE | H70: =IF(C70,1,0) -> #REF! | I70: =IF(SUIVI!#REF!,1,0) -> #REF! | J70: =SUIVI!#REF! -> #REF! | K70: =SUIVI!#REF! -> #REF! | L70: =SUIVI!#REF! -> #REF! | M70: Parc | N70: Scie | O70: =SUIVI!#REF! -> #REF! | P70: 62
A71: =$A$17 -> 0 | B71: =SUIVI!#REF! -> #REF! | C71: =SUIVI!#REF! -> #REF! | D71: + | H71: =IF(C71,1,0) -> #REF! | I71: =IF(SUIVI!#REF!,1,0) -> #REF! | J71: =SUIVI!#REF! -> #REF! | K71: =SUIVI!#REF! -> #REF! | L71: =SUIVI!#REF! -> #REF! | M71: Parc | N71: Scie | O71: =SUIVI!#REF! -> #REF! | P71: 63
A72: =$A$9 -> 1100633635-636 | B72: =SUIVI!#REF! -> #REF! | C72: =SUIVI!#REF! -> #REF! | D72: ÉQUERRAGE | H72: =IF(C72,1,0) -> #REF! | I72: =IF(SUIVI!#REF!,1,0) -> #REF! | J72: =SUIVI!#REF! -> #REF! | K72: =SUIVI!#REF! -> #REF! | L72: =SUIVI!#REF! -> #REF! | M72: Parc | N72: Scie | O72: =SUIVI!#REF! -> #REF! | P72: 64
A73: =$A$10 -> Z128 | B73: =SUIVI!#REF! -> #REF! | C73: =SUIVI!#REF! -> #REF! | H73: =IF(C73,1,0) -> #REF! | I73: =IF(SUIVI!#REF!,1,0) -> #REF! | J73: =SUIVI!#REF! -> #REF! | K73: =SUIVI!#REF! -> #REF! | L73: =SUIVI!#REF! -> #REF! | M73: Parc | N73: Scie | O73: =SUIVI!#REF! -> #REF! | P73: 65
A74: =$A$11 -> 1900015151-15087 | B74: =SUIVI!#REF! -> #REF! | C74: =SUIVI!#REF! -> #REF! | H74: =IF(C74,1,0) -> #REF! | I74: =IF(SUIVI!#REF!,1,0) -> #REF! | J74: =SUIVI!#REF! -> #REF! | K74: =SUIVI!#REF! -> #REF! | L74: =SUIVI!#REF! -> #REF! | M74: Parc | N74: Scie | O74: =SUIVI!#REF! -> #REF! | P74: 66
A75: =$A$12 -> CIMOLAI | B75: =SUIVI!#REF! -> #REF! | C75: =SUIVI!#REF! -> #REF! | D75: DOUBLE | H75: =IF(C75,1,0) -> #REF! | I75: =IF(SUIVI!#REF!,1,0) -> #REF! | J75: =SUIVI!#REF! -> #REF! | K75: =SUIVI!#REF! -> #REF! | L75: =SUIVI!#REF! -> #REF! | M75: Parc | N75: Scie | O75: =SUIVI!#REF! -> #REF! | P75: 67
A76: =$A$13 -> PASSERELLE DE BELVAL | B76: =SUIVI!#REF! -> #REF! | C76: =SUIVI!#REF! -> #REF! | D76: DRESSAGE | H76: =IF(C76,1,0) -> #REF! | I76: =IF(SUIVI!#REF!,1,0) -> #REF! | J76: =SUIVI!#REF! -> #REF! | K76: =SUIVI!#REF! -> #REF! | L76: =SUIVI!#REF! -> #REF! | M76: Parc | N76: Scie | O76: =SUIVI!#REF! -> #REF! | P76: 68
A77: N° de plans | B77: =SUIVI!#REF! -> #REF! | C77: =SUIVI!#REF! -> #REF! | D77: + | H77: =IF(C77,1,0) -> #REF! | I77: =IF(SUIVI!#REF!,1,0) -> #REF! | J77: =SUIVI!#REF! -> #REF! | K77: =SUIVI!#REF! -> #REF! | L77: =SUIVI!#REF! -> #REF! | M77: Parc | N77: Scie | O77: =SUIVI!#REF! -> #REF! | P77: 69
A78: =$A$15 -> 0 | B78: =SUIVI!#REF! -> #REF! | C78: =SUIVI!#REF! -> #REF! | D78: ÉQUERRAGE | H78: =IF(C78,1,0) -> #REF! | I78: =IF(SUIVI!#REF!,1,0) -> #REF! | J78: =SUIVI!#REF! -> #REF! | K78: =SUIVI!#REF! -> #REF! | L78: =SUIVI!#REF! -> #REF! | M78: Parc | N78: Scie | O78: =SUIVI!#REF! -> #REF! | P78: 70
A79: =$A$16 -> 0 | B79: =SUIVI!#REF! -> #REF! | C79: =SUIVI!#REF! -> #REF! | H79: =IF(C79,1,0) -> #REF! | I79: =IF(SUIVI!#REF!,1,0) -> #REF! | J79: =SUIVI!#REF! -> #REF! | K79: =SUIVI!#REF! -> #REF! | L79: =SUIVI!#REF! -> #REF! | M79: Parc | N79: Scie | O79: =SUIVI!#REF! -> #REF! | P79: 71
A80: =$A$17 -> 0 | B80: =SUIVI!#REF! -> #REF! | C80: =SUIVI!#REF! -> #REF! | H80: =IF(C80,1,0) -> #REF! | I80: =IF(SUIVI!#REF!,1,0) -> #REF! | J80: =SUIVI!#REF! -> #REF! | K80: =SUIVI!#REF! -> #REF! | L80: =SUIVI!#REF! -> #REF! | M80: Parc | N80: Scie | O80: =SUIVI!#REF! -> #REF! | P80: 72
A81: =$A$9 -> 1100633635-636 | B81: =SUIVI!#REF! -> #REF! | C81: =SUIVI!#REF! -> #REF! | D81: DOUBLE | H81: =IF(C81,1,0) -> #REF! | I81: =IF(SUIVI!#REF!,1,0) -> #REF! | J81: =SUIVI!#REF! -> #REF! | K81: =SUIVI!#REF! -> #REF! | L81: =SUIVI!#REF! -> #REF! | M81: Parc | N81: Scie | O81: =SUIVI!#REF! -> #REF! | P81: 73
A82: =$A$10 -> Z128 | B82: =SUIVI!#REF! -> #REF! | C82: =SUIVI!#REF! -> #REF! | D82: DRESSAGE | H82: =IF(C82,1,0) -> #REF! | I82: =IF(SUIVI!#REF!,1,0) -> #REF! | J82: =SUIVI!#REF! -> #REF! | K82: =SUIVI!#REF! -> #REF! | L82: =SUIVI!#REF! -> #REF! | M82: Parc | N82: Scie | O82: =SUIVI!#REF! -> #REF! | P82: 74
A83: =$A$11 -> 1900015151-15087 | B83: =SUIVI!#REF! -> #REF! | C83: =SUIVI!#REF! -> #REF! | D83: + | H83: =IF(C83,1,0) -> #REF! | I83: =IF(SUIVI!#REF!,1,0) -> #REF! | J83: =SUIVI!#REF! -> #REF! | K83: =SUIVI!#REF! -> #REF! | L83: =SUIVI!#REF! -> #REF! | M83: Parc | N83: Scie | O83: =SUIVI!#REF! -> #REF! | P83: 75
A84: =$A$12 -> CIMOLAI | B84: =SUIVI!#REF! -> #REF! | C84: =SUIVI!#REF! -> #REF! | D84: ÉQUERRAGE | H84: =IF(C84,1,0) -> #REF! | I84: =IF(SUIVI!#REF!,1,0) -> #REF! | J84: =SUIVI!#REF! -> #REF! | K84: =SUIVI!#REF! -> #REF! | L84: =SUIVI!#REF! -> #REF! | M84: Parc | N84: Scie | O84: =SUIVI!#REF! -> #REF! | P84: 76
A85: =$A$13 -> PASSERELLE DE BELVAL | B85: =SUIVI!#REF! -> #REF! | C85: =SUIVI!#REF! -> #REF! | H85: =IF(C85,1,0) -> #REF! | I85: =IF(SUIVI!#REF!,1,0) -> #REF! | J85: =SUIVI!#REF! -> #REF! | K85: =SUIVI!#REF! -> #REF! | L85: =SUIVI!#REF! -> #REF! | M85: Parc | N85: Scie | O85: =SUIVI!#REF! -> #REF! | P85: 77
A86: N° de plans | B86: =SUIVI!#REF! -> #REF! | C86: =SUIVI!#REF! -> #REF! | H86: =IF(C86,1,0) -> #REF! | I86: =IF(SUIVI!#REF!,1,0) -> #REF! | J86: =SUIVI!#REF! -> #REF! | K86: =SUIVI!#REF! -> #REF! | L86: =SUIVI!#REF! -> #REF! | M86: Parc | N86: Scie | O86: =SUIVI!#REF! -> #REF! | P86: 78
A87: =$A$15 -> 0 | B87: =SUIVI!#REF! -> #REF! | C87: =SUIVI!#REF! -> #REF! | D87: DOUBLE | H87: =IF(C87,1,0) -> #REF! | I87: =IF(SUIVI!#REF!,1,0) -> #REF! | J87: =SUIVI!#REF! -> #REF! | K87: =SUIVI!#REF! -> #REF! | L87: =SUIVI!#REF! -> #REF! | M87: Parc | N87: Scie | O87: =SUIVI!#REF! -> #REF! | P87: 79
A88: =$A$16 -> 0 | B88: =SUIVI!#REF! -> #REF! | C88: =SUIVI!#REF! -> #REF! | D88: DRESSAGE | H88: =IF(C88,1,0) -> #REF! | I88: =IF(SUIVI!#REF!,1,0) -> #REF! | J88: =SUIVI!#REF! -> #REF! | K88: =SUIVI!#REF! -> #REF! | L88: =SUIVI!#REF! -> #REF! | M88: Parc | N88: Scie | O88: =SUIVI!#REF! -> #REF! | P88: 80
A89: =$A$17 -> 0 | B89: =SUIVI!#REF! -> #REF! | C89: =SUIVI!#REF! -> #REF! | D89: + | H89: =IF(C89,1,0) -> #REF! | I89: =IF(SUIVI!#REF!,1,0) -> #REF! | J89: =SUIVI!#REF! -> #REF! | K89: =SUIVI!#REF! -> #REF! | L89: =SUIVI!#REF! -> #REF! | M89: Parc | N89: Scie | O89: =SUIVI!#REF! -> #REF! | P89: 81
A90: =$A$9 -> 1100633635-636 | B90: =SUIVI!#REF! -> #REF! | C90: =SUIVI!#REF! -> #REF! | D90: ÉQUERRAGE | H90: =IF(C90,1,0) -> #REF! | I90: =IF(SUIVI!#REF!,1,0) -> #REF! | J90: =SUIVI!#REF! -> #REF! | K90: =SUIVI!#REF! -> #REF! | L90: =SUIVI!#REF! -> #REF! | M90: Parc | N90: Scie | O90: =SUIVI!#REF! -> #REF! | P90: 82
A91: =$A$10 -> Z128 | B91: =SUIVI!#REF! -> #REF! | C91: =SUIVI!#REF! -> #REF! | H91: =IF(C91,1,0) -> #REF! | I91: =IF(SUIVI!#REF!,1,0) -> #REF! | J91: =SUIVI!#REF! -> #REF! | K91: =SUIVI!#REF! -> #REF! | L91: =SUIVI!#REF! -> #REF! | M91: Parc | N91: Scie | O91: =SUIVI!#REF! -> #REF! | P91: 83
A92: =$A$11 -> 1900015151-15087 | B92: =SUIVI!#REF! -> #REF! | C92: =SUIVI!#REF! -> #REF! | H92: =IF(C92,1,0) -> #REF! | I92: =IF(SUIVI!#REF!,1,0) -> #REF! | J92: =SUIVI!#REF! -> #REF! | K92: =SUIVI!#REF! -> #REF! | L92: =SUIVI!#REF! -> #REF! | M92: Parc | N92: Scie | O92: =SUIVI!#REF! -> #REF! | P92: 84
A93: =$A$12 -> CIMOLAI | B93: =SUIVI!#REF! -> #REF! | C93: =SUIVI!#REF! -> #REF! | D93: DOUBLE | H93: =IF(C93,1,0) -> #REF! | I93: =IF(SUIVI!#REF!,1,0) -> #REF! | J93: =SUIVI!#REF! -> #REF! | K93: =SUIVI!#REF! -> #REF! | L93: =SUIVI!#REF! -> #REF! | M93: Parc | N93: Scie | O93: =SUIVI!#REF! -> #REF! | P93: 85
A94: =$A$13 -> PASSERELLE DE BELVAL | B94: =SUIVI!#REF! -> #REF! | C94: =SUIVI!#REF! -> #REF! | D94: DRESSAGE | H94: =IF(C94,1,0) -> #REF! | I94: =IF(SUIVI!#REF!,1,0) -> #REF! | J94: =SUIVI!#REF! -> #REF! | K94: =SUIVI!#REF! -> #REF! | L94: =SUIVI!#REF! -> #REF! | M94: Parc | N94: Scie | O94: =SUIVI!#REF! -> #REF! | P94: 86
A95: N° de plans | B95: =SUIVI!#REF! -> #REF! | C95: =SUIVI!#REF! -> #REF! | D95: + | H95: =IF(C95,1,0) -> #REF! | I95: =IF(SUIVI!#REF!,1,0) -> #REF! | J95: =SUIVI!#REF! -> #REF! | K95: =SUIVI!#REF! -> #REF! | L95: =SUIVI!#REF! -> #REF! | M95: Parc | N95: Scie | O95: =SUIVI!#REF! -> #REF! | P95: 87
A96: =$A$15 -> 0 | B96: =SUIVI!#REF! -> #REF! | C96: =SUIVI!#REF! -> #REF! | D96: ÉQUERRAGE | H96: =IF(C96,1,0) -> #REF! | I96: =IF(SUIVI!#REF!,1,0) -> #REF! | J96: =SUIVI!#REF! -> #REF! | K96: =SUIVI!#REF! -> #REF! | L96: =SUIVI!#REF! -> #REF! | M96: Parc | N96: Scie | O96: =SUIVI!#REF! -> #REF! | P96: 88
A97: =$A$16 -> 0 | B97: =SUIVI!#REF! -> #REF! | C97: =SUIVI!#REF! -> #REF! | H97: =IF(C97,1,0) -> #REF! | I97: =IF(SUIVI!#REF!,1,0) -> #REF! | J97: =SUIVI!#REF! -> #REF! | K97: =SUIVI!#REF! -> #REF! | L97: =SUIVI!#REF! -> #REF! | M97: Parc | N97: Scie | O97: =SUIVI!#REF! -> #REF! | P97: 89
A98: =$A$17 -> 0 | B98: =SUIVI!#REF! -> #REF! | C98: =SUIVI!#REF! -> #REF! | H98: =IF(C98,1,0) -> #REF! | I98: =IF(SUIVI!#REF!,1,0) -> #REF! | J98: =SUIVI!#REF! -> #REF! | K98: =SUIVI!#REF! -> #REF! | L98: =SUIVI!#REF! -> #REF! | M98: Parc | N98: Scie | O98: =SUIVI!#REF! -> #REF! | P98: 90
A99: =$A$9 -> 1100633635-636 | B99: =SUIVI!#REF! -> #REF! | C99: =SUIVI!#REF! -> #REF! | D99: DOUBLE | H99: =IF(C99,1,0) -> #REF! | I99: =IF(SUIVI!#REF!,1,0) -> #REF! | J99: =SUIVI!#REF! -> #REF! | K99: =SUIVI!#REF! -> #REF! | L99: =SUIVI!#REF! -> #REF! | M99: Parc | N99: Scie | O99: =SUIVI!#REF! -> #REF! | P99: 91
A100: =$A$10 -> Z128 | B100: =SUIVI!#REF! -> #REF! | C100: =SUIVI!#REF! -> #REF! | D100: DRESSAGE | H100: =IF(C100,1,0) -> #REF! | I100: =IF(SUIVI!#REF!,1,0) -> #REF! | J100: =SUIVI!#REF! -> #REF! | K100: =SUIVI!#REF! -> #REF! | L100: =SUIVI!#REF! -> #REF! | M100: Parc | N100: Scie | O100: =SUIVI!#REF! -> #REF! | P100: 92
...

Sheet FT-US-REP
U1: DOUBLE DRESSAGE + ÉQUERRAGE
U2: TOLÉRANCES RÉDUITES 0.7MM/M
A3: ArcelorMittal Belval & Differdange S.A. | E3: Parachèvement spécial
A4: Site de Differdange
D5: MACHINE: U.S. ET REPARATION | U5: POINÇONNER LE N° DE COULÉE
A6: Nom: | D6: Date: | I6: Poste: | L6: CE:
A7: Commande | B7: Profil | C7: Longueur | D7: Descriptif du travail | F7: Tronçon | G7: REP | H7: Nbre | I7: Nbre | J7: Numero | K7: Poste | L7: Poste | M7: Proven. | N7: Destin. | O7: L-LAM | W7: TOL -2 / + 0mm
C8: finie | H8: prévu | I8: réalisé | J8: laminage | K8: Asia | L8: R 3
A9: =PREVI!$A$10 -> 1100633635-636 | B9: =SUIVI!H9 -> HL1100A | C9: =SUIVI!J9 -> 10300 | D9: CONTRÔLE | H9: =IF(C9,1,0) -> 1 | I9: =IF(SUIVI!P9,1,0) -> 0 | J9: =SUIVI!M9 -> CZ6 | K9: =SUIVI!E9 -> 1 | L9: =SUIVI!G9 -> 10 | M9: Parc | N9: Scie | O9: =SUIVI!I9 -> 11100 | P9: 1 | T9: OPERATEUR | U9: CE | W9: TOL -0 / +2mm
A10: =PREVI!$A$11 -> Z128 | B10: =SUIVI!H10 -> HL1100A | C10: =SUIVI!J10 -> 10300 | D10: ULTRA SON | H10: =IF(C10,1,0) -> 1 | I10: =IF(SUIVI!P10,1,0) -> 0 | J10: =SUIVI!M10 -> CZ7 | K10: =SUIVI!E10 -> 1 | L10: =SUIVI!G10 -> 10 | M10: Parc | N10: Scie | O10: =SUIVI!I10 -> 11100 | P10: 2 | T10: GLODT | U10: VALLE
A11: =PREVI!$A$12 -> 1900015151-15087 | B11: =SUIVI!H11 -> HL1100A | C11: =SUIVI!J11 -> 10400 | D11: 1 | H11: =IF(C11,1,0) -> 1 | I11: =IF(SUIVI!P11,1,0) -> 0 | J11: =SUIVI!M11 -> CZ52 | K11: =SUIVI!E11 -> 9 | L11: =SUIVI!G11 -> 20 | M11: Parc | N11: Scie | O11: =SUIVI!I11 -> 11300 | P11: 3 | T11: NICOLI | U11: WELSCHER | W11: TOL + / - 2 mm
A12: =PREVI!$C$10 -> CIMOLAI | B12: =SUIVI!H12 -> HL1100A | C12: =SUIVI!J12 -> 9000 | H12: =IF(C12,1,0) -> 1 | I12: =IF(SUIVI!P12,1,0) -> 0 | J12: =SUIVI!M12 -> EA15 | K12: =SUIVI!E12 -> 10 | L12: =SUIVI!G12 -> 10 | M12: Parc | N12: Scie | O12: =SUIVI!I12 -> 9200 | P12: 4 | T12: SCHMISSER
A13: =PREVI!$C$11 -> PASSERELLE DE BELVAL | B13: =SUIVI!H13 -> HL1100A | C13: =SUIVI!J13 -> 10100 | D13: CONTRÔLE ETAT | H13: =IF(C13,1,0) -> 1 | I13: =IF(SUIVI!P13,1,0) -> 0 | J13: =SUIVI!M13 -> CZ9 oder10 | K13: =SUIVI!E13 -> 2 | L13: =SUIVI!G13 -> 20 | M13: Parc | N13: Scie | O13: =SUIVI!I13 -> 10700 | P13: 5 | W13: TOL -0 / +50mm
A14: N° de plans | B14: =SUIVI!H14 -> HL1100A | C14: =SUIVI!J14 -> 10400 | D14: ET RÉPARATION | H14: =IF(C14,1,0) -> 1 | I14: =IF(SUIVI!P14,1,0) -> 0 | J14: =SUIVI!M14 -> EC48 | K14: =SUIVI!E14 -> 38 | L14: =SUIVI!G14 -> 20 | M14: Parc | N14: Scie | O14: =SUIVI!I14 -> 10600 | P14: 6 | U14: POSTE
A15: =PREVI!$A$24 -> 0 | B15: =SUIVI!H15 -> HL1100A | C15: =SUIVI!J15 -> 10400 | D15: DE SURFACE | H15: =IF(C15,1,0) -> 1 | I15: =IF(SUIVI!P15,1,0) -> 0 | J15: =SUIVI!M15 -> EC49 | K15: =SUIVI!E15 -> 38 | L15: =SUIVI!G15 -> 20 | M15: Parc | N15: Scie | O15: =SUIVI!I15 -> 10600 | P15: 7 | U15: 06-14
A16: =PREVI!$A$25 -> 0 | B16: =SUIVI!H16 -> HL1100A | C16: =SUIVI!J16 -> 10400 | H16: =IF(C16,1,0) -> 1 | I16: =IF(SUIVI!P16,1,0) -> 0 | J16: =SUIVI!M16 -> EC50 | K16: =SUIVI!E16 -> 38 | L16: =SUIVI!G16 -> 30 | M16: Parc | N16: Scie | O16: =SUIVI!I16 -> 10600 | P16: 8 | U16: 14-22
A17: =PREVI!$A$26 -> 0 | B17: =SUIVI!H17 -> HL1100A | C17: =SUIVI!J17 -> 10400 | H17: =IF(C17,1,0) -> 1 | I17: =IF(SUIVI!P17,1,0) -> 0 | J17: =SUIVI!M17 -> EC51 | K17: =SUIVI!E17 -> 38 | L17: =SUIVI!G17 -> 30 | M17: Parc | N17: Scie | O17: =SUIVI!I17 -> 10600 | P17: 9 | U17: 22-06
A18: =$A$9 -> 1100633635-636 | B18: =SUIVI!H18 -> HL1100B | C18: =SUIVI!J18 -> 5300 | H18: =IF(C18,1,0) -> 1 | I18: =IF(SUIVI!P18,1,0) -> 0 | J18: =SUIVI!M18 -> EC406 oder 407 | K18: =SUIVI!E18 -> 27 | L18: =SUIVI!G18 -> 40 | M18: Parc | N18: Scie | O18: =SUIVI!I18 -> 15800 | P18: 10
A19: =$A$10 -> Z128 | P19: 11
A20: =$A$11 -> 1900015151-15087 | P20: 12
A21: =$A$12 -> CIMOLAI | P21: 13
A22: =$A$13 -> PASSERELLE DE BELVAL | P22: 14
A23: N° de plans | P23: 15 | R23: DOUBLE DRESSAGE + ÉQUERRAGE
A24: =$A$15 -> 0 | P24: 16 | R24: TOLÉRANCES RÉDUITES 0.7MM/M
A25: =$A$16 -> 0 | P25: 17
A26: =$A$17 -> 0 | P26: 18
A27: =$A$9 -> 1100633635-636 | P27: 19
A28: =$A$10 -> Z128 | P28: 20
A29: =$A$11 -> 1900015151-15087 | P29: 21
A30: =$A$12 -> CIMOLAI | B30: =SUIVI!#REF! -> #REF! | C30: =SUIVI!#REF! -> #REF! | H30: =IF(C30,1,0) -> #REF! | I30: =IF(SUIVI!#REF!,1,0) -> #REF! | J30: =SUIVI!#REF! -> #REF! | K30: =SUIVI!#REF! -> #REF! | L30: =SUIVI!#REF! -> #REF! | M30: Parc | N30: Scie | O30: =SUIVI!#REF! -> #REF! | P30: 22
A31: =$A$13 -> PASSERELLE DE BELVAL | B31: =SUIVI!#REF! -> #REF! | C31: =SUIVI!#REF! -> #REF! | H31: =IF(C31,1,0) -> #REF! | I31: =IF(SUIVI!#REF!,1,0) -> #REF! | J31: =SUIVI!#REF! -> #REF! | K31: =SUIVI!#REF! -> #REF! | L31: =SUIVI!#REF! -> #REF! | M31: Parc | N31: Scie | O31: =SUIVI!#REF! -> #REF! | P31: 23
A32: N° de plans | B32: =SUIVI!#REF! -> #REF! | C32: =SUIVI!#REF! -> #REF! | H32: =IF(C32,1,0) -> #REF! | I32: =IF(SUIVI!#REF!,1,0) -> #REF! | J32: =SUIVI!#REF! -> #REF! | K32: =SUIVI!#REF! -> #REF! | L32: =SUIVI!#REF! -> #REF! | M32: Parc | N32: Scie | O32: =SUIVI!#REF! -> #REF! | P32: 24
A33: =$A$15 -> 0 | B33: =SUIVI!#REF! -> #REF! | C33: =SUIVI!#REF! -> #REF! | H33: =IF(C33,1,0) -> #REF! | I33: =IF(SUIVI!#REF!,1,0) -> #REF! | J33: =SUIVI!#REF! -> #REF! | K33: =SUIVI!#REF! -> #REF! | L33: =SUIVI!#REF! -> #REF! | M33: Parc | N33: Scie | O33: =SUIVI!#REF! -> #REF! | P33: 25
A34: =$A$16 -> 0 | B34: =SUIVI!#REF! -> #REF! | C34: =SUIVI!#REF! -> #REF! | H34: =IF(C34,1,0) -> #REF! | I34: =IF(SUIVI!#REF!,1,0) -> #REF! | J34: =SUIVI!#REF! -> #REF! | K34: =SUIVI!#REF! -> #REF! | L34: =SUIVI!#REF! -> #REF! | M34: Parc | N34: Scie | O34: =SUIVI!#REF! -> #REF! | P34: 26
A35: =$A$17 -> 0 | B35: =SUIVI!#REF! -> #REF! | C35: =SUIVI!#REF! -> #REF! | H35: =IF(C35,1,0) -> #REF! | I35: =IF(SUIVI!#REF!,1,0) -> #REF! | J35: =SUIVI!#REF! -> #REF! | K35: =SUIVI!#REF! -> #REF! | L35: =SUIVI!#REF! -> #REF! | M35: Parc | N35: Scie | O35: =SUIVI!#REF! -> #REF! | P35: 27
A36: =$A$9 -> 1100633635-636 | B36: =SUIVI!#REF! -> #REF! | C36: =SUIVI!#REF! -> #REF! | H36: =IF(C36,1,0) -> #REF! | I36: =IF(SUIVI!#REF!,1,0) -> #REF! | J36: =SUIVI!#REF! -> #REF! | K36: =SUIVI!#REF! -> #REF! | L36: =SUIVI!#REF! -> #REF! | M36: Parc | N36: Scie | O36: =SUIVI!#REF! -> #REF! | P36: 28
A37: =$A$10 -> Z128 | B37: =SUIVI!#REF! -> #REF! | C37: =SUIVI!#REF! -> #REF! | H37: =IF(C37,1,0) -> #REF! | I37: =IF(SUIVI!#REF!,1,0) -> #REF! | J37: =SUIVI!#REF! -> #REF! | K37: =SUIVI!#REF! -> #REF! | L37: =SUIVI!#REF! -> #REF! | M37: Parc | N37: Scie | O37: =SUIVI!#REF! -> #REF! | P37: 29
A38: =$A$11 -> 1900015151-15087 | B38: =SUIVI!#REF! -> #REF! | C38: =SUIVI!#REF! -> #REF! | H38: =IF(C38,1,0) -> #REF! | I38: =IF(SUIVI!#REF!,1,0) -> #REF! | J38: =SUIVI!#REF! -> #REF! | K38: =SUIVI!#REF! -> #REF! | L38: =SUIVI!#REF! -> #REF! | M38: Parc | N38: Scie | O38: =SUIVI!#REF! -> #REF! | P38: 30
A39: =$A$12 -> CIMOLAI | B39: =SUIVI!#REF! -> #REF! | C39: =SUIVI!#REF! -> #REF! | H39: =IF(C39,1,0) -> #REF! | I39: =IF(SUIVI!#REF!,1,0) -> #REF! | J39: =SUIVI!#REF! -> #REF! | K39: =SUIVI!#REF! -> #REF! | L39: =SUIVI!#REF! -> #REF! | M39: Parc | N39: Scie | O39: =SUIVI!#REF! -> #REF! | P39: 31
A40: =$A$13 -> PASSERELLE DE BELVAL | B40: =SUIVI!#REF! -> #REF! | C40: =SUIVI!#REF! -> #REF! | H40: =IF(C40,1,0) -> #REF! | I40: =IF(SUIVI!#REF!,1,0) -> #REF! | J40: =SUIVI!#REF! -> #REF! | K40: =SUIVI!#REF! -> #REF! | L40: =SUIVI!#REF! -> #REF! | M40: Parc | N40: Scie | O40: =SUIVI!#REF! -> #REF! | P40: 32
A41: N° de plans | B41: =SUIVI!#REF! -> #REF! | C41: =SUIVI!#REF! -> #REF! | H41: =IF(C41,1,0) -> #REF! | I41: =IF(SUIVI!#REF!,1,0) -> #REF! | J41: =SUIVI!#REF! -> #REF! | K41: =SUIVI!#REF! -> #REF! | L41: =SUIVI!#REF! -> #REF! | M41: Parc | N41: Scie | O41: =SUIVI!#REF! -> #REF! | P41: 33
A42: =$A$15 -> 0 | B42: =SUIVI!#REF! -> #REF! | C42: =SUIVI!#REF! -> #REF! | H42: =IF(C42,1,0) -> #REF! | I42: =IF(SUIVI!#REF!,1,0) -> #REF! | J42: =SUIVI!#REF! -> #REF! | K42: =SUIVI!#REF! -> #REF! | L42: =SUIVI!#REF! -> #REF! | M42: Parc | N42: Scie | O42: =SUIVI!#REF! -> #REF! | P42: 34
A43: =$A$16 -> 0 | B43: =SUIVI!#REF! -> #REF! | C43: =SUIVI!#REF! -> #REF! | H43: =IF(C43,1,0) -> #REF! | I43: =IF(SUIVI!#REF!,1,0) -> #REF! | J43: =SUIVI!#REF! -> #REF! | K43: =SUIVI!#REF! -> #REF! | L43: =SUIVI!#REF! -> #REF! | M43: Parc | N43: Scie | O43: =SUIVI!#REF! -> #REF! | P43: 35
A44: =$A$17 -> 0 | B44: =SUIVI!#REF! -> #REF! | C44: =SUIVI!#REF! -> #REF! | H44: =IF(C44,1,0) -> #REF! | I44: =IF(SUIVI!#REF!,1,0) -> #REF! | J44: =SUIVI!#REF! -> #REF! | K44: =SUIVI!#REF! -> #REF! | L44: =SUIVI!#REF! -> #REF! | M44: Parc | N44: Scie | O44: =SUIVI!#REF! -> #REF! | P44: 36
A45: =$A$9 -> 1100633635-636 | B45: =SUIVI!#REF! -> #REF! | C45: =SUIVI!#REF! -> #REF! | H45: =IF(C45,1,0) -> #REF! | I45: =IF(SUIVI!#REF!,1,0) -> #REF! | J45: =SUIVI!#REF! -> #REF! | K45: =SUIVI!#REF! -> #REF! | L45: =SUIVI!#REF! -> #REF! | M45: Parc | N45: Scie | O45: =SUIVI!#REF! -> #REF! | P45: 37
A46: =$A$10 -> Z128 | B46: =SUIVI!#REF! -> #REF! | C46: =SUIVI!#REF! -> #REF! | H46: =IF(C46,1,0) -> #REF! | I46: =IF(SUIVI!#REF!,1,0) -> #REF! | J46: =SUIVI!#REF! -> #REF! | K46: =SUIVI!#REF! -> #REF! | L46: =SUIVI!#REF! -> #REF! | M46: Parc | N46: Scie | O46: =SUIVI!#REF! -> #REF! | P46: 38
A47: =$A$11 -> 1900015151-15087 | B47: =SUIVI!#REF! -> #REF! | C47: =SUIVI!#REF! -> #REF! | H47: =IF(C47,1,0) -> #REF! | I47: =IF(SUIVI!#REF!,1,0) -> #REF! | J47: =SUIVI!#REF! -> #REF! | K47: =SUIVI!#REF! -> #REF! | L47: =SUIVI!#REF! -> #REF! | M47: Parc | N47: Scie | O47: =SUIVI!#REF! -> #REF! | P47: 39
A48: =$A$12 -> CIMOLAI | B48: =SUIVI!#REF! -> #REF! | C48: =SUIVI!#REF! -> #REF! | H48: =IF(C48,1,0) -> #REF! | I48: =IF(SUIVI!#REF!,1,0) -> #REF! | J48: =SUIVI!#REF! -> #REF! | K48: =SUIVI!#REF! -> #REF! | L48: =SUIVI!#REF! -> #REF! | M48: Parc | N48: Scie | O48: =SUIVI!#REF! -> #REF! | P48: 40
A49: =$A$13 -> PASSERELLE DE BELVAL | B49: =SUIVI!#REF! -> #REF! | C49: =SUIVI!#REF! -> #REF! | H49: =IF(C49,1,0) -> #REF! | I49: =IF(SUIVI!#REF!,1,0) -> #REF! | J49: =SUIVI!#REF! -> #REF! | K49: =SUIVI!#REF! -> #REF! | L49: =SUIVI!#REF! -> #REF! | M49: Parc | N49: Scie | O49: =SUIVI!#REF! -> #REF! | P49: 41
A50: N° de plans | B50: =SUIVI!#REF! -> #REF! | C50: =SUIVI!#REF! -> #REF! | H50: =IF(C50,1,0) -> #REF! | I50: =IF(SUIVI!#REF!,1,0) -> #REF! | J50: =SUIVI!#REF! -> #REF! | K50: =SUIVI!#REF! -> #REF! | L50: =SUIVI!#REF! -> #REF! | M50: Parc | N50: Scie | O50: =SUIVI!#REF! -> #REF! | P50: 42
A51: =$A$15 -> 0 | B51: =SUIVI!#REF! -> #REF! | C51: =SUIVI!#REF! -> #REF! | H51: =IF(C51,1,0) -> #REF! | I51: =IF(SUIVI!#REF!,1,0) -> #REF! | J51: =SUIVI!#REF! -> #REF! | K51: =SUIVI!#REF! -> #REF! | L51: =SUIVI!#REF! -> #REF! | M51: Parc | N51: Scie | O51: =SUIVI!#REF! -> #REF! | P51: 43
A52: =$A$16 -> 0 | B52: =SUIVI!#REF! -> #REF! | C52: =SUIVI!#REF! -> #REF! | H52: =IF(C52,1,0) -> #REF! | I52: =IF(SUIVI!#REF!,1,0) -> #REF! | J52: =SUIVI!#REF! -> #REF! | K52: =SUIVI!#REF! -> #REF! | L52: =SUIVI!#REF! -> #REF! | M52: Parc | N52: Scie | O52: =SUIVI!#REF! -> #REF! | P52: 44
A53: =$A$17 -> 0 | B53: =SUIVI!#REF! -> #REF! | C53: =SUIVI!#REF! -> #REF! | H53: =IF(C53,1,0) -> #REF! | I53: =IF(SUIVI!#REF!,1,0) -> #REF! | J53: =SUIVI!#REF! -> #REF! | K53: =SUIVI!#REF! -> #REF! | L53: =SUIVI!#REF! -> #REF! | M53: Parc | N53: Scie | O53: =SUIVI!#REF! -> #REF! | P53: 45
A54: =$A$9 -> 1100633635-636 | B54: =SUIVI!#REF! -> #REF! | C54: =SUIVI!#REF! -> #REF! | H54: =IF(C54,1,0) -> #REF! | I54: =IF(SUIVI!#REF!,1,0) -> #REF! | J54: =SUIVI!#REF! -> #REF! | K54: =SUIVI!#REF! -> #REF! | L54: =SUIVI!#REF! -> #REF! | M54: Parc | N54: Scie | O54: =SUIVI!#REF! -> #REF! | P54: 46
A55: =$A$10 -> Z128 | B55: =SUIVI!#REF! -> #REF! | C55: =SUIVI!#REF! -> #REF! | H55: =IF(C55,1,0) -> #REF! | I55: =IF(SUIVI!#REF!,1,0) -> #REF! | J55: =SUIVI!#REF! -> #REF! | K55: =SUIVI!#REF! -> #REF! | L55: =SUIVI!#REF! -> #REF! | M55: Parc | N55: Scie | O55: =SUIVI!#REF! -> #REF! | P55: 47
A56: =$A$11 -> 1900015151-15087 | B56: =SUIVI!#REF! -> #REF! | C56: =SUIVI!#REF! -> #REF! | H56: =IF(C56,1,0) -> #REF! | I56: =IF(SUIVI!#REF!,1,0) -> #REF! | J56: =SUIVI!#REF! -> #REF! | K56: =SUIVI!#REF! -> #REF! | L56: =SUIVI!#REF! -> #REF! | M56: Parc | N56: Scie | O56: =SUIVI!#REF! -> #REF! | P56: 48
A57: =$A$12 -> CIMOLAI | B57: =SUIVI!#REF! -> #REF! | C57: =SUIVI!#REF! -> #REF! | H57: =IF(C57,1,0) -> #REF! | I57: =IF(SUIVI!#REF!,1,0) -> #REF! | J57: =SUIVI!#REF! -> #REF! | K57: =SUIVI!#REF! -> #REF! | L57: =SUIVI!#REF! -> #REF! | M57: Parc | N57: Scie | O57: =SUIVI!#REF! -> #REF! | P57: 49
A58: =$A$13 -> PASSERELLE DE BELVAL | B58: =SUIVI!#REF! -> #REF! | C58: =SUIVI!#REF! -> #REF! | H58: =IF(C58,1,0) -> #REF! | I58: =IF(SUIVI!#REF!,1,0) -> #REF! | J58: =SUIVI!#REF! -> #REF! | K58: =SUIVI!#REF! -> #REF! | L58: =SUIVI!#REF! -> #REF! | M58: Parc | N58: Scie | O58: =SUIVI!#REF! -> #REF! | P58: 50
A59: N° de plans | B59: =SUIVI!#REF! -> #REF! | C59: =SUIVI!#REF! -> #REF! | H59: =IF(C59,1,0) -> #REF! | I59: =IF(SUIVI!#REF!,1,0) -> #REF! | J59: =SUIVI!#REF! -> #REF! | K59: =SUIVI!#REF! -> #REF! | L59: =SUIVI!#REF! -> #REF! | M59: Parc | N59: Scie | O59: =SUIVI!#REF! -> #REF! | P59: 51
A60: =$A$15 -> 0 | B60: =SUIVI!#REF! -> #REF! | C60: =SUIVI!#REF! -> #REF! | H60: =IF(C60,1,0) -> #REF! | I60: =IF(SUIVI!#REF!,1,0) -> #REF! | J60: =SUIVI!#REF! -> #REF! | K60: =SUIVI!#REF! -> #REF! | L60: =SUIVI!#REF! -> #REF! | M60: Parc | N60: Scie | O60: =SUIVI!#REF! -> #REF! | P60: 52
A61: =$A$16 -> 0 | B61: =SUIVI!#REF! -> #REF! | C61: =SUIVI!#REF! -> #REF! | H61: =IF(C61,1,0) -> #REF! | I61: =IF(SUIVI!#REF!,1,0) -> #REF! | J61: =SUIVI!#REF! -> #REF! | K61: =SUIVI!#REF! -> #REF! | L61: =SUIVI!#REF! -> #REF! | M61: Parc | N61: Scie | O61: =SUIVI!#REF! -> #REF! | P61: 53
A62: =$A$17 -> 0 | B62: =SUIVI!#REF! -> #REF! | C62: =SUIVI!#REF! -> #REF! | H62: =IF(C62,1,0) -> #REF! | I62: =IF(SUIVI!#REF!,1,0) -> #REF! | J62: =SUIVI!#REF! -> #REF! | K62: =SUIVI!#REF! -> #REF! | L62: =SUIVI!#REF! -> #REF! | M62: Parc | N62: Scie | O62: =SUIVI!#REF! -> #REF! | P62: 54
A63: =$A$9 -> 1100633635-636 | B63: =SUIVI!#REF! -> #REF! | C63: =SUIVI!#REF! -> #REF! | H63: =IF(C63,1,0) -> #REF! | I63: =IF(SUIVI!#REF!,1,0) -> #REF! | J63: =SUIVI!#REF! -> #REF! | K63: =SUIVI!#REF! -> #REF! | L63: =SUIVI!#REF! -> #REF! | M63: Parc | N63: Scie | O63: =SUIVI!#REF! -> #REF! | P63: 55
A64: =$A$10 -> Z128 | B64: =SUIVI!#REF! -> #REF! | C64: =SUIVI!#REF! -> #REF! | H64: =IF(C64,1,0) -> #REF! | I64: =IF(SUIVI!#REF!,1,0) -> #REF! | J64: =SUIVI!#REF! -> #REF! | K64: =SUIVI!#REF! -> #REF! | L64: =SUIVI!#REF! -> #REF! | M64: Parc | N64: Scie | O64: =SUIVI!#REF! -> #REF! | P64: 56
A65: =$A$11 -> 1900015151-15087 | B65: =SUIVI!#REF! -> #REF! | C65: =SUIVI!#REF! -> #REF! | H65: =IF(C65,1,0) -> #REF! | I65: =IF(SUIVI!#REF!,1,0) -> #REF! | J65: =SUIVI!#REF! -> #REF! | K65: =SUIVI!#REF! -> #REF! | L65: =SUIVI!#REF! -> #REF! | M65: Parc | N65: Scie | O65: =SUIVI!#REF! -> #REF! | P65: 57
A66: =$A$12 -> CIMOLAI | B66: =SUIVI!#REF! -> #REF! | C66: =SUIVI!#REF! -> #REF! | H66: =IF(C66,1,0) -> #REF! | I66: =IF(SUIVI!#REF!,1,0) -> #REF! | J66: =SUIVI!#REF! -> #REF! | K66: =SUIVI!#REF! -> #REF! | L66: =SUIVI!#REF! -> #REF! | M66: Parc | N66: Scie | O66: =SUIVI!#REF! -> #REF! | P66: 58
A67: =$A$13 -> PASSERELLE DE BELVAL | B67: =SUIVI!#REF! -> #REF! | C67: =SUIVI!#REF! -> #REF! | H67: =IF(C67,1,0) -> #REF! | I67: =IF(SUIVI!#REF!,1,0) -> #REF! | J67: =SUIVI!#REF! -> #REF! | K67: =SUIVI!#REF! -> #REF! | L67: =SUIVI!#REF! -> #REF! | M67: Parc | N67: Scie | O67: =SUIVI!#REF! -> #REF! | P67: 59
A68: N° de plans | B68: =SUIVI!#REF! -> #REF! | C68: =SUIVI!#REF! -> #REF! | H68: =IF(C68,1,0) -> #REF! | I68: =IF(SUIVI!#REF!,1,0) -> #REF! | J68: =SUIVI!#REF! -> #REF! | K68: =SUIVI!#REF! -> #REF! | L68: =SUIVI!#REF! -> #REF! | M68: Parc | N68: Scie | O68: =SUIVI!#REF! -> #REF! | P68: 60
A69: =$A$15 -> 0 | B69: =SUIVI!#REF! -> #REF! | C69: =SUIVI!#REF! -> #REF! | H69: =IF(C69,1,0) -> #REF! | I69: =IF(SUIVI!#REF!,1,0) -> #REF! | J69: =SUIVI!#REF! -> #REF! | K69: =SUIVI!#REF! -> #REF! | L69: =SUIVI!#REF! -> #REF! | M69: Parc | N69: Scie | O69: =SUIVI!#REF! -> #REF! | P69: 61
A70: =$A$16 -> 0 | B70: =SUIVI!#REF! -> #REF! | C70: =SUIVI!#REF! -> #REF! | H70: =IF(C70,1,0) -> #REF! | I70: =IF(SUIVI!#REF!,1,0) -> #REF! | J70: =SUIVI!#REF! -> #REF! | K70: =SUIVI!#REF! -> #REF! | L70: =SUIVI!#REF! -> #REF! | M70: Parc | N70: Scie | O70: =SUIVI!#REF! -> #REF! | P70: 62
A71: =$A$17 -> 0 | B71: =SUIVI!#REF! -> #REF! | C71: =SUIVI!#REF! -> #REF! | H71: =IF(C71,1,0) -> #REF! | I71: =IF(SUIVI!#REF!,1,0) -> #REF! | J71: =SUIVI!#REF! -> #REF! | K71: =SUIVI!#REF! -> #REF! | L71: =SUIVI!#REF! -> #REF! | M71: Parc | N71: Scie | O71: =SUIVI!#REF! -> #REF! | P71: 63
A72: =$A$9 -> 1100633635-636 | B72: =SUIVI!#REF! -> #REF! | C72: =SUIVI!#REF! -> #REF! | H72: =IF(C72,1,0) -> #REF! | I72: =IF(SUIVI!#REF!,1,0) -> #REF! | J72: =SUIVI!#REF! -> #REF! | K72: =SUIVI!#REF! -> #REF! | L72: =SUIVI!#REF! -> #REF! | M72: Parc | N72: Scie | O72: =SUIVI!#REF! -> #REF! | P72: 64
A73: =$A$10 -> Z128 | B73: =SUIVI!#REF! -> #REF! | C73: =SUIVI!#REF! -> #REF! | H73: =IF(C73,1,0) -> #REF! | I73: =IF(SUIVI!#REF!,1,0) -> #REF! | J73: =SUIVI!#REF! -> #REF! | K73: =SUIVI!#REF! -> #REF! | L73: =SUIVI!#REF! -> #REF! | M73: Parc | N73: Scie | O73: =SUIVI!#REF! -> #REF! | P73: 65
A74: =$A$11 -> 1900015151-15087 | B74: =SUIVI!#REF! -> #REF! | C74: =SUIVI!#REF! -> #REF! | H74: =IF(C74,1,0) -> #REF! | I74: =IF(SUIVI!#REF!,1,0) -> #REF! | J74: =SUIVI!#REF! -> #REF! | K74: =SUIVI!#REF! -> #REF! | L74: =SUIVI!#REF! -> #REF! | M74: Parc | N74: Scie | O74: =SUIVI!#REF! -> #REF! | P74: 66
A75: =$A$12 -> CIMOLAI | B75: =SUIVI!#REF! -> #REF! | C75: =SUIVI!#REF! -> #REF! | H75: =IF(C75,1,0) -> #REF! | I75: =IF(SUIVI!#REF!,1,0) -> #REF! | J75: =SUIVI!#REF! -> #REF! | K75: =SUIVI!#REF! -> #REF! | L75: =SUIVI!#REF! -> #REF! | M75: Parc | N75: Scie | O75: =SUIVI!#REF! -> #REF! | P75: 67
A76: =$A$13 -> PASSERELLE DE BELVAL | B76: =SUIVI!#REF! -> #REF! | C76: =SUIVI!#REF! -> #REF! | H76: =IF(C76,1,0) -> #REF! | I76: =IF(SUIVI!#REF!,1,0) -> #REF! | J76: =SUIVI!#REF! -> #REF! | K76: =SUIVI!#REF! -> #REF! | L76: =SUIVI!#REF! -> #REF! | M76: Parc | N76: Scie | O76: =SUIVI!#REF! -> #REF! | P76: 68
A77: N° de plans | B77: =SUIVI!#REF! -> #REF! | C77: =SUIVI!#REF! -> #REF! | H77: =IF(C77,1,0) -> #REF! | I77: =IF(SUIVI!#REF!,1,0) -> #REF! | J77: =SUIVI!#REF! -> #REF! | K77: =SUIVI!#REF! -> #REF! | L77: =SUIVI!#REF! -> #REF! | M77: Parc | N77: Scie | O77: =SUIVI!#REF! -> #REF! | P77: 69
A78: =$A$15 -> 0 | B78: =SUIVI!#REF! -> #REF! | C78: =SUIVI!#REF! -> #REF! | H78: =IF(C78,1,0) -> #REF! | I78: =IF(SUIVI!#REF!,1,0) -> #REF! | J78: =SUIVI!#REF! -> #REF! | K78: =SUIVI!#REF! -> #REF! | L78: =SUIVI!#REF! -> #REF! | M78: Parc | N78: Scie | O78: =SUIVI!#REF! -> #REF! | P78: 70
A79: =$A$16 -> 0 | B79: =SUIVI!#REF! -> #REF! | C79: =SUIVI!#REF! -> #REF! | H79: =IF(C79,1,0) -> #REF! | I79: =IF(SUIVI!#REF!,1,0) -> #REF! | J79: =SUIVI!#REF! -> #REF! | K79: =SUIVI!#REF! -> #REF! | L79: =SUIVI!#REF! -> #REF! | M79: Parc | N79: Scie | O79: =SUIVI!#REF! -> #REF! | P79: 71
A80: =$A$17 -> 0 | B80: =SUIVI!#REF! -> #REF! | C80: =SUIVI!#REF! -> #REF! | H80: =IF(C80,1,0) -> #REF! | I80: =IF(SUIVI!#REF!,1,0) -> #REF! | J80: =SUIVI!#REF! -> #REF! | K80: =SUIVI!#REF! -> #REF! | L80: =SUIVI!#REF! -> #REF! | M80: Parc | N80: Scie | O80: =SUIVI!#REF! -> #REF! | P80: 72
A81: =$A$9 -> 1100633635-636 | B81: =SUIVI!#REF! -> #REF! | C81: =SUIVI!#REF! -> #REF! | H81: =IF(C81,1,0) -> #REF! | I81: =IF(SUIVI!#REF!,1,0) -> #REF! | J81: =SUIVI!#REF! -> #REF! | K81: =SUIVI!#REF! -> #REF! | L81: =SUIVI!#REF! -> #REF! | M81: Parc | N81: Scie | O81: =SUIVI!#REF! -> #REF! | P81: 73
A82: =$A$10 -> Z128 | B82: =SUIVI!#REF! -> #REF! | C82: =SUIVI!#REF! -> #REF! | H82: =IF(C82,1,0) -> #REF! | I82: =IF(SUIVI!#REF!,1,0) -> #REF! | J82: =SUIVI!#REF! -> #REF! | K82: =SUIVI!#REF! -> #REF! | L82: =SUIVI!#REF! -> #REF! | M82: Parc | N82: Scie | O82: =SUIVI!#REF! -> #REF! | P82: 74
A83: =$A$11 -> 1900015151-15087 | B83: =SUIVI!#REF! -> #REF! | C83: =SUIVI!#REF! -> #REF! | H83: =IF(C83,1,0) -> #REF! | I83: =IF(SUIVI!#REF!,1,0) -> #REF! | J83: =SUIVI!#REF! -> #REF! | K83: =SUIVI!#REF! -> #REF! | L83: =SUIVI!#REF! -> #REF! | M83: Parc | N83: Scie | O83: =SUIVI!#REF! -> #REF! | P83: 75
A84: =$A$12 -> CIMOLAI | B84: =SUIVI!#REF! -> #REF! | C84: =SUIVI!#REF! -> #REF! | H84: =IF(C84,1,0) -> #REF! | I84: =IF(SUIVI!#REF!,1,0) -> #REF! | J84: =SUIVI!#REF! -> #REF! | K84: =SUIVI!#REF! -> #REF! | L84: =SUIVI!#REF! -> #REF! | M84: Parc | N84: Scie | O84: =SUIVI!#REF! -> #REF! | P84: 76
A85: =$A$13 -> PASSERELLE DE BELVAL | B85: =SUIVI!#REF! -> #REF! | C85: =SUIVI!#REF! -> #REF! | H85: =IF(C85,1,0) -> #REF! | I85: =IF(SUIVI!#REF!,1,0) -> #REF! | J85: =SUIVI!#REF! -> #REF! | K85: =SUIVI!#REF! -> #REF! | L85: =SUIVI!#REF! -> #REF! | M85: Parc | N85: Scie | O85: =SUIVI!#REF! -> #REF! | P85: 77
A86: N° de plans | B86: =SUIVI!#REF! -> #REF! | C86: =SUIVI!#REF! -> #REF! | H86: =IF(C86,1,0) -> #REF! | I86: =IF(SUIVI!#REF!,1,0) -> #REF! | J86: =SUIVI!#REF! -> #REF! | K86: =SUIVI!#REF! -> #REF! | L86: =SUIVI!#REF! -> #REF! | M86: Parc | N86: Scie | O86: =SUIVI!#REF! -> #REF! | P86: 78
A87: =$A$15 -> 0 | B87: =SUIVI!#REF! -> #REF! | C87: =SUIVI!#REF! -> #REF! | H87: =IF(C87,1,0) -> #REF! | I87: =IF(SUIVI!#REF!,1,0) -> #REF! | J87: =SUIVI!#REF! -> #REF! | K87: =SUIVI!#REF! -> #REF! | L87: =SUIVI!#REF! -> #REF! | M87: Parc | N87: Scie | O87: =SUIVI!#REF! -> #REF! | P87: 79
A88: =$A$16 -> 0 | B88: =SUIVI!#REF! -> #REF! | C88: =SUIVI!#REF! -> #REF! | H88: =IF(C88,1,0) -> #REF! | I88: =IF(SUIVI!#REF!,1,0) -> #REF! | J88: =SUIVI!#REF! -> #REF! | K88: =SUIVI!#REF! -> #REF! | L88: =SUIVI!#REF! -> #REF! | M88: Parc | N88: Scie | O88: =SUIVI!#REF! -> #REF! | P88: 80
A89: =$A$17 -> 0 | B89: =SUIVI!#REF! -> #REF! | C89: =SUIVI!#REF! -> #REF! | H89: =IF(C89,1,0) -> #REF! | I89: =IF(SUIVI!#REF!,1,0) -> #REF! | J89: =SUIVI!#REF! -> #REF! | K89: =SUIVI!#REF! -> #REF! | L89: =SUIVI!#REF! -> #REF! | M89: Parc | N89: Scie | O89: =SUIVI!#REF! -> #REF! | P89: 81
A90: =$A$9 -> 1100633635-636 | B90: =SUIVI!#REF! -> #REF! | C90: =SUIVI!#REF! -> #REF! | H90: =IF(C90,1,0) -> #REF! | I90: =IF(SUIVI!#REF!,1,0) -> #REF! | J90: =SUIVI!#REF! -> #REF! | K90: =SUIVI!#REF! -> #REF! | L90: =SUIVI!#REF! -> #REF! | M90: Parc | N90: Scie | O90: =SUIVI!#REF! -> #REF! | P90: 82
A91: =$A$10 -> Z128 | B91: =SUIVI!#REF! -> #REF! | C91: =SUIVI!#REF! -> #REF! | H91: =IF(C91,1,0) -> #REF! | I91: =IF(SUIVI!#REF!,1,0) -> #REF! | J91: =SUIVI!#REF! -> #REF! | K91: =SUIVI!#REF! -> #REF! | L91: =SUIVI!#REF! -> #REF! | M91: Parc | N91: Scie | O91: =SUIVI!#REF! -> #REF! | P91: 83
A92: =$A$11 -> 1900015151-15087 | B92: =SUIVI!#REF! -> #REF! | C92: =SUIVI!#REF! -> #REF! | H92: =IF(C92,1,0) -> #REF! | I92: =IF(SUIVI!#REF!,1,0) -> #REF! | J92: =SUIVI!#REF! -> #REF! | K92: =SUIVI!#REF! -> #REF! | L92: =SUIVI!#REF! -> #REF! | M92: Parc | N92: Scie | O92: =SUIVI!#REF! -> #REF! | P92: 84
A93: =$A$12 -> CIMOLAI | B93: =SUIVI!#REF! -> #REF! | C93: =SUIVI!#REF! -> #REF! | H93: =IF(C93,1,0) -> #REF! | I93: =IF(SUIVI!#REF!,1,0) -> #REF! | J93: =SUIVI!#REF! -> #REF! | K93: =SUIVI!#REF! -> #REF! | L93: =SUIVI!#REF! -> #REF! | M93: Parc | N93: Scie | O93: =SUIVI!#REF! -> #REF! | P93: 85
A94: =$A$13 -> PASSERELLE DE BELVAL | B94: =SUIVI!#REF! -> #REF! | C94: =SUIVI!#REF! -> #REF! | H94: =IF(C94,1,0) -> #REF! | I94: =IF(SUIVI!#REF!,1,0) -> #REF! | J94: =SUIVI!#REF! -> #REF! | K94: =SUIVI!#REF! -> #REF! | L94: =SUIVI!#REF! -> #REF! | M94: Parc | N94: Scie | O94: =SUIVI!#REF! -> #REF! | P94: 86
A95: N° de plans | B95: =SUIVI!#REF! -> #REF! | C95: =SUIVI!#REF! -> #REF! | H95: =IF(C95,1,0) -> #REF! | I95: =IF(SUIVI!#REF!,1,0) -> #REF! | J95: =SUIVI!#REF! -> #REF! | K95: =SUIVI!#REF! -> #REF! | L95: =SUIVI!#REF! -> #REF! | M95: Parc | N95: Scie | O95: =SUIVI!#REF! -> #REF! | P95: 87
A96: =$A$15 -> 0 | B96: =SUIVI!#REF! -> #REF! | C96: =SUIVI!#REF! -> #REF! | H96: =IF(C96,1,0) -> #REF! | I96: =IF(SUIVI!#REF!,1,0) -> #REF! | J96: =SUIVI!#REF! -> #REF! | K96: =SUIVI!#REF! -> #REF! | L96: =SUIVI!#REF! -> #REF! | M96: Parc | N96: Scie | O96: =SUIVI!#REF! -> #REF! | P96: 88
A97: =$A$16 -> 0 | B97: =SUIVI!#REF! -> #REF! | C97: =SUIVI!#REF! -> #REF! | H97: =IF(C97,1,0) -> #REF! | I97: =IF(SUIVI!#REF!,1,0) -> #REF! | J97: =SUIVI!#REF! -> #REF! | K97: =SUIVI!#REF! -> #REF! | L97: =SUIVI!#REF! -> #REF! | M97: Parc | N97: Scie | O97: =SUIVI!#REF! -> #REF! | P97: 89
A98: =$A$17 -> 0 | B98: =SUIVI!#REF! -> #REF! | C98: =SUIVI!#REF! -> #REF! | H98: =IF(C98,1,0) -> #REF! | I98: =IF(SUIVI!#REF!,1,0) -> #REF! | J98: =SUIVI!#REF! -> #REF! | K98: =SUIVI!#REF! -> #REF! | L98: =SUIVI!#REF! -> #REF! | M98: Parc | N98: Scie | O98: =SUIVI!#REF! -> #REF! | P98: 90
A99: =$A$9 -> 1100633635-636 | B99: =SUIVI!#REF! -> #REF! | C99: =SUIVI!#REF! -> #REF! | H99: =IF(C99,1,0) -> #REF! | I99: =IF(SUIVI!#REF!,1,0) -> #REF! | J99: =SUIVI!#REF! -> #REF! | K99: =SUIVI!#REF! -> #REF! | L99: =SUIVI!#REF! -> #REF! | M99: Parc | N99: Scie | O99: =SUIVI!#REF! -> #REF! | P99: 91
A100: =$A$10 -> Z128 | B100: =SUIVI!#REF! -> #REF! | C100: =SUIVI!#REF! -> #REF! | H100: =IF(C100,1,0) -> #REF! | I100: =IF(SUIVI!#REF!,1,0) -> #REF! | J100: =SUIVI!#REF! -> #REF! | K100: =SUIVI!#REF! -> #REF! | L100: =SUIVI!#REF! -> #REF! | M100: Parc | N100: Scie | O100: =SUIVI!#REF! -> #REF! | P100: 92
...

Sheet FT-SCIE
A3: ArcelorMittal Belval & Differdange S.A. | E3: Parachèvement spécial
A4: Site de Differdange
D5: MACHINE: SCIE | U5: POINÇONNER LE N° DE COULÉE
A6: Nom: | D6: Date: | I6: Poste: | L6: CE:
A7: Commande | B7: Profil | C7: Longueur | D7: Descriptif du travail | F7: Tronçon | G7: REP | H7: Nbre | I7: Nbre | J7: Numero | K7: Poste | L7: Poste | M7: Proven. | N7: Destin. | O7: L-LAM | W7: TOL -2 / + 0mm
C8: finie | H8: prévu | I8: réalisé | J8: laminage | K8: Asia | L8: R 3
A9: =PREVI!$A$10 -> 1100633635-636 | B9: =SUIVI!H9 -> HL1100A | C9: =SUIVI!J9 -> 10300 | F9: =SUIVI!Q9 -> 0 | G9: =SUIVI!R9 -> 0 | H9: =IF(C9,1,0) -> 1 | I9: =IF(SUIVI!T9,1,0) -> #VALUE! | J9: =SUIVI!S9 -> CZ6 | K9: =SUIVI!E9 -> 1 | L9: =SUIVI!G9 -> 10 | M9: PARC | N9: PARC | O9: =SUIVI!I9 -> 11100 | P9: 1 | T9: OPERATEUR | U9: CE | W9: TOL -0 / +2mm
A10: =PREVI!$A$11 -> Z128 | N10: =SUIVI!$V$8 -> LKW | P10: 2 | T10: VALLE | U10: VALLE
A11: =PREVI!$A$12 -> 1900015151-15087 | P11: 3 | T11: MUNO | U11: WELSCHER | W11: TOL + / - 2 mm
A12: =PREVI!$C$10 -> CIMOLAI | P12: 4 | T12: GLODT
A13: =PREVI!$C$11 -> PASSERELLE DE BELVAL | P13: 5 | T13: SCHOLLER | W13: TOL -0 / +50mm
A14: N° de plans | P14: 6 | T14: GONCALVES JC | U14: POSTE
A15: =PREVI!$A$24 -> 0 | P15: 7 | U15: 06-14
A16: =PREVI!$A$25 -> 0 | P16: 8 | U16: 14-22
A17: =PREVI!$A$26 -> 0 | D17: CONTRÔLE DE | P17: 9 | U17: 22-06
A18: =$A$9 -> 1100633635-636 | D18: L'ÉTAT DE | P18: 10
A19: =$A$10 -> Z128 | D19: SURFACE ET | P19: 11
A20: =$A$11 -> 1900015151-15087 | D20: ENVOYER EN | P20: 12
A21: =$A$12 -> CIMOLAI | D21: RÉPARATION | P21: 13 | S21: LG DE CHARGEMENT MAXI SUR CAMION
A22: =$A$13 -> PASSERELLE DE BELVAL | D22: SI | P22: 14 | S22: 22000 | T22: MAXI RECOMMANDÉ
A23: N° de plans | D23: NÉCESSAIRE | P23: 15 | S23: 23000 | T23: A VÉRIFIER
A24: =$A$15 -> 0 | P24: 16 | S24: 24000 | T24: fait avec casse rétroviseur
A25: =$A$16 -> 0 | P25: 17
A26: =$A$17 -> 0 | P26: 18
A27: =$A$9 -> 1100633635-636 | P27: 19
B28: F577 SCIAGE BARRE DE SCHROTT

Sheet FT-ROBOT AUTO
A3: ArcelorMittal Belval & Differdange S.A. | E3: Parachèvement spécial
A4: Site de Differdange
D5: MACHINE: ROBOT | U5: POINÇONNER LE N° DE COULÉE
A6: Nom: | B6: GERON | D6: Date: | E6: 44589 | I6: Poste: | J6: 06-14 | L6: CE:
A7: Commande | B7: Profil | C7: Longueur | D7: Descriptif du travail | F7: Tronçon | G7: REP | H7: Nbre | I7: Nbre | J7: Numero | K7: Poste | L7: Poste | M7: Proven. | N7: Destin. | O7: L-LAM | W7: TOL -2 / + 0mm
C8: finie | H8: prévu | I8: réalisé | J8: laminage | K8: Asia | L8: R 3
A9: =PREVI!$A$10 -> 1100633635-636 | B9: =SUIVI!H9 -> HL1100A | C9: =SUIVI!J9 -> 10300 | D9: 2 bouts 90° -0/+10mm | F9: =SUIVI!Q9 -> 0 | G9: =SUIVI!R9 -> 0 | H9: =IF(C9,1,0) -> 1 | I9: =IF(SUIVI!T9,1,0) -> #VALUE! | J9: =SUIVI!S9 -> CZ6 | K9: =SUIVI!E9 -> 1 | L9: =SUIVI!G9 -> 10 | M9: Parc | N9: Parc | O9: =SUIVI!I9 -> 11100 | P9: 1 | T9: OPERATEUR | U9: CE | W9: TOL -0 / +2mm
A10: =PREVI!$A$11 -> Z128 | B10: =SUIVI!H10 -> HL1100A | C10: =SUIVI!J10 -> 10300 | D10: 2 bouts 90° -0/+10mm | F10: =SUIVI!Q10 -> 0 | G10: =SUIVI!R10 -> 0 | H10: =IF(C10,1,0) -> 1 | I10: =IF(SUIVI!T10,1,0) -> #VALUE! | J10: =SUIVI!S10 -> CZ7 | K10: =SUIVI!E10 -> 1 | L10: =SUIVI!G10 -> 10 | M10: Parc | N10: =SUIVI!$V$8 -> LKW | O10: =SUIVI!I10 -> 11100 | P10: 2 | T10: SCHILS | U10: VALLE
A11: =PREVI!$A$12 -> 1900015151-15087 | B11: =SUIVI!H11 -> HL1100A | C11: =SUIVI!J11 -> 10400 | D11: 2 bouts 90° -0/+10mm | F11: =SUIVI!Q11 -> 0 | G11: =SUIVI!R11 -> 0 | H11: =IF(C11,1,0) -> 1 | I11: =IF(SUIVI!T11,1,0) -> #VALUE! | J11: =SUIVI!S11 -> CZ52 | K11: =SUIVI!E11 -> 9 | L11: =SUIVI!G11 -> 20 | M11: Parc | N11: Parc | O11: =SUIVI!I11 -> 11300 | P11: 3 | T11: GERON | U11: WELSCHER | W11: TOL + / - 2 mm
A12: =PREVI!$C$10 -> CIMOLAI | B12: =SUIVI!H12 -> HL1100A | C12: =SUIVI!J12 -> 9000 | D12: 2 bouts 90° -0/+10mm | F12: =SUIVI!Q12 -> 0 | G12: =SUIVI!R12 -> 0 | H12: =IF(C12,1,0) -> 1 | I12: =IF(SUIVI!T12,1,0) -> #VALUE! | J12: =SUIVI!S12 -> EA15 | K12: =SUIVI!E12 -> 10 | L12: =SUIVI!G12 -> 10 | M12: Parc | N12: =SUIVI!$V$8 -> LKW | O12: =SUIVI!I12 -> 9200 | P12: 4 | T12: MATHIEU
A13: =PREVI!$C$11 -> PASSERELLE DE BELVAL | B13: =SUIVI!H13 -> HL1100A | C13: =SUIVI!J13 -> 10100 | D13: 2 bouts 90° -0/+10mm | F13: =SUIVI!Q13 -> 0 | G13: =SUIVI!R13 -> 0 | H13: =IF(C13,1,0) -> 1 | I13: =IF(SUIVI!T13,1,0) -> #VALUE! | J13: =SUIVI!S13 -> CZ9 | K13: =SUIVI!E13 -> 2 | L13: =SUIVI!G13 -> 20 | M13: Parc | N13: Parc | O13: =SUIVI!I13 -> 10700 | P13: 5 | T13: MUNO | W13: TOL -0 / +50mm
A14: N° de plans | B14: =SUIVI!H14 -> HL1100A | C14: =SUIVI!J14 -> 10400 | D14: èpreuve | F14: =SUIVI!Q14 -> 0 | G14: =SUIVI!R14 -> 0 | H14: =IF(C14,1,0) -> 1 | I14: =IF(SUIVI!T14,1,0) -> #VALUE! | J14: =SUIVI!S14 -> EC48 | K14: =SUIVI!E14 -> 38 | L14: =SUIVI!G14 -> 20 | M14: Parc | N14: =SUIVI!$V$8 -> LKW | O14: =SUIVI!I14 -> 10600 | P14: 6 | T14: WIRTGEN | U14: POSTE
A15: =PREVI!$A$24 -> 0 | B15: =SUIVI!H15 -> HL1100A | C15: =SUIVI!J15 -> 10400 | D15: 2 bouts 90° -0/+10mm | F15: =SUIVI!Q15 -> 0 | G15: =SUIVI!R15 -> 0 | H15: =IF(C15,1,0) -> 1 | I15: =IF(SUIVI!T15,1,0) -> #VALUE! | J15: =SUIVI!S15 -> EC49 | K15: =SUIVI!E15 -> 38 | L15: =SUIVI!G15 -> 20 | M15: Parc | N15: Parc | O15: =SUIVI!I15 -> 10600 | P15: 7 | U15: 06-14
A16: =PREVI!$A$25 -> 0 | B16: =SUIVI!H16 -> HL1100A | C16: =SUIVI!J16 -> 10400 | D16: 2 bouts 90° -0/+10mm | F16: =SUIVI!Q16 -> 0 | G16: =SUIVI!R16 -> 0 | H16: =IF(C16,1,0) -> 1 | I16: =IF(SUIVI!T16,1,0) -> #VALUE! | J16: =SUIVI!S16 -> EC50 | K16: =SUIVI!E16 -> 38 | L16: =SUIVI!G16 -> 30 | M16: Parc | N16: =SUIVI!$V$8 -> LKW | O16: =SUIVI!I16 -> 10600 | P16: 8 | U16: 14-22
A17: =PREVI!$A$26 -> 0 | B17: =SUIVI!H17 -> HL1100A | C17: =SUIVI!J17 -> 10400 | D17: 2 bouts 90° -0/+10mm | F17: =SUIVI!Q17 -> 0 | G17: =SUIVI!R17 -> 0 | H17: =IF(C17,1,0) -> 1 | I17: =IF(SUIVI!T17,1,0) -> #VALUE! | J17: =SUIVI!S17 -> EC51 | K17: =SUIVI!E17 -> 38 | L17: =SUIVI!G17 -> 30 | M17: Parc | N17: Parc | O17: =SUIVI!I17 -> 10600 | P17: 9 | U17: 22-06
A18: =$A$9 -> 1100633635-636 | B18: =SUIVI!H18 -> HL1100B | C18: =SUIVI!J18 -> 5300 | D18: 2 bouts 90° -0/+10mm | F18: =SUIVI!Q18 -> 0 | G18: =SUIVI!R18 -> 0 | H18: =IF(C18,1,0) -> 1 | I18: =IF(SUIVI!T18,1,0) -> 1 | J18: =SUIVI!S18 -> EC407 | K18: =SUIVI!E18 -> 27 | L18: =SUIVI!G18 -> 40 | M18: Parc | N18: =SUIVI!$V$8 -> LKW | O18: =SUIVI!I18 -> 15800 | P18: 10
A19: =$A$10 -> Z128 | P19: 11
A20: =$A$11 -> 1900015151-15087 | P20: 12
A21: =$A$12 -> CIMOLAI | P21: 13 | S21: LG DE CHARGEMENT MAXI SUR CAMION
A22: =$A$13 -> PASSERELLE DE BELVAL | P22: 14 | S22: 22000 | T22: MAXI RECOMMANDÉ
A23: N° de plans | P23: 15 | S23: 23000 | T23: A VÉRIFIER
A24: =$A$15 -> 0 | P24: 16 | S24: 24000 | T24: fait avec casse rétroviseur
A25: =$A$16 -> 0 | P25: 17
A26: =$A$17 -> 0 | P26: 18
A27: =$A$9 -> 1100633635-636 | P27: 19
A28: =$A$10 -> Z128 | P28: 20 | S28: INDIQUER LES 2 APPELLATIONS (ex) WTM 27x140x336 = W690x360x500
A29: =$A$11 -> 1900015151-15087 | P29: 21
A30: =$A$12 -> CIMOLAI | B30: =SUIVI!#REF! -> #REF! | C30: =SUIVI!#REF! -> #REF! | F30: =SUIVI!#REF! -> #REF! | G30: =SUIVI!#REF! -> #REF! | H30: =IF(C30,1,0) -> #REF! | I30: =IF(SUIVI!#REF!,1,0) -> #REF! | J30: =SUIVI!#REF! -> #REF! | K30: =SUIVI!#REF! -> #REF! | L30: =SUIVI!#REF! -> #REF! | M30: Parc | N30: =SUIVI!$V$8 -> LKW | O30: =SUIVI!#REF! -> #REF! | P30: 22
A31: =$A$13 -> PASSERELLE DE BELVAL | B31: =SUIVI!#REF! -> #REF! | C31: =SUIVI!#REF! -> #REF! | F31: =SUIVI!#REF! -> #REF! | G31: =SUIVI!#REF! -> #REF! | H31: =IF(C31,1,0) -> #REF! | I31: =IF(SUIVI!#REF!,1,0) -> #REF! | J31: =SUIVI!#REF! -> #REF! | K31: =SUIVI!#REF! -> #REF! | L31: =SUIVI!#REF! -> #REF! | M31: Parc | N31: Parc | O31: =SUIVI!#REF! -> #REF! | P31: 23
A32: N° de plans | B32: =SUIVI!#REF! -> #REF! | C32: =SUIVI!#REF! -> #REF! | F32: =SUIVI!#REF! -> #REF! | G32: =SUIVI!#REF! -> #REF! | H32: =IF(C32,1,0) -> #REF! | I32: =IF(SUIVI!#REF!,1,0) -> #REF! | J32: =SUIVI!#REF! -> #REF! | K32: =SUIVI!#REF! -> #REF! | L32: =SUIVI!#REF! -> #REF! | M32: Parc | N32: =SUIVI!$V$8 -> LKW | O32: =SUIVI!#REF! -> #REF! | P32: 24
A33: =$A$15 -> 0 | B33: =SUIVI!#REF! -> #REF! | C33: =SUIVI!#REF! -> #REF! | F33: =SUIVI!#REF! -> #REF! | G33: =SUIVI!#REF! -> #REF! | H33: =IF(C33,1,0) -> #REF! | I33: =IF(SUIVI!#REF!,1,0) -> #REF! | J33: =SUIVI!#REF! -> #REF! | K33: =SUIVI!#REF! -> #REF! | L33: =SUIVI!#REF! -> #REF! | M33: Parc | N33: Parc | O33: =SUIVI!#REF! -> #REF! | P33: 25
A34: =$A$16 -> 0 | B34: =SUIVI!#REF! -> #REF! | C34: =SUIVI!#REF! -> #REF! | F34: =SUIVI!#REF! -> #REF! | G34: =SUIVI!#REF! -> #REF! | H34: =IF(C34,1,0) -> #REF! | I34: =IF(SUIVI!#REF!,1,0) -> #REF! | J34: =SUIVI!#REF! -> #REF! | K34: =SUIVI!#REF! -> #REF! | L34: =SUIVI!#REF! -> #REF! | M34: Parc | N34: =SUIVI!$V$8 -> LKW | O34: =SUIVI!#REF! -> #REF! | P34: 26
A35: =$A$17 -> 0 | B35: =SUIVI!#REF! -> #REF! | C35: =SUIVI!#REF! -> #REF! | F35: =SUIVI!#REF! -> #REF! | G35: =SUIVI!#REF! -> #REF! | H35: =IF(C35,1,0) -> #REF! | I35: =IF(SUIVI!#REF!,1,0) -> #REF! | J35: =SUIVI!#REF! -> #REF! | K35: =SUIVI!#REF! -> #REF! | L35: =SUIVI!#REF! -> #REF! | M35: Parc | N35: Parc | O35: =SUIVI!#REF! -> #REF! | P35: 27
A36: =$A$9 -> 1100633635-636 | B36: =SUIVI!#REF! -> #REF! | C36: =SUIVI!#REF! -> #REF! | F36: =SUIVI!#REF! -> #REF! | G36: =SUIVI!#REF! -> #REF! | H36: =IF(C36,1,0) -> #REF! | I36: =IF(SUIVI!#REF!,1,0) -> #REF! | J36: =SUIVI!#REF! -> #REF! | K36: =SUIVI!#REF! -> #REF! | L36: =SUIVI!#REF! -> #REF! | M36: Parc | N36: =SUIVI!$V$8 -> LKW | O36: =SUIVI!#REF! -> #REF! | P36: 28
A37: =$A$10 -> Z128 | B37: =SUIVI!#REF! -> #REF! | C37: =SUIVI!#REF! -> #REF! | F37: =SUIVI!#REF! -> #REF! | G37: =SUIVI!#REF! -> #REF! | H37: =IF(C37,1,0) -> #REF! | I37: =IF(SUIVI!#REF!,1,0) -> #REF! | J37: =SUIVI!#REF! -> #REF! | K37: =SUIVI!#REF! -> #REF! | L37: =SUIVI!#REF! -> #REF! | M37: Parc | N37: Parc | O37: =SUIVI!#REF! -> #REF! | P37: 29
A38: =$A$11 -> 1900015151-15087 | B38: =SUIVI!#REF! -> #REF! | C38: =SUIVI!#REF! -> #REF! | F38: =SUIVI!#REF! -> #REF! | G38: =SUIVI!#REF! -> #REF! | H38: =IF(C38,1,0) -> #REF! | I38: =IF(SUIVI!#REF!,1,0) -> #REF! | J38: =SUIVI!#REF! -> #REF! | K38: =SUIVI!#REF! -> #REF! | L38: =SUIVI!#REF! -> #REF! | M38: Parc | N38: =SUIVI!$V$8 -> LKW | O38: =SUIVI!#REF! -> #REF! | P38: 30
A39: =$A$12 -> CIMOLAI | B39: =SUIVI!#REF! -> #REF! | C39: =SUIVI!#REF! -> #REF! | F39: =SUIVI!#REF! -> #REF! | G39: =SUIVI!#REF! -> #REF! | H39: =IF(C39,1,0) -> #REF! | I39: =IF(SUIVI!#REF!,1,0) -> #REF! | J39: =SUIVI!#REF! -> #REF! | K39: =SUIVI!#REF! -> #REF! | L39: =SUIVI!#REF! -> #REF! | M39: Parc | N39: Parc | O39: =SUIVI!#REF! -> #REF! | P39: 31
A40: =$A$13 -> PASSERELLE DE BELVAL | B40: =SUIVI!#REF! -> #REF! | C40: =SUIVI!#REF! -> #REF! | F40: =SUIVI!#REF! -> #REF! | G40: =SUIVI!#REF! -> #REF! | H40: =IF(C40,1,0) -> #REF! | I40: =IF(SUIVI!#REF!,1,0) -> #REF! | J40: =SUIVI!#REF! -> #REF! | K40: =SUIVI!#REF! -> #REF! | L40: =SUIVI!#REF! -> #REF! | M40: Parc | N40: =SUIVI!$V$8 -> LKW | O40: =SUIVI!#REF! -> #REF! | P40: 32
A41: N° de plans | B41: =SUIVI!#REF! -> #REF! | C41: =SUIVI!#REF! -> #REF! | F41: =SUIVI!#REF! -> #REF! | G41: =SUIVI!#REF! -> #REF! | H41: =IF(C41,1,0) -> #REF! | I41: =IF(SUIVI!#REF!,1,0) -> #REF! | J41: =SUIVI!#REF! -> #REF! | K41: =SUIVI!#REF! -> #REF! | L41: =SUIVI!#REF! -> #REF! | M41: Parc | N41: Parc | O41: =SUIVI!#REF! -> #REF! | P41: 33
A42: =$A$15 -> 0 | B42: =SUIVI!#REF! -> #REF! | C42: =SUIVI!#REF! -> #REF! | F42: =SUIVI!#REF! -> #REF! | G42: =SUIVI!#REF! -> #REF! | H42: =IF(C42,1,0) -> #REF! | I42: =IF(SUIVI!#REF!,1,0) -> #REF! | J42: =SUIVI!#REF! -> #REF! | K42: =SUIVI!#REF! -> #REF! | L42: =SUIVI!#REF! -> #REF! | M42: Parc | N42: =SUIVI!$V$8 -> LKW | O42: =SUIVI!#REF! -> #REF! | P42: 34
A43: =$A$16 -> 0 | B43: =SUIVI!#REF! -> #REF! | C43: =SUIVI!#REF! -> #REF! | F43: =SUIVI!#REF! -> #REF! | G43: =SUIVI!#REF! -> #REF! | H43: =IF(C43,1,0) -> #REF! | I43: =IF(SUIVI!#REF!,1,0) -> #REF! | J43: =SUIVI!#REF! -> #REF! | K43: =SUIVI!#REF! -> #REF! | L43: =SUIVI!#REF! -> #REF! | M43: Parc | N43: Parc | O43: =SUIVI!#REF! -> #REF! | P43: 35
A44: =$A$17 -> 0 | B44: =SUIVI!#REF! -> #REF! | C44: =SUIVI!#REF! -> #REF! | F44: =SUIVI!#REF! -> #REF! | G44: =SUIVI!#REF! -> #REF! | H44: =IF(C44,1,0) -> #REF! | I44: =IF(SUIVI!#REF!,1,0) -> #REF! | J44: =SUIVI!#REF! -> #REF! | K44: =SUIVI!#REF! -> #REF! | L44: =SUIVI!#REF! -> #REF! | M44: Parc | N44: =SUIVI!$V$8 -> LKW | O44: =SUIVI!#REF! -> #REF! | P44: 36
A45: =$A$9 -> 1100633635-636 | B45: =SUIVI!#REF! -> #REF! | C45: =SUIVI!#REF! -> #REF! | F45: =SUIVI!#REF! -> #REF! | G45: =SUIVI!#REF! -> #REF! | H45: =IF(C45,1,0) -> #REF! | I45: =IF(SUIVI!#REF!,1,0) -> #REF! | J45: =SUIVI!#REF! -> #REF! | K45: =SUIVI!#REF! -> #REF! | L45: =SUIVI!#REF! -> #REF! | M45: Parc | N45: Parc | O45: =SUIVI!#REF! -> #REF! | P45: 37
A46: =$A$10 -> Z128 | B46: =SUIVI!#REF! -> #REF! | C46: =SUIVI!#REF! -> #REF! | F46: =SUIVI!#REF! -> #REF! | G46: =SUIVI!#REF! -> #REF! | H46: =IF(C46,1,0) -> #REF! | I46: =IF(SUIVI!#REF!,1,0) -> #REF! | J46: =SUIVI!#REF! -> #REF! | K46: =SUIVI!#REF! -> #REF! | L46: =SUIVI!#REF! -> #REF! | M46: Parc | N46: =SUIVI!$V$8 -> LKW | O46: =SUIVI!#REF! -> #REF! | P46: 38
A47: =$A$11 -> 1900015151-15087 | B47: =SUIVI!#REF! -> #REF! | C47: =SUIVI!#REF! -> #REF! | F47: =SUIVI!#REF! -> #REF! | G47: =SUIVI!#REF! -> #REF! | H47: =IF(C47,1,0) -> #REF! | I47: =IF(SUIVI!#REF!,1,0) -> #REF! | J47: =SUIVI!#REF! -> #REF! | K47: =SUIVI!#REF! -> #REF! | L47: =SUIVI!#REF! -> #REF! | M47: Parc | N47: Parc | O47: =SUIVI!#REF! -> #REF! | P47: 39
A48: =$A$12 -> CIMOLAI | B48: =SUIVI!#REF! -> #REF! | C48: =SUIVI!#REF! -> #REF! | F48: =SUIVI!#REF! -> #REF! | G48: =SUIVI!#REF! -> #REF! | H48: =IF(C48,1,0) -> #REF! | I48: =IF(SUIVI!#REF!,1,0) -> #REF! | J48: =SUIVI!#REF! -> #REF! | K48: =SUIVI!#REF! -> #REF! | L48: =SUIVI!#REF! -> #REF! | M48: Parc | N48: =SUIVI!$V$8 -> LKW | O48: =SUIVI!#REF! -> #REF! | P48: 40
A49: =$A$13 -> PASSERELLE DE BELVAL | B49: =SUIVI!#REF! -> #REF! | C49: =SUIVI!#REF! -> #REF! | F49: =SUIVI!#REF! -> #REF! | G49: =SUIVI!#REF! -> #REF! | H49: =IF(C49,1,0) -> #REF! | I49: =IF(SUIVI!#REF!,1,0) -> #REF! | J49: =SUIVI!#REF! -> #REF! | K49: =SUIVI!#REF! -> #REF! | L49: =SUIVI!#REF! -> #REF! | M49: Parc | N49: Parc | O49: =SUIVI!#REF! -> #REF! | P49: 41
A50: N° de plans | B50: =SUIVI!#REF! -> #REF! | C50: =SUIVI!#REF! -> #REF! | F50: =SUIVI!#REF! -> #REF! | G50: =SUIVI!#REF! -> #REF! | H50: =IF(C50,1,0) -> #REF! | I50: =IF(SUIVI!#REF!,1,0) -> #REF! | J50: =SUIVI!#REF! -> #REF! | K50: =SUIVI!#REF! -> #REF! | L50: =SUIVI!#REF! -> #REF! | M50: Parc | N50: =SUIVI!$V$8 -> LKW | O50: =SUIVI!#REF! -> #REF! | P50: 42
A51: =$A$15 -> 0 | B51: =SUIVI!#REF! -> #REF! | C51: =SUIVI!#REF! -> #REF! | F51: =SUIVI!#REF! -> #REF! | G51: =SUIVI!#REF! -> #REF! | H51: =IF(C51,1,0) -> #REF! | I51: =IF(SUIVI!#REF!,1,0) -> #REF! | J51: =SUIVI!#REF! -> #REF! | K51: =SUIVI!#REF! -> #REF! | L51: =SUIVI!#REF! -> #REF! | M51: Parc | N51: Parc | O51: =SUIVI!#REF! -> #REF! | P51: 43
A52: =$A$16 -> 0 | B52: =SUIVI!#REF! -> #REF! | C52: =SUIVI!#REF! -> #REF! | F52: =SUIVI!#REF! -> #REF! | G52: =SUIVI!#REF! -> #REF! | H52: =IF(C52,1,0) -> #REF! | I52: =IF(SUIVI!#REF!,1,0) -> #REF! | J52: =SUIVI!#REF! -> #REF! | K52: =SUIVI!#REF! -> #REF! | L52: =SUIVI!#REF! -> #REF! | M52: Parc | N52: =SUIVI!$V$8 -> LKW | O52: =SUIVI!#REF! -> #REF! | P52: 44
A53: =$A$17 -> 0 | B53: =SUIVI!#REF! -> #REF! | C53: =SUIVI!#REF! -> #REF! | F53: =SUIVI!#REF! -> #REF! | G53: =SUIVI!#REF! -> #REF! | H53: =IF(C53,1,0) -> #REF! | I53: =IF(SUIVI!#REF!,1,0) -> #REF! | J53: =SUIVI!#REF! -> #REF! | K53: =SUIVI!#REF! -> #REF! | L53: =SUIVI!#REF! -> #REF! | M53: Parc | N53: Parc | O53: =SUIVI!#REF! -> #REF! | P53: 45
A54: =$A$9 -> 1100633635-636 | B54: =SUIVI!#REF! -> #REF! | C54: =SUIVI!#REF! -> #REF! | F54: =SUIVI!#REF! -> #REF! | G54: =SUIVI!#REF! -> #REF! | H54: =IF(C54,1,0) -> #REF! | I54: =IF(SUIVI!#REF!,1,0) -> #REF! | J54: =SUIVI!#REF! -> #REF! | K54: =SUIVI!#REF! -> #REF! | L54: =SUIVI!#REF! -> #REF! | M54: Parc | N54: =SUIVI!$V$8 -> LKW | O54: =SUIVI!#REF! -> #REF! | P54: 46
A55: =$A$10 -> Z128 | B55: =SUIVI!#REF! -> #REF! | C55: =SUIVI!#REF! -> #REF! | F55: =SUIVI!#REF! -> #REF! | G55: =SUIVI!#REF! -> #REF! | H55: =IF(C55,1,0) -> #REF! | I55: =IF(SUIVI!#REF!,1,0) -> #REF! | J55: =SUIVI!#REF! -> #REF! | K55: =SUIVI!#REF! -> #REF! | L55: =SUIVI!#REF! -> #REF! | M55: Parc | N55: Parc | O55: =SUIVI!#REF! -> #REF! | P55: 47
A56: =$A$11 -> 1900015151-15087 | B56: =SUIVI!#REF! -> #REF! | C56: =SUIVI!#REF! -> #REF! | F56: =SUIVI!#REF! -> #REF! | G56: =SUIVI!#REF! -> #REF! | H56: =IF(C56,1,0) -> #REF! | I56: =IF(SUIVI!#REF!,1,0) -> #REF! | J56: =SUIVI!#REF! -> #REF! | K56: =SUIVI!#REF! -> #REF! | L56: =SUIVI!#REF! -> #REF! | M56: Parc | N56: =SUIVI!$V$8 -> LKW | O56: =SUIVI!#REF! -> #REF! | P56: 48
A57: =$A$12 -> CIMOLAI | B57: =SUIVI!#REF! -> #REF! | C57: =SUIVI!#REF! -> #REF! | F57: =SUIVI!#REF! -> #REF! | G57: =SUIVI!#REF! -> #REF! | H57: =IF(C57,1,0) -> #REF! | I57: =IF(SUIVI!#REF!,1,0) -> #REF! | J57: =SUIVI!#REF! -> #REF! | K57: =SUIVI!#REF! -> #REF! | L57: =SUIVI!#REF! -> #REF! | M57: Parc | N57: Parc | O57: =SUIVI!#REF! -> #REF! | P57: 49
A58: =$A$13 -> PASSERELLE DE BELVAL | B58: =SUIVI!#REF! -> #REF! | C58: =SUIVI!#REF! -> #REF! | F58: =SUIVI!#REF! -> #REF! | G58: =SUIVI!#REF! -> #REF! | H58: =IF(C58,1,0) -> #REF! | I58: =IF(SUIVI!#REF!,1,0) -> #REF! | J58: =SUIVI!#REF! -> #REF! | K58: =SUIVI!#REF! -> #REF! | L58: =SUIVI!#REF! -> #REF! | M58: Parc | N58: =SUIVI!$V$8 -> LKW | O58: =SUIVI!#REF! -> #REF! | P58: 50
A59: N° de plans | B59: =SUIVI!#REF! -> #REF! | C59: =SUIVI!#REF! -> #REF! | F59: =SUIVI!#REF! -> #REF! | G59: =SUIVI!#REF! -> #REF! | H59: =IF(C59,1,0) -> #REF! | I59: =IF(SUIVI!#REF!,1,0) -> #REF! | J59: =SUIVI!#REF! -> #REF! | K59: =SUIVI!#REF! -> #REF! | L59: =SUIVI!#REF! -> #REF! | M59: Parc | N59: Parc | O59: =SUIVI!#REF! -> #REF! | P59: 51
A60: =$A$15 -> 0 | B60: =SUIVI!#REF! -> #REF! | C60: =SUIVI!#REF! -> #REF! | F60: =SUIVI!#REF! -> #REF! | G60: =SUIVI!#REF! -> #REF! | H60: =IF(C60,1,0) -> #REF! | I60: =IF(SUIVI!#REF!,1,0) -> #REF! | J60: =SUIVI!#REF! -> #REF! | K60: =SUIVI!#REF! -> #REF! | L60: =SUIVI!#REF! -> #REF! | M60: Parc | N60: =SUIVI!$V$8 -> LKW | O60: =SUIVI!#REF! -> #REF! | P60: 52
A61: =$A$16 -> 0 | B61: =SUIVI!#REF! -> #REF! | C61: =SUIVI!#REF! -> #REF! | F61: =SUIVI!#REF! -> #REF! | G61: =SUIVI!#REF! -> #REF! | H61: =IF(C61,1,0) -> #REF! | I61: =IF(SUIVI!#REF!,1,0) -> #REF! | J61: =SUIVI!#REF! -> #REF! | K61: =SUIVI!#REF! -> #REF! | L61: =SUIVI!#REF! -> #REF! | M61: Parc | N61: Parc | O61: =SUIVI!#REF! -> #REF! | P61: 53
A62: =$A$17 -> 0 | B62: =SUIVI!#REF! -> #REF! | C62: =SUIVI!#REF! -> #REF! | F62: =SUIVI!#REF! -> #REF! | G62: =SUIVI!#REF! -> #REF! | H62: =IF(C62,1,0) -> #REF! | I62: =IF(SUIVI!#REF!,1,0) -> #REF! | J62: =SUIVI!#REF! -> #REF! | K62: =SUIVI!#REF! -> #REF! | L62: =SUIVI!#REF! -> #REF! | M62: Parc | N62: =SUIVI!$V$8 -> LKW | O62: =SUIVI!#REF! -> #REF! | P62: 54
A63: =$A$9 -> 1100633635-636 | B63: =SUIVI!#REF! -> #REF! | C63: =SUIVI!#REF! -> #REF! | F63: =SUIVI!#REF! -> #REF! | G63: =SUIVI!#REF! -> #REF! | H63: =IF(C63,1,0) -> #REF! | I63: =IF(SUIVI!#REF!,1,0) -> #REF! | J63: =SUIVI!#REF! -> #REF! | K63: =SUIVI!#REF! -> #REF! | L63: =SUIVI!#REF! -> #REF! | M63: Parc | N63: Parc | O63: =SUIVI!#REF! -> #REF! | P63: 55
A64: =$A$10 -> Z128 | B64: =SUIVI!#REF! -> #REF! | C64: =SUIVI!#REF! -> #REF! | F64: =SUIVI!#REF! -> #REF! | G64: =SUIVI!#REF! -> #REF! | H64: =IF(C64,1,0) -> #REF! | I64: =IF(SUIVI!#REF!,1,0) -> #REF! | J64: =SUIVI!#REF! -> #REF! | K64: =SUIVI!#REF! -> #REF! | L64: =SUIVI!#REF! -> #REF! | M64: Parc | N64: =SUIVI!$V$8 -> LKW | O64: =SUIVI!#REF! -> #REF! | P64: 56
A65: =$A$11 -> 1900015151-15087 | B65: =SUIVI!#REF! -> #REF! | C65: =SUIVI!#REF! -> #REF! | F65: =SUIVI!#REF! -> #REF! | G65: =SUIVI!#REF! -> #REF! | H65: =IF(C65,1,0) -> #REF! | I65: =IF(SUIVI!#REF!,1,0) -> #REF! | J65: =SUIVI!#REF! -> #REF! | K65: =SUIVI!#REF! -> #REF! | L65: =SUIVI!#REF! -> #REF! | M65: Parc | N65: Parc | O65: =SUIVI!#REF! -> #REF! | P65: 57
A66: =$A$12 -> CIMOLAI | B66: =SUIVI!#REF! -> #REF! | C66: =SUIVI!#REF! -> #REF! | F66: =SUIVI!#REF! -> #REF! | G66: =SUIVI!#REF! -> #REF! | H66: =IF(C66,1,0) -> #REF! | I66: =IF(SUIVI!#REF!,1,0) -> #REF! | J66: =SUIVI!#REF! -> #REF! | K66: =SUIVI!#REF! -> #REF! | L66: =SUIVI!#REF! -> #REF! | M66: Parc | N66: =SUIVI!$V$8 -> LKW | O66: =SUIVI!#REF! -> #REF! | P66: 58
A67: =$A$13 -> PASSERELLE DE BELVAL | B67: =SUIVI!#REF! -> #REF! | C67: =SUIVI!#REF! -> #REF! | F67: =SUIVI!#REF! -> #REF! | G67: =SUIVI!#REF! -> #REF! | H67: =IF(C67,1,0) -> #REF! | I67: =IF(SUIVI!#REF!,1,0) -> #REF! | J67: =SUIVI!#REF! -> #REF! | K67: =SUIVI!#REF! -> #REF! | L67: =SUIVI!#REF! -> #REF! | M67: Parc | N67: Parc | O67: =SUIVI!#REF! -> #REF! | P67: 59
A68: N° de plans | B68: =SUIVI!#REF! -> #REF! | C68: =SUIVI!#REF! -> #REF! | F68: =SUIVI!#REF! -> #REF! | G68: =SUIVI!#REF! -> #REF! | H68: =IF(C68,1,0) -> #REF! | I68: =IF(SUIVI!#REF!,1,0) -> #REF! | J68: =SUIVI!#REF! -> #REF! | K68: =SUIVI!#REF! -> #REF! | L68: =SUIVI!#REF! -> #REF! | M68: Parc | N68: =SUIVI!$V$8 -> LKW | O68: =SUIVI!#REF! -> #REF! | P68: 60
A69: =$A$15 -> 0 | B69: =SUIVI!#REF! -> #REF! | C69: =SUIVI!#REF! -> #REF! | F69: =SUIVI!#REF! -> #REF! | G69: =SUIVI!#REF! -> #REF! | H69: =IF(C69,1,0) -> #REF! | I69: =IF(SUIVI!#REF!,1,0) -> #REF! | J69: =SUIVI!#REF! -> #REF! | K69: =SUIVI!#REF! -> #REF! | L69: =SUIVI!#REF! -> #REF! | M69: Parc | N69: Parc | O69: =SUIVI!#REF! -> #REF! | P69: 61
A70: =$A$16 -> 0 | B70: =SUIVI!#REF! -> #REF! | C70: =SUIVI!#REF! -> #REF! | F70: =SUIVI!#REF! -> #REF! | G70: =SUIVI!#REF! -> #REF! | H70: =IF(C70,1,0) -> #REF! | I70: =IF(SUIVI!#REF!,1,0) -> #REF! | J70: =SUIVI!#REF! -> #REF! | K70: =SUIVI!#REF! -> #REF! | L70: =SUIVI!#REF! -> #REF! | M70: Parc | N70: =SUIVI!$V$8 -> LKW | O70: =SUIVI!#REF! -> #REF! | P70: 62
A71: =$A$17 -> 0 | B71: =SUIVI!#REF! -> #REF! | C71: =SUIVI!#REF! -> #REF! | F71: =SUIVI!#REF! -> #REF! | G71: =SUIVI!#REF! -> #REF! | H71: =IF(C71,1,0) -> #REF! | I71: =IF(SUIVI!#REF!,1,0) -> #REF! | J71: =SUIVI!#REF! -> #REF! | K71: =SUIVI!#REF! -> #REF! | L71: =SUIVI!#REF! -> #REF! | M71: Parc | N71: Parc | O71: =SUIVI!#REF! -> #REF! | P71: 63
A72: =$A$9 -> 1100633635-636 | B72: =SUIVI!#REF! -> #REF! | C72: =SUIVI!#REF! -> #REF! | F72: =SUIVI!#REF! -> #REF! | G72: =SUIVI!#REF! -> #REF! | H72: =IF(C72,1,0) -> #REF! | I72: =IF(SUIVI!#REF!,1,0) -> #REF! | J72: =SUIVI!#REF! -> #REF! | K72: =SUIVI!#REF! -> #REF! | L72: =SUIVI!#REF! -> #REF! | M72: Parc | N72: =SUIVI!$V$8 -> LKW | O72: =SUIVI!#REF! -> #REF! | P72: 64
A73: =$A$10 -> Z128 | B73: =SUIVI!#REF! -> #REF! | C73: =SUIVI!#REF! -> #REF! | F73: =SUIVI!#REF! -> #REF! | G73: =SUIVI!#REF! -> #REF! | H73: =IF(C73,1,0) -> #REF! | I73: =IF(SUIVI!#REF!,1,0) -> #REF! | J73: =SUIVI!#REF! -> #REF! | K73: =SUIVI!#REF! -> #REF! | L73: =SUIVI!#REF! -> #REF! | M73: Parc | N73: Parc | O73: =SUIVI!#REF! -> #REF! | P73: 65
A74: =$A$11 -> 1900015151-15087 | B74: =SUIVI!#REF! -> #REF! | C74: =SUIVI!#REF! -> #REF! | F74: =SUIVI!#REF! -> #REF! | G74: =SUIVI!#REF! -> #REF! | H74: =IF(C74,1,0) -> #REF! | I74: =IF(SUIVI!#REF!,1,0) -> #REF! | J74: =SUIVI!#REF! -> #REF! | K74: =SUIVI!#REF! -> #REF! | L74: =SUIVI!#REF! -> #REF! | M74: Parc | N74: =SUIVI!$V$8 -> LKW | O74: =SUIVI!#REF! -> #REF! | P74: 66
A75: =$A$12 -> CIMOLAI | B75: =SUIVI!#REF! -> #REF! | C75: =SUIVI!#REF! -> #REF! | F75: =SUIVI!#REF! -> #REF! | G75: =SUIVI!#REF! -> #REF! | H75: =IF(C75,1,0) -> #REF! | I75: =IF(SUIVI!#REF!,1,0) -> #REF! | J75: =SUIVI!#REF! -> #REF! | K75: =SUIVI!#REF! -> #REF! | L75: =SUIVI!#REF! -> #REF! | M75: Parc | N75: Parc | O75: =SUIVI!#REF! -> #REF! | P75: 67
A76: =$A$13 -> PASSERELLE DE BELVAL | B76: =SUIVI!#REF! -> #REF! | C76: =SUIVI!#REF! -> #REF! | F76: =SUIVI!#REF! -> #REF! | G76: =SUIVI!#REF! -> #REF! | H76: =IF(C76,1,0) -> #REF! | I76: =IF(SUIVI!#REF!,1,0) -> #REF! | J76: =SUIVI!#REF! -> #REF! | K76: =SUIVI!#REF! -> #REF! | L76: =SUIVI!#REF! -> #REF! | M76: Parc | N76: =SUIVI!$V$8 -> LKW | O76: =SUIVI!#REF! -> #REF! | P76: 68
A77: N° de plans | B77: =SUIVI!#REF! -> #REF! | C77: =SUIVI!#REF! -> #REF! | F77: =SUIVI!#REF! -> #REF! | G77: =SUIVI!#REF! -> #REF! | H77: =IF(C77,1,0) -> #REF! | I77: =IF(SUIVI!#REF!,1,0) -> #REF! | J77: =SUIVI!#REF! -> #REF! | K77: =SUIVI!#REF! -> #REF! | L77: =SUIVI!#REF! -> #REF! | M77: Parc | N77: Parc | O77: =SUIVI!#REF! -> #REF! | P77: 69
A78: =$A$15 -> 0 | B78: =SUIVI!#REF! -> #REF! | C78: =SUIVI!#REF! -> #REF! | F78: =SUIVI!#REF! -> #REF! | G78: =SUIVI!#REF! -> #REF! | H78: =IF(C78,1,0) -> #REF! | I78: =IF(SUIVI!#REF!,1,0) -> #REF! | J78: =SUIVI!#REF! -> #REF! | K78: =SUIVI!#REF! -> #REF! | L78: =SUIVI!#REF! -> #REF! | M78: Parc | N78: =SUIVI!$V$8 -> LKW | O78: =SUIVI!#REF! -> #REF! | P78: 70
A79: =$A$16 -> 0 | B79: =SUIVI!#REF! -> #REF! | C79: =SUIVI!#REF! -> #REF! | F79: =SUIVI!#REF! -> #REF! | G79: =SUIVI!#REF! -> #REF! | H79: =IF(C79,1,0) -> #REF! | I79: =IF(SUIVI!#REF!,1,0) -> #REF! | J79: =SUIVI!#REF! -> #REF! | K79: =SUIVI!#REF! -> #REF! | L79: =SUIVI!#REF! -> #REF! | M79: Parc | N79: Parc | O79: =SUIVI!#REF! -> #REF! | P79: 71
A80: =$A$17 -> 0 | B80: =SUIVI!#REF! -> #REF! | C80: =SUIVI!#REF! -> #REF! | F80: =SUIVI!#REF! -> #REF! | G80: =SUIVI!#REF! -> #REF! | H80: =IF(C80,1,0) -> #REF! | I80: =IF(SUIVI!#REF!,1,0) -> #REF! | J80: =SUIVI!#REF! -> #REF! | K80: =SUIVI!#REF! -> #REF! | L80: =SUIVI!#REF! -> #REF! | M80: Parc | N80: =SUIVI!$V$8 -> LKW | O80: =SUIVI!#REF! -> #REF! | P80: 72
A81: =$A$9 -> 1100633635-636 | B81: =SUIVI!#REF! -> #REF! | C81: =SUIVI!#REF! -> #REF! | F81: =SUIVI!#REF! -> #REF! | G81: =SUIVI!#REF! -> #REF! | H81: =IF(C81,1,0) -> #REF! | I81: =IF(SUIVI!#REF!,1,0) -> #REF! | J81: =SUIVI!#REF! -> #REF! | K81: =SUIVI!#REF! -> #REF! | L81: =SUIVI!#REF! -> #REF! | M81: Parc | N81: Parc | O81: =SUIVI!#REF! -> #REF! | P81: 73
A82: =$A$10 -> Z128 | B82: =SUIVI!#REF! -> #REF! | C82: =SUIVI!#REF! -> #REF! | F82: =SUIVI!#REF! -> #REF! | G82: =SUIVI!#REF! -> #REF! | H82: =IF(C82,1,0) -> #REF! | I82: =IF(SUIVI!#REF!,1,0) -> #REF! | J82: =SUIVI!#REF! -> #REF! | K82: =SUIVI!#REF! -> #REF! | L82: =SUIVI!#REF! -> #REF! | M82: Parc | N82: =SUIVI!$V$8 -> LKW | O82: =SUIVI!#REF! -> #REF! | P82: 74
A83: =$A$11 -> 1900015151-15087 | B83: =SUIVI!#REF! -> #REF! | C83: =SUIVI!#REF! -> #REF! | F83: =SUIVI!#REF! -> #REF! | G83: =SUIVI!#REF! -> #REF! | H83: =IF(C83,1,0) -> #REF! | I83: =IF(SUIVI!#REF!,1,0) -> #REF! | J83: =SUIVI!#REF! -> #REF! | K83: =SUIVI!#REF! -> #REF! | L83: =SUIVI!#REF! -> #REF! | M83: Parc | N83: Parc | O83: =SUIVI!#REF! -> #REF! | P83: 75
A84: =$A$12 -> CIMOLAI | B84: =SUIVI!#REF! -> #REF! | C84: =SUIVI!#REF! -> #REF! | F84: =SUIVI!#REF! -> #REF! | G84: =SUIVI!#REF! -> #REF! | H84: =IF(C84,1,0) -> #REF! | I84: =IF(SUIVI!#REF!,1,0) -> #REF! | J84: =SUIVI!#REF! -> #REF! | K84: =SUIVI!#REF! -> #REF! | L84: =SUIVI!#REF! -> #REF! | M84: Parc | N84: =SUIVI!$V$8 -> LKW | O84: =SUIVI!#REF! -> #REF! | P84: 76
A85: =$A$13 -> PASSERELLE DE BELVAL | B85: =SUIVI!#REF! -> #REF! | C85: =SUIVI!#REF! -> #REF! | F85: =SUIVI!#REF! -> #REF! | G85: =SUIVI!#REF! -> #REF! | H85: =IF(C85,1,0) -> #REF! | I85: =IF(SUIVI!#REF!,1,0) -> #REF! | J85: =SUIVI!#REF! -> #REF! | K85: =SUIVI!#REF! -> #REF! | L85: =SUIVI!#REF! -> #REF! | M85: Parc | N85: Parc | O85: =SUIVI!#REF! -> #REF! | P85: 77
A86: N° de plans | B86: =SUIVI!#REF! -> #REF! | C86: =SUIVI!#REF! -> #REF! | F86: =SUIVI!#REF! -> #REF! | G86: =SUIVI!#REF! -> #REF! | H86: =IF(C86,1,0) -> #REF! | I86: =IF(SUIVI!#REF!,1,0) -> #REF! | J86: =SUIVI!#REF! -> #REF! | K86: =SUIVI!#REF! -> #REF! | L86: =SUIVI!#REF! -> #REF! | M86: Parc | N86: =SUIVI!$V$8 -> LKW | O86: =SUIVI!#REF! -> #REF! | P86: 78
A87: =$A$15 -> 0 | B87: =SUIVI!#REF! -> #REF! | C87: =SUIVI!#REF! -> #REF! | F87: =SUIVI!#REF! -> #REF! | G87: =SUIVI!#REF! -> #REF! | H87: =IF(C87,1,0) -> #REF! | I87: =IF(SUIVI!#REF!,1,0) -> #REF! | J87: =SUIVI!#REF! -> #REF! | K87: =SUIVI!#REF! -> #REF! | L87: =SUIVI!#REF! -> #REF! | M87: Parc | N87: Parc | O87: =SUIVI!#REF! -> #REF! | P87: 79
A88: =$A$16 -> 0 | B88: =SUIVI!#REF! -> #REF! | C88: =SUIVI!#REF! -> #REF! | F88: =SUIVI!#REF! -> #REF! | G88: =SUIVI!#REF! -> #REF! | H88: =IF(C88,1,0) -> #REF! | I88: =IF(SUIVI!#REF!,1,0) -> #REF! | J88: =SUIVI!#REF! -> #REF! | K88: =SUIVI!#REF! -> #REF! | L88: =SUIVI!#REF! -> #REF! | M88: Parc | N88: =SUIVI!$V$8 -> LKW | O88: =SUIVI!#REF! -> #REF! | P88: 80
A89: =$A$17 -> 0 | B89: =SUIVI!#REF! -> #REF! | C89: =SUIVI!#REF! -> #REF! | F89: =SUIVI!#REF! -> #REF! | G89: =SUIVI!#REF! -> #REF! | H89: =IF(C89,1,0) -> #REF! | I89: =IF(SUIVI!#REF!,1,0) -> #REF! | J89: =SUIVI!#REF! -> #REF! | K89: =SUIVI!#REF! -> #REF! | L89: =SUIVI!#REF! -> #REF! | M89: Parc | N89: Parc | O89: =SUIVI!#REF! -> #REF! | P89: 81
A90: =$A$9 -> 1100633635-636 | B90: =SUIVI!#REF! -> #REF! | C90: =SUIVI!#REF! -> #REF! | F90: =SUIVI!#REF! -> #REF! | G90: =SUIVI!#REF! -> #REF! | H90: =IF(C90,1,0) -> #REF! | I90: =IF(SUIVI!#REF!,1,0) -> #REF! | J90: =SUIVI!#REF! -> #REF! | K90: =SUIVI!#REF! -> #REF! | L90: =SUIVI!#REF! -> #REF! | M90: Parc | N90: =SUIVI!$V$8 -> LKW | O90: =SUIVI!#REF! -> #REF! | P90: 82
A91: =$A$10 -> Z128 | B91: =SUIVI!#REF! -> #REF! | C91: =SUIVI!#REF! -> #REF! | F91: =SUIVI!#REF! -> #REF! | G91: =SUIVI!#REF! -> #REF! | H91: =IF(C91,1,0) -> #REF! | I91: =IF(SUIVI!#REF!,1,0) -> #REF! | J91: =SUIVI!#REF! -> #REF! | K91: =SUIVI!#REF! -> #REF! | L91: =SUIVI!#REF! -> #REF! | M91: Parc | N91: Parc | O91: =SUIVI!#REF! -> #REF! | P91: 83
A92: =$A$11 -> 1900015151-15087 | B92: =SUIVI!#REF! -> #REF! | C92: =SUIVI!#REF! -> #REF! | F92: =SUIVI!#REF! -> #REF! | G92: =SUIVI!#REF! -> #REF! | H92: =IF(C92,1,0) -> #REF! | I92: =IF(SUIVI!#REF!,1,0) -> #REF! | J92: =SUIVI!#REF! -> #REF! | K92: =SUIVI!#REF! -> #REF! | L92: =SUIVI!#REF! -> #REF! | M92: Parc | N92: =SUIVI!$V$8 -> LKW | O92: =SUIVI!#REF! -> #REF! | P92: 84
A93: =$A$12 -> CIMOLAI | B93: =SUIVI!#REF! -> #REF! | C93: =SUIVI!#REF! -> #REF! | F93: =SUIVI!#REF! -> #REF! | G93: =SUIVI!#REF! -> #REF! | H93: =IF(C93,1,0) -> #REF! | I93: =IF(SUIVI!#REF!,1,0) -> #REF! | J93: =SUIVI!#REF! -> #REF! | K93: =SUIVI!#REF! -> #REF! | L93: =SUIVI!#REF! -> #REF! | M93: Parc | N93: Parc | O93: =SUIVI!#REF! -> #REF! | P93: 85
A94: =$A$13 -> PASSERELLE DE BELVAL | B94: =SUIVI!#REF! -> #REF! | C94: =SUIVI!#REF! -> #REF! | F94: =SUIVI!#REF! -> #REF! | G94: =SUIVI!#REF! -> #REF! | H94: =IF(C94,1,0) -> #REF! | I94: =IF(SUIVI!#REF!,1,0) -> #REF! | J94: =SUIVI!#REF! -> #REF! | K94: =SUIVI!#REF! -> #REF! | L94: =SUIVI!#REF! -> #REF! | M94: Parc | N94: =SUIVI!$V$8 -> LKW | O94: =SUIVI!#REF! -> #REF! | P94: 86
A95: N° de plans | B95: =SUIVI!#REF! -> #REF! | C95: =SUIVI!#REF! -> #REF! | F95: =SUIVI!#REF! -> #REF! | G95: =SUIVI!#REF! -> #REF! | H95: =IF(C95,1,0) -> #REF! | I95: =IF(SUIVI!#REF!,1,0) -> #REF! | J95: =SUIVI!#REF! -> #REF! | K95: =SUIVI!#REF! -> #REF! | L95: =SUIVI!#REF! -> #REF! | M95: Parc | N95: Parc | O95: =SUIVI!#REF! -> #REF! | P95: 87
A96: =$A$15 -> 0 | B96: =SUIVI!#REF! -> #REF! | C96: =SUIVI!#REF! -> #REF! | F96: =SUIVI!#REF! -> #REF! | G96: =SUIVI!#REF! -> #REF! | H96: =IF(C96,1,0) -> #REF! | I96: =IF(SUIVI!#REF!,1,0) -> #REF! | J96: =SUIVI!#REF! -> #REF! | K96: =SUIVI!#REF! -> #REF! | L96: =SUIVI!#REF! -> #REF! | M96: Parc | N96: =SUIVI!$V$8 -> LKW | O96: =SUIVI!#REF! -> #REF! | P96: 88
A97: =$A$16 -> 0 | B97: =SUIVI!#REF! -> #REF! | C97: =SUIVI!#REF! -> #REF! | F97: =SUIVI!#REF! -> #REF! | G97: =SUIVI!#REF! -> #REF! | H97: =IF(C97,1,0) -> #REF! | I97: =IF(SUIVI!#REF!,1,0) -> #REF! | J97: =SUIVI!#REF! -> #REF! | K97: =SUIVI!#REF! -> #REF! | L97: =SUIVI!#REF! -> #REF! | M97: Parc | N97: Parc | O97: =SUIVI!#REF! -> #REF! | P97: 89
A98: =$A$17 -> 0 | B98: =SUIVI!#REF! -> #REF! | C98: =SUIVI!#REF! -> #REF! | F98: =SUIVI!#REF! -> #REF! | G98: =SUIVI!#REF! -> #REF! | H98: =IF(C98,1,0) -> #REF! | I98: =IF(SUIVI!#REF!,1,0) -> #REF! | J98: =SUIVI!#REF! -> #REF! | K98: =SUIVI!#REF! -> #REF! | L98: =SUIVI!#REF! -> #REF! | M98: Parc | N98: =SUIVI!$V$8 -> LKW | O98: =SUIVI!#REF! -> #REF! | P98: 90
A99: =$A$9 -> 1100633635-636 | B99: =SUIVI!#REF! -> #REF! | C99: =SUIVI!#REF! -> #REF! | F99: =SUIVI!#REF! -> #REF! | G99: =SUIVI!#REF! -> #REF! | H99: =IF(C99,1,0) -> #REF! | I99: =IF(SUIVI!#REF!,1,0) -> #REF! | J99: =SUIVI!#REF! -> #REF! | K99: =SUIVI!#REF! -> #REF! | L99: =SUIVI!#REF! -> #REF! | M99: Parc | N99: Parc | O99: =SUIVI!#REF! -> #REF! | P99: 91
A100: =$A$10 -> Z128 | B100: =SUIVI!#REF! -> #REF! | C100: =SUIVI!#REF! -> #REF! | F100: =SUIVI!#REF! -> #REF! | G100: =SUIVI!#REF! -> #REF! | H100: =IF(C100,1,0) -> #REF! | I100: =IF(SUIVI!#REF!,1,0) -> #REF! | J100: =SUIVI!#REF! -> #REF! | K100: =SUIVI!#REF! -> #REF! | L100: =SUIVI!#REF! -> #REF! | M100: Parc | N100: =SUIVI!$V$8 -> LKW | O100: =SUIVI!#REF! -> #REF! | P100: 92
A101: =$A$11 -> 1900015151-15087 | B101: =SUIVI!#REF! -> #REF! | C101: =SUIVI!#REF! -> #REF! | F101: =SUIVI!#REF! -> #REF! | G101: =SUIVI!#REF! -> #REF! | H101: =IF(C101,1,0) -> #REF! | I101: =IF(SUIVI!#REF!,1,0) -> #REF! | J101: =SUIVI!#REF! -> #REF! | K101: =SUIVI!#REF! -> #REF! | L101: =SUIVI!#REF! -> #REF! | M101: Parc | N101: Parc | O101: =SUIVI!#REF! -> #REF! | P101: 93
A102: =$A$12 -> CIMOLAI | B102: =SUIVI!#REF! -> #REF! | C102: =SUIVI!#REF! -> #REF! | F102: =SUIVI!#REF! -> #REF! | G102: =SUIVI!#REF! -> #REF! | H102: =IF(C102,1,0) -> #REF! | I102: =IF(SUIVI!#REF!,1,0) -> #REF! | J102: =SUIVI!#REF! -> #REF! | K102: =SUIVI!#REF! -> #REF! | L102: =SUIVI!#REF! -> #REF! | M102: Parc | N102: =SUIVI!$V$8 -> LKW | O102: =SUIVI!#REF! -> #REF! | P102: 94
...

Sheet FT-CTR
A3: ArcelorMittal Belval & Differdange S.A. | E3: Parachèvement spécial
A4: Site de Differdange
D5: MACHINE: CONTRÔLE DIMENSIONNEL | U5: POINÇONNER LE N° DE COULÉE
A6: Nom: | D6: Date: | I6: Poste: | L6: CE:
A7: Commande | B7: Profil | C7: Longueur | D7: Descriptif du travail | F7: Tronçon | G7: REP | H7: Nbre | I7: Nbre | J7: Numero | K7: Poste | L7: Poste | M7: Proven. | N7: Destin. | O7: L-LAM
C8: finie | H8: prévu | I8: réalisé | J8: laminage | K8: Asia | L8: R 3
A9: =PREVI!$A$10 -> 1100633635-636 | B9: =SUIVI!H9 -> HL1100A | C9: =SUIVI!J9 -> 10300 | D9: CONTRÔLE | F9: =SUIVI!Q9 -> 0 | G9: =SUIVI!R9 -> 0 | H9: =IF(C9,1,0) -> 1 | I9: =IF(SUIVI!U9,1,0) -> #VALUE! | J9: =SUIVI!S9 -> CZ6 | K9: =SUIVI!E9 -> 1 | L9: =SUIVI!G9 -> 10 | M9: Parc | N9: Parc | O9: =SUIVI!I9 -> 11100 | P9: 1 | T9: OPERATEUR | U9: CE | W9: MACHINE: ULTRASCHALL
A10: =PREVI!$A$11 -> Z128 | B10: =SUIVI!H10 -> HL1100A | C10: =SUIVI!J10 -> 10300 | D10: GÉOMÉTRIQUE | F10: =SUIVI!Q10 -> 0 | G10: =SUIVI!R10 -> 0 | H10: =IF(C10,1,0) -> 1 | I10: =IF(SUIVI!U10,1,0) -> #VALUE! | J10: =SUIVI!S10 -> CZ7 | K10: =SUIVI!E10 -> 1 | L10: =SUIVI!G10 -> 10 | M10: Parc | N10: =SUIVI!$V$8 -> LKW | O10: =SUIVI!I10 -> 11100 | P10: 2 | T10: VALLE | U10: VALLE | W10: MACHINE: CONTRÔLE SURFACE
A11: =PREVI!$A$12 -> 1900015151-15087 | B11: =SUIVI!H11 -> HL1100A | C11: =SUIVI!J11 -> 10400 | D11: ET | F11: =SUIVI!Q11 -> 0 | G11: =SUIVI!R11 -> 0 | H11: =IF(C11,1,0) -> 1 | I11: =IF(SUIVI!U11,1,0) -> #VALUE! | J11: =SUIVI!S11 -> CZ52 | K11: =SUIVI!E11 -> 9 | L11: =SUIVI!G11 -> 20 | M11: Parc | N11: Parc | O11: =SUIVI!I11 -> 11300 | P11: 3 | T11: MUNO | U11: WELSCHER
A12: =PREVI!$C$10 -> CIMOLAI | B12: =SUIVI!H12 -> HL1100A | C12: =SUIVI!J12 -> 9000 | D12: DIMENSIONNEL | F12: =SUIVI!Q12 -> 0 | G12: =SUIVI!R12 -> 0 | H12: =IF(C12,1,0) -> 1 | I12: =IF(SUIVI!U12,1,0) -> #VALUE! | J12: =SUIVI!S12 -> EA15 | K12: =SUIVI!E12 -> 10 | L12: =SUIVI!G12 -> 10 | M12: Parc | N12: =SUIVI!$V$8 -> LKW | O12: =SUIVI!I12 -> 9200 | P12: 4 | T12: GLODT
A13: =PREVI!$C$11 -> PASSERELLE DE BELVAL | B13: =SUIVI!H13 -> HL1100A | C13: =SUIVI!J13 -> 10100 | F13: =SUIVI!Q13 -> 0 | G13: =SUIVI!R13 -> 0 | H13: =IF(C13,1,0) -> 1 | I13: =IF(SUIVI!U13,1,0) -> #VALUE! | J13: =SUIVI!S13 -> CZ9 | K13: =SUIVI!E13 -> 2 | L13: =SUIVI!G13 -> 20 | M13: Parc | N13: Parc | O13: =SUIVI!I13 -> 10700 | P13: 5 | T13: SCHOLLER
A14: N° de plans | B14: =SUIVI!H14 -> HL1100A | C14: =SUIVI!J14 -> 10400 | F14: =SUIVI!Q14 -> 0 | G14: =SUIVI!R14 -> 0 | H14: =IF(C14,1,0) -> 1 | I14: =IF(SUIVI!U14,1,0) -> #VALUE! | J14: =SUIVI!S14 -> EC48 | K14: =SUIVI!E14 -> 38 | L14: =SUIVI!G14 -> 20 | M14: Parc | N14: =SUIVI!$V$8 -> LKW | O14: =SUIVI!I14 -> 10600 | P14: 6 | U14: POSTE
A15: =PREVI!$A$24 -> 0 | B15: =SUIVI!H15 -> HL1100A | C15: =SUIVI!J15 -> 10400 | F15: =SUIVI!Q15 -> 0 | G15: =SUIVI!R15 -> 0 | H15: =IF(C15,1,0) -> 1 | I15: =IF(SUIVI!U15,1,0) -> #VALUE! | J15: =SUIVI!S15 -> EC49 | K15: =SUIVI!E15 -> 38 | L15: =SUIVI!G15 -> 20 | M15: Parc | N15: Parc | O15: =SUIVI!I15 -> 10600 | P15: 7 | U15: 06-14
A16: =PREVI!$A$25 -> 0 | B16: =SUIVI!H16 -> HL1100A | C16: =SUIVI!J16 -> 10400 | F16: =SUIVI!Q16 -> 0 | G16: =SUIVI!R16 -> 0 | H16: =IF(C16,1,0) -> 1 | I16: =IF(SUIVI!U16,1,0) -> #VALUE! | J16: =SUIVI!S16 -> EC50 | K16: =SUIVI!E16 -> 38 | L16: =SUIVI!G16 -> 30 | M16: Parc | N16: =SUIVI!$V$8 -> LKW | O16: =SUIVI!I16 -> 10600 | P16: 8 | U16: 14-22
A17: =PREVI!$A$26 -> 0 | B17: =SUIVI!H17 -> HL1100A | C17: =SUIVI!J17 -> 10400 | F17: =SUIVI!Q17 -> 0 | G17: =SUIVI!R17 -> 0 | H17: =IF(C17,1,0) -> 1 | I17: =IF(SUIVI!U17,1,0) -> #VALUE! | J17: =SUIVI!S17 -> EC51 | K17: =SUIVI!E17 -> 38 | L17: =SUIVI!G17 -> 30 | M17: Parc | N17: Parc | O17: =SUIVI!I17 -> 10600 | P17: 9 | U17: 22-06
A18: =$A$9 -> 1100633635-636 | B18: =SUIVI!H18 -> HL1100B | C18: =SUIVI!J18 -> 5300 | F18: =SUIVI!Q18 -> 0 | G18: =SUIVI!R18 -> 0 | H18: =IF(C18,1,0) -> 1 | I18: =IF(SUIVI!U18,1,0) -> #VALUE! | J18: =SUIVI!S18 -> EC407 | K18: =SUIVI!E18 -> 27 | L18: =SUIVI!G18 -> 40 | M18: Parc | N18: =SUIVI!$V$8 -> LKW | O18: =SUIVI!I18 -> 15800 | P18: 10
A19: =$A$10 -> Z128 | P19: 11
A20: =$A$11 -> 1900015151-15087 | P20: 12
A21: =$A$12 -> CIMOLAI | P21: 13 | S21: LG DE CHARGEMENT MAXI SUR CAMION
A22: =$A$13 -> PASSERELLE DE BELVAL | P22: 14 | S22: 22000 | T22: MAXI RECOMMANDÉ
A23: N° de plans | P23: 15 | S23: 23000 | T23: A VÉRIFIER
A24: =$A$15 -> 0 | P24: 16 | S24: 24000 | T24: fait avec casse rétroviseur
A25: =$A$16 -> 0 | P25: 17
A26: =$A$17 -> 0 | P26: 18
A27: =$A$9 -> 1100633635-636 | P27: 19
A28: =$A$10 -> Z128 | P28: 20
A29: =$A$11 -> 1900015151-15087 | P29: 21
A30: =$A$12 -> CIMOLAI | P30: 22
A31: =$A$13 -> PASSERELLE DE BELVAL | P31: 23
A32: N° de plans | P32: 24
A33: =$A$15 -> 0 | P33: 25
A34: =$A$16 -> 0 | P34: 26
A35: =$A$17 -> 0 | P35: 27
A36: =$A$9 -> 1100633635-636 | B36: =SUIVI!#REF! -> #REF! | C36: =SUIVI!#REF! -> #REF! | F36: =SUIVI!#REF! -> #REF! | G36: =SUIVI!#REF! -> #REF! | H36: =IF(C36,1,0) -> #REF! | I36: =IF(SUIVI!#REF!,1,0) -> #REF! | J36: =SUIVI!#REF! -> #REF! | K36: =SUIVI!#REF! -> #REF! | L36: =SUIVI!#REF! -> #REF! | P36: 28
A37: =$A$10 -> Z128 | B37: =SUIVI!#REF! -> #REF! | C37: =SUIVI!#REF! -> #REF! | F37: =SUIVI!#REF! -> #REF! | G37: =SUIVI!#REF! -> #REF! | H37: =IF(C37,1,0) -> #REF! | I37: =IF(SUIVI!#REF!,1,0) -> #REF! | J37: =SUIVI!#REF! -> #REF! | K37: =SUIVI!#REF! -> #REF! | L37: =SUIVI!#REF! -> #REF! | P37: 29
A38: =$A$11 -> 1900015151-15087 | B38: =SUIVI!#REF! -> #REF! | C38: =SUIVI!#REF! -> #REF! | F38: =SUIVI!#REF! -> #REF! | G38: =SUIVI!#REF! -> #REF! | H38: =IF(C38,1,0) -> #REF! | I38: =IF(SUIVI!#REF!,1,0) -> #REF! | J38: =SUIVI!#REF! -> #REF! | K38: =SUIVI!#REF! -> #REF! | L38: =SUIVI!#REF! -> #REF! | P38: 30
A39: =$A$12 -> CIMOLAI | B39: =SUIVI!#REF! -> #REF! | C39: =SUIVI!#REF! -> #REF! | F39: =SUIVI!#REF! -> #REF! | G39: =SUIVI!#REF! -> #REF! | H39: =IF(C39,1,0) -> #REF! | I39: =IF(SUIVI!#REF!,1,0) -> #REF! | J39: =SUIVI!#REF! -> #REF! | K39: =SUIVI!#REF! -> #REF! | L39: =SUIVI!#REF! -> #REF! | P39: 31
A40: =$A$13 -> PASSERELLE DE BELVAL | B40: =SUIVI!#REF! -> #REF! | C40: =SUIVI!#REF! -> #REF! | F40: =SUIVI!#REF! -> #REF! | G40: =SUIVI!#REF! -> #REF! | H40: =IF(C40,1,0) -> #REF! | I40: =IF(SUIVI!#REF!,1,0) -> #REF! | J40: =SUIVI!#REF! -> #REF! | K40: =SUIVI!#REF! -> #REF! | L40: =SUIVI!#REF! -> #REF! | M40: Parc | N40: =SUIVI!$V$8 -> LKW | O40: =SUIVI!#REF! -> #REF! | P40: 32
A41: N° de plans | B41: =SUIVI!#REF! -> #REF! | C41: =SUIVI!#REF! -> #REF! | F41: =SUIVI!#REF! -> #REF! | G41: =SUIVI!#REF! -> #REF! | H41: =IF(C41,1,0) -> #REF! | I41: =IF(SUIVI!#REF!,1,0) -> #REF! | J41: =SUIVI!#REF! -> #REF! | K41: =SUIVI!#REF! -> #REF! | L41: =SUIVI!#REF! -> #REF! | M41: Parc | N41: Parc | O41: =SUIVI!#REF! -> #REF! | P41: 33
A42: =$A$15 -> 0 | B42: =SUIVI!#REF! -> #REF! | C42: =SUIVI!#REF! -> #REF! | F42: =SUIVI!#REF! -> #REF! | G42: =SUIVI!#REF! -> #REF! | H42: =IF(C42,1,0) -> #REF! | I42: =IF(SUIVI!#REF!,1,0) -> #REF! | J42: =SUIVI!#REF! -> #REF! | K42: =SUIVI!#REF! -> #REF! | L42: =SUIVI!#REF! -> #REF! | M42: Parc | N42: =SUIVI!$V$8 -> LKW | O42: =SUIVI!#REF! -> #REF! | P42: 34
A43: =$A$16 -> 0 | B43: =SUIVI!#REF! -> #REF! | C43: =SUIVI!#REF! -> #REF! | F43: =SUIVI!#REF! -> #REF! | G43: =SUIVI!#REF! -> #REF! | H43: =IF(C43,1,0) -> #REF! | I43: =IF(SUIVI!#REF!,1,0) -> #REF! | J43: =SUIVI!#REF! -> #REF! | K43: =SUIVI!#REF! -> #REF! | L43: =SUIVI!#REF! -> #REF! | M43: Parc | N43: Parc | O43: =SUIVI!#REF! -> #REF! | P43: 35
A44: =$A$17 -> 0 | B44: =SUIVI!#REF! -> #REF! | C44: =SUIVI!#REF! -> #REF! | F44: =SUIVI!#REF! -> #REF! | G44: =SUIVI!#REF! -> #REF! | H44: =IF(C44,1,0) -> #REF! | I44: =IF(SUIVI!#REF!,1,0) -> #REF! | J44: =SUIVI!#REF! -> #REF! | K44: =SUIVI!#REF! -> #REF! | L44: =SUIVI!#REF! -> #REF! | M44: Parc | N44: =SUIVI!$V$8 -> LKW | O44: =SUIVI!#REF! -> #REF! | P44: 36
A45: =$A$9 -> 1100633635-636 | B45: =SUIVI!#REF! -> #REF! | C45: =SUIVI!#REF! -> #REF! | F45: =SUIVI!#REF! -> #REF! | G45: =SUIVI!#REF! -> #REF! | H45: =IF(C45,1,0) -> #REF! | I45: =IF(SUIVI!#REF!,1,0) -> #REF! | J45: =SUIVI!#REF! -> #REF! | K45: =SUIVI!#REF! -> #REF! | L45: =SUIVI!#REF! -> #REF! | M45: Parc | N45: Parc | O45: =SUIVI!#REF! -> #REF! | P45: 37
A46: =$A$10 -> Z128 | B46: =SUIVI!#REF! -> #REF! | C46: =SUIVI!#REF! -> #REF! | F46: =SUIVI!#REF! -> #REF! | G46: =SUIVI!#REF! -> #REF! | H46: =IF(C46,1,0) -> #REF! | I46: =IF(SUIVI!#REF!,1,0) -> #REF! | J46: =SUIVI!#REF! -> #REF! | K46: =SUIVI!#REF! -> #REF! | L46: =SUIVI!#REF! -> #REF! | M46: Parc | N46: =SUIVI!$V$8 -> LKW | O46: =SUIVI!#REF! -> #REF! | P46: 38
A47: =$A$11 -> 1900015151-15087 | B47: =SUIVI!#REF! -> #REF! | C47: =SUIVI!#REF! -> #REF! | F47: =SUIVI!#REF! -> #REF! | G47: =SUIVI!#REF! -> #REF! | H47: =IF(C47,1,0) -> #REF! | I47: =IF(SUIVI!#REF!,1,0) -> #REF! | J47: =SUIVI!#REF! -> #REF! | K47: =SUIVI!#REF! -> #REF! | L47: =SUIVI!#REF! -> #REF! | M47: Parc | N47: Parc | O47: =SUIVI!#REF! -> #REF! | P47: 39
A48: =$A$12 -> CIMOLAI | B48: =SUIVI!#REF! -> #REF! | C48: =SUIVI!#REF! -> #REF! | F48: =SUIVI!#REF! -> #REF! | G48: =SUIVI!#REF! -> #REF! | H48: =IF(C48,1,0) -> #REF! | I48: =IF(SUIVI!#REF!,1,0) -> #REF! | J48: =SUIVI!#REF! -> #REF! | K48: =SUIVI!#REF! -> #REF! | L48: =SUIVI!#REF! -> #REF! | M48: Parc | N48: =SUIVI!$V$8 -> LKW | O48: =SUIVI!#REF! -> #REF! | P48: 40
A49: =$A$13 -> PASSERELLE DE BELVAL | B49: =SUIVI!#REF! -> #REF! | C49: =SUIVI!#REF! -> #REF! | F49: =SUIVI!#REF! -> #REF! | G49: =SUIVI!#REF! -> #REF! | H49: =IF(C49,1,0) -> #REF! | I49: =IF(SUIVI!#REF!,1,0) -> #REF! | J49: =SUIVI!#REF! -> #REF! | K49: =SUIVI!#REF! -> #REF! | L49: =SUIVI!#REF! -> #REF! | M49: Parc | N49: Parc | O49: =SUIVI!#REF! -> #REF! | P49: 41
A50: N° de plans | B50: =SUIVI!#REF! -> #REF! | C50: =SUIVI!#REF! -> #REF! | F50: =SUIVI!#REF! -> #REF! | G50: =SUIVI!#REF! -> #REF! | H50: =IF(C50,1,0) -> #REF! | I50: =IF(SUIVI!#REF!,1,0) -> #REF! | J50: =SUIVI!#REF! -> #REF! | K50: =SUIVI!#REF! -> #REF! | L50: =SUIVI!#REF! -> #REF! | M50: Parc | N50: =SUIVI!$V$8 -> LKW | O50: =SUIVI!#REF! -> #REF! | P50: 42
A51: =$A$15 -> 0 | B51: =SUIVI!#REF! -> #REF! | C51: =SUIVI!#REF! -> #REF! | F51: =SUIVI!#REF! -> #REF! | G51: =SUIVI!#REF! -> #REF! | H51: =IF(C51,1,0) -> #REF! | I51: =IF(SUIVI!#REF!,1,0) -> #REF! | J51: =SUIVI!#REF! -> #REF! | K51: =SUIVI!#REF! -> #REF! | L51: =SUIVI!#REF! -> #REF! | M51: Parc | N51: Parc | O51: =SUIVI!#REF! -> #REF! | P51: 43
A52: =$A$16 -> 0 | B52: =SUIVI!#REF! -> #REF! | C52: =SUIVI!#REF! -> #REF! | F52: =SUIVI!#REF! -> #REF! | G52: =SUIVI!#REF! -> #REF! | H52: =IF(C52,1,0) -> #REF! | I52: =IF(SUIVI!#REF!,1,0) -> #REF! | J52: =SUIVI!#REF! -> #REF! | K52: =SUIVI!#REF! -> #REF! | L52: =SUIVI!#REF! -> #REF! | M52: Parc | N52: =SUIVI!$V$8 -> LKW | O52: =SUIVI!#REF! -> #REF! | P52: 44
A53: =$A$17 -> 0 | B53: =SUIVI!#REF! -> #REF! | C53: =SUIVI!#REF! -> #REF! | F53: =SUIVI!#REF! -> #REF! | G53: =SUIVI!#REF! -> #REF! | H53: =IF(C53,1,0) -> #REF! | I53: =IF(SUIVI!#REF!,1,0) -> #REF! | J53: =SUIVI!#REF! -> #REF! | K53: =SUIVI!#REF! -> #REF! | L53: =SUIVI!#REF! -> #REF! | M53: Parc | N53: Parc | O53: =SUIVI!#REF! -> #REF! | P53: 45
A54: =$A$9 -> 1100633635-636 | B54: =SUIVI!#REF! -> #REF! | C54: =SUIVI!#REF! -> #REF! | F54: =SUIVI!#REF! -> #REF! | G54: =SUIVI!#REF! -> #REF! | H54: =IF(C54,1,0) -> #REF! | I54: =IF(SUIVI!#REF!,1,0) -> #REF! | J54: =SUIVI!#REF! -> #REF! | K54: =SUIVI!#REF! -> #REF! | L54: =SUIVI!#REF! -> #REF! | M54: Parc | N54: =SUIVI!$V$8 -> LKW | O54: =SUIVI!#REF! -> #REF! | P54: 46
A55: =$A$10 -> Z128 | B55: =SUIVI!#REF! -> #REF! | C55: =SUIVI!#REF! -> #REF! | F55: =SUIVI!#REF! -> #REF! | G55: =SUIVI!#REF! -> #REF! | H55: =IF(C55,1,0) -> #REF! | I55: =IF(SUIVI!#REF!,1,0) -> #REF! | J55: =SUIVI!#REF! -> #REF! | K55: =SUIVI!#REF! -> #REF! | L55: =SUIVI!#REF! -> #REF! | M55: Parc | N55: Parc | O55: =SUIVI!#REF! -> #REF! | P55: 47
A56: =$A$11 -> 1900015151-15087 | B56: =SUIVI!#REF! -> #REF! | C56: =SUIVI!#REF! -> #REF! | F56: =SUIVI!#REF! -> #REF! | G56: =SUIVI!#REF! -> #REF! | H56: =IF(C56,1,0) -> #REF! | I56: =IF(SUIVI!#REF!,1,0) -> #REF! | J56: =SUIVI!#REF! -> #REF! | K56: =SUIVI!#REF! -> #REF! | L56: =SUIVI!#REF! -> #REF! | M56: Parc | N56: =SUIVI!$V$8 -> LKW | O56: =SUIVI!#REF! -> #REF! | P56: 48
A57: =$A$12 -> CIMOLAI | B57: =SUIVI!#REF! -> #REF! | C57: =SUIVI!#REF! -> #REF! | F57: =SUIVI!#REF! -> #REF! | G57: =SUIVI!#REF! -> #REF! | H57: =IF(C57,1,0) -> #REF! | I57: =IF(SUIVI!#REF!,1,0) -> #REF! | J57: =SUIVI!#REF! -> #REF! | K57: =SUIVI!#REF! -> #REF! | L57: =SUIVI!#REF! -> #REF! | M57: Parc | N57: Parc | O57: =SUIVI!#REF! -> #REF! | P57: 49
A58: =$A$13 -> PASSERELLE DE BELVAL | B58: =SUIVI!#REF! -> #REF! | C58: =SUIVI!#REF! -> #REF! | F58: =SUIVI!#REF! -> #REF! | G58: =SUIVI!#REF! -> #REF! | H58: =IF(C58,1,0) -> #REF! | I58: =IF(SUIVI!#REF!,1,0) -> #REF! | J58: =SUIVI!#REF! -> #REF! | K58: =SUIVI!#REF! -> #REF! | L58: =SUIVI!#REF! -> #REF! | M58: Parc | N58: =SUIVI!$V$8 -> LKW | O58: =SUIVI!#REF! -> #REF! | P58: 50
A59: N° de plans | B59: =SUIVI!#REF! -> #REF! | C59: =SUIVI!#REF! -> #REF! | F59: =SUIVI!#REF! -> #REF! | G59: =SUIVI!#REF! -> #REF! | H59: =IF(C59,1,0) -> #REF! | I59: =IF(SUIVI!#REF!,1,0) -> #REF! | J59: =SUIVI!#REF! -> #REF! | K59: =SUIVI!#REF! -> #REF! | L59: =SUIVI!#REF! -> #REF! | M59: Parc | N59: Parc | O59: =SUIVI!#REF! -> #REF! | P59: 51
A60: =$A$15 -> 0 | B60: =SUIVI!#REF! -> #REF! | C60: =SUIVI!#REF! -> #REF! | F60: =SUIVI!#REF! -> #REF! | G60: =SUIVI!#REF! -> #REF! | H60: =IF(C60,1,0) -> #REF! | I60: =IF(SUIVI!#REF!,1,0) -> #REF! | J60: =SUIVI!#REF! -> #REF! | K60: =SUIVI!#REF! -> #REF! | L60: =SUIVI!#REF! -> #REF! | M60: Parc | N60: =SUIVI!$V$8 -> LKW | O60: =SUIVI!#REF! -> #REF! | P60: 52
A61: =$A$16 -> 0 | B61: =SUIVI!#REF! -> #REF! | C61: =SUIVI!#REF! -> #REF! | F61: =SUIVI!#REF! -> #REF! | G61: =SUIVI!#REF! -> #REF! | H61: =IF(C61,1,0) -> #REF! | I61: =IF(SUIVI!#REF!,1,0) -> #REF! | J61: =SUIVI!#REF! -> #REF! | K61: =SUIVI!#REF! -> #REF! | L61: =SUIVI!#REF! -> #REF! | M61: Parc | N61: Parc | O61: =SUIVI!#REF! -> #REF! | P61: 53
A62: =$A$17 -> 0 | B62: =SUIVI!#REF! -> #REF! | C62: =SUIVI!#REF! -> #REF! | F62: =SUIVI!#REF! -> #REF! | G62: =SUIVI!#REF! -> #REF! | H62: =IF(C62,1,0) -> #REF! | I62: =IF(SUIVI!#REF!,1,0) -> #REF! | J62: =SUIVI!#REF! -> #REF! | K62: =SUIVI!#REF! -> #REF! | L62: =SUIVI!#REF! -> #REF! | M62: Parc | N62: =SUIVI!$V$8 -> LKW | O62: =SUIVI!#REF! -> #REF! | P62: 54
A63: =$A$9 -> 1100633635-636 | B63: =SUIVI!#REF! -> #REF! | C63: =SUIVI!#REF! -> #REF! | F63: =SUIVI!#REF! -> #REF! | G63: =SUIVI!#REF! -> #REF! | H63: =IF(C63,1,0) -> #REF! | I63: =IF(SUIVI!#REF!,1,0) -> #REF! | J63: =SUIVI!#REF! -> #REF! | K63: =SUIVI!#REF! -> #REF! | L63: =SUIVI!#REF! -> #REF! | M63: Parc | N63: Parc | O63: =SUIVI!#REF! -> #REF! | P63: 55
A64: =$A$10 -> Z128 | B64: =SUIVI!#REF! -> #REF! | C64: =SUIVI!#REF! -> #REF! | F64: =SUIVI!#REF! -> #REF! | G64: =SUIVI!#REF! -> #REF! | H64: =IF(C64,1,0) -> #REF! | I64: =IF(SUIVI!#REF!,1,0) -> #REF! | J64: =SUIVI!#REF! -> #REF! | K64: =SUIVI!#REF! -> #REF! | L64: =SUIVI!#REF! -> #REF! | M64: Parc | N64: =SUIVI!$V$8 -> LKW | O64: =SUIVI!#REF! -> #REF! | P64: 56
A65: =$A$11 -> 1900015151-15087 | B65: =SUIVI!#REF! -> #REF! | C65: =SUIVI!#REF! -> #REF! | F65: =SUIVI!#REF! -> #REF! | G65: =SUIVI!#REF! -> #REF! | H65: =IF(C65,1,0) -> #REF! | I65: =IF(SUIVI!#REF!,1,0) -> #REF! | J65: =SUIVI!#REF! -> #REF! | K65: =SUIVI!#REF! -> #REF! | L65: =SUIVI!#REF! -> #REF! | M65: Parc | N65: Parc | O65: =SUIVI!#REF! -> #REF! | P65: 57
A66: =$A$12 -> CIMOLAI | B66: =SUIVI!#REF! -> #REF! | C66: =SUIVI!#REF! -> #REF! | F66: =SUIVI!#REF! -> #REF! | G66: =SUIVI!#REF! -> #REF! | H66: =IF(C66,1,0) -> #REF! | I66: =IF(SUIVI!#REF!,1,0) -> #REF! | J66: =SUIVI!#REF! -> #REF! | K66: =SUIVI!#REF! -> #REF! | L66: =SUIVI!#REF! -> #REF! | M66: Parc | N66: =SUIVI!$V$8 -> LKW | O66: =SUIVI!#REF! -> #REF! | P66: 58
A67: =$A$13 -> PASSERELLE DE BELVAL | B67: =SUIVI!#REF! -> #REF! | C67: =SUIVI!#REF! -> #REF! | F67: =SUIVI!#REF! -> #REF! | G67: =SUIVI!#REF! -> #REF! | H67: =IF(C67,1,0) -> #REF! | I67: =IF(SUIVI!#REF!,1,0) -> #REF! | J67: =SUIVI!#REF! -> #REF! | K67: =SUIVI!#REF! -> #REF! | L67: =SUIVI!#REF! -> #REF! | M67: Parc | N67: Parc | O67: =SUIVI!#REF! -> #REF! | P67: 59
A68: N° de plans | B68: =SUIVI!#REF! -> #REF! | C68: =SUIVI!#REF! -> #REF! | F68: =SUIVI!#REF! -> #REF! | G68: =SUIVI!#REF! -> #REF! | H68: =IF(C68,1,0) -> #REF! | I68: =IF(SUIVI!#REF!,1,0) -> #REF! | J68: =SUIVI!#REF! -> #REF! | K68: =SUIVI!#REF! -> #REF! | L68: =SUIVI!#REF! -> #REF! | M68: Parc | N68: =SUIVI!$V$8 -> LKW | O68: =SUIVI!#REF! -> #REF! | P68: 60
A69: =$A$15 -> 0 | B69: =SUIVI!#REF! -> #REF! | C69: =SUIVI!#REF! -> #REF! | F69: =SUIVI!#REF! -> #REF! | G69: =SUIVI!#REF! -> #REF! | H69: =IF(C69,1,0) -> #REF! | I69: =IF(SUIVI!#REF!,1,0) -> #REF! | J69: =SUIVI!#REF! -> #REF! | K69: =SUIVI!#REF! -> #REF! | L69: =SUIVI!#REF! -> #REF! | M69: Parc | N69: Parc | O69: =SUIVI!#REF! -> #REF! | P69: 61
A70: =$A$16 -> 0 | B70: =SUIVI!#REF! -> #REF! | C70: =SUIVI!#REF! -> #REF! | F70: =SUIVI!#REF! -> #REF! | G70: =SUIVI!#REF! -> #REF! | H70: =IF(C70,1,0) -> #REF! | I70: =IF(SUIVI!#REF!,1,0) -> #REF! | J70: =SUIVI!#REF! -> #REF! | K70: =SUIVI!#REF! -> #REF! | L70: =SUIVI!#REF! -> #REF! | M70: Parc | N70: =SUIVI!$V$8 -> LKW | O70: =SUIVI!#REF! -> #REF! | P70: 62
A71: =$A$17 -> 0 | B71: =SUIVI!#REF! -> #REF! | C71: =SUIVI!#REF! -> #REF! | F71: =SUIVI!#REF! -> #REF! | G71: =SUIVI!#REF! -> #REF! | H71: =IF(C71,1,0) -> #REF! | I71: =IF(SUIVI!#REF!,1,0) -> #REF! | J71: =SUIVI!#REF! -> #REF! | K71: =SUIVI!#REF! -> #REF! | L71: =SUIVI!#REF! -> #REF! | M71: Parc | N71: Parc | O71: =SUIVI!#REF! -> #REF! | P71: 63
A72: =$A$9 -> 1100633635-636 | B72: =SUIVI!#REF! -> #REF! | C72: =SUIVI!#REF! -> #REF! | F72: =SUIVI!#REF! -> #REF! | G72: =SUIVI!#REF! -> #REF! | H72: =IF(C72,1,0) -> #REF! | I72: =IF(SUIVI!#REF!,1,0) -> #REF! | J72: =SUIVI!#REF! -> #REF! | K72: =SUIVI!#REF! -> #REF! | L72: =SUIVI!#REF! -> #REF! | M72: Parc | N72: =SUIVI!$V$8 -> LKW | O72: =SUIVI!#REF! -> #REF! | P72: 64
A73: =$A$10 -> Z128 | B73: =SUIVI!#REF! -> #REF! | C73: =SUIVI!#REF! -> #REF! | F73: =SUIVI!#REF! -> #REF! | G73: =SUIVI!#REF! -> #REF! | H73: =IF(C73,1,0) -> #REF! | I73: =IF(SUIVI!#REF!,1,0) -> #REF! | J73: =SUIVI!#REF! -> #REF! | K73: =SUIVI!#REF! -> #REF! | L73: =SUIVI!#REF! -> #REF! | M73: Parc | N73: Parc | O73: =SUIVI!#REF! -> #REF! | P73: 65
A74: =$A$11 -> 1900015151-15087 | B74: =SUIVI!#REF! -> #REF! | C74: =SUIVI!#REF! -> #REF! | F74: =SUIVI!#REF! -> #REF! | G74: =SUIVI!#REF! -> #REF! | H74: =IF(C74,1,0) -> #REF! | I74: =IF(SUIVI!#REF!,1,0) -> #REF! | J74: =SUIVI!#REF! -> #REF! | K74: =SUIVI!#REF! -> #REF! | L74: =SUIVI!#REF! -> #REF! | M74: Parc | N74: =SUIVI!$V$8 -> LKW | O74: =SUIVI!#REF! -> #REF! | P74: 66
A75: =$A$12 -> CIMOLAI | B75: =SUIVI!#REF! -> #REF! | C75: =SUIVI!#REF! -> #REF! | F75: =SUIVI!#REF! -> #REF! | G75: =SUIVI!#REF! -> #REF! | H75: =IF(C75,1,0) -> #REF! | I75: =IF(SUIVI!#REF!,1,0) -> #REF! | J75: =SUIVI!#REF! -> #REF! | K75: =SUIVI!#REF! -> #REF! | L75: =SUIVI!#REF! -> #REF! | M75: Parc | N75: Parc | O75: =SUIVI!#REF! -> #REF! | P75: 67
A76: =$A$13 -> PASSERELLE DE BELVAL | B76: =SUIVI!#REF! -> #REF! | C76: =SUIVI!#REF! -> #REF! | F76: =SUIVI!#REF! -> #REF! | G76: =SUIVI!#REF! -> #REF! | H76: =IF(C76,1,0) -> #REF! | I76: =IF(SUIVI!#REF!,1,0) -> #REF! | J76: =SUIVI!#REF! -> #REF! | K76: =SUIVI!#REF! -> #REF! | L76: =SUIVI!#REF! -> #REF! | M76: Parc | N76: =SUIVI!$V$8 -> LKW | O76: =SUIVI!#REF! -> #REF! | P76: 68
A77: N° de plans | B77: =SUIVI!#REF! -> #REF! | C77: =SUIVI!#REF! -> #REF! | F77: =SUIVI!#REF! -> #REF! | G77: =SUIVI!#REF! -> #REF! | H77: =IF(C77,1,0) -> #REF! | I77: =IF(SUIVI!#REF!,1,0) -> #REF! | J77: =SUIVI!#REF! -> #REF! | K77: =SUIVI!#REF! -> #REF! | L77: =SUIVI!#REF! -> #REF! | M77: Parc | N77: Parc | O77: =SUIVI!#REF! -> #REF! | P77: 69
A78: =$A$15 -> 0 | B78: =SUIVI!#REF! -> #REF! | C78: =SUIVI!#REF! -> #REF! | F78: =SUIVI!#REF! -> #REF! | G78: =SUIVI!#REF! -> #REF! | H78: =IF(C78,1,0) -> #REF! | I78: =IF(SUIVI!#REF!,1,0) -> #REF! | J78: =SUIVI!#REF! -> #REF! | K78: =SUIVI!#REF! -> #REF! | L78: =SUIVI!#REF! -> #REF! | M78: Parc | N78: =SUIVI!$V$8 -> LKW | O78: =SUIVI!#REF! -> #REF! | P78: 70
A79: =$A$16 -> 0 | B79: =SUIVI!#REF! -> #REF! | C79: =SUIVI!#REF! -> #REF! | F79: =SUIVI!#REF! -> #REF! | G79: =SUIVI!#REF! -> #REF! | H79: =IF(C79,1,0) -> #REF! | I79: =IF(SUIVI!#REF!,1,0) -> #REF! | J79: =SUIVI!#REF! -> #REF! | K79: =SUIVI!#REF! -> #REF! | L79: =SUIVI!#REF! -> #REF! | M79: Parc | N79: Parc | O79: =SUIVI!#REF! -> #REF! | P79: 71
A80: =$A$17 -> 0 | B80: =SUIVI!#REF! -> #REF! | C80: =SUIVI!#REF! -> #REF! | F80: =SUIVI!#REF! -> #REF! | G80: =SUIVI!#REF! -> #REF! | H80: =IF(C80,1,0) -> #REF! | I80: =IF(SUIVI!#REF!,1,0) -> #REF! | J80: =SUIVI!#REF! -> #REF! | K80: =SUIVI!#REF! -> #REF! | L80: =SUIVI!#REF! -> #REF! | M80: Parc | N80: =SUIVI!$V$8 -> LKW | O80: =SUIVI!#REF! -> #REF! | P80: 72
A81: =$A$9 -> 1100633635-636 | B81: =SUIVI!#REF! -> #REF! | C81: =SUIVI!#REF! -> #REF! | F81: =SUIVI!#REF! -> #REF! | G81: =SUIVI!#REF! -> #REF! | H81: =IF(C81,1,0) -> #REF! | I81: =IF(SUIVI!#REF!,1,0) -> #REF! | J81: =SUIVI!#REF! -> #REF! | K81: =SUIVI!#REF! -> #REF! | L81: =SUIVI!#REF! -> #REF! | M81: Parc | N81: Parc | O81: =SUIVI!#REF! -> #REF! | P81: 73
A82: =$A$10 -> Z128 | B82: =SUIVI!#REF! -> #REF! | C82: =SUIVI!#REF! -> #REF! | F82: =SUIVI!#REF! -> #REF! | G82: =SUIVI!#REF! -> #REF! | H82: =IF(C82,1,0) -> #REF! | I82: =IF(SUIVI!#REF!,1,0) -> #REF! | J82: =SUIVI!#REF! -> #REF! | K82: =SUIVI!#REF! -> #REF! | L82: =SUIVI!#REF! -> #REF! | M82: Parc | N82: =SUIVI!$V$8 -> LKW | O82: =SUIVI!#REF! -> #REF! | P82: 74
A83: =$A$11 -> 1900015151-15087 | B83: =SUIVI!#REF! -> #REF! | C83: =SUIVI!#REF! -> #REF! | F83: =SUIVI!#REF! -> #REF! | G83: =SUIVI!#REF! -> #REF! | H83: =IF(C83,1,0) -> #REF! | I83: =IF(SUIVI!#REF!,1,0) -> #REF! | J83: =SUIVI!#REF! -> #REF! | K83: =SUIVI!#REF! -> #REF! | L83: =SUIVI!#REF! -> #REF! | M83: Parc | N83: Parc | O83: =SUIVI!#REF! -> #REF! | P83: 75
A84: =$A$12 -> CIMOLAI | B84: =SUIVI!#REF! -> #REF! | C84: =SUIVI!#REF! -> #REF! | F84: =SUIVI!#REF! -> #REF! | G84: =SUIVI!#REF! -> #REF! | H84: =IF(C84,1,0) -> #REF! | I84: =IF(SUIVI!#REF!,1,0) -> #REF! | J84: =SUIVI!#REF! -> #REF! | K84: =SUIVI!#REF! -> #REF! | L84: =SUIVI!#REF! -> #REF! | M84: Parc | N84: =SUIVI!$V$8 -> LKW | O84: =SUIVI!#REF! -> #REF! | P84: 76
A85: =$A$13 -> PASSERELLE DE BELVAL | B85: =SUIVI!#REF! -> #REF! | C85: =SUIVI!#REF! -> #REF! | F85: =SUIVI!#REF! -> #REF! | G85: =SUIVI!#REF! -> #REF! | H85: =IF(C85,1,0) -> #REF! | I85: =IF(SUIVI!#REF!,1,0) -> #REF! | J85: =SUIVI!#REF! -> #REF! | K85: =SUIVI!#REF! -> #REF! | L85: =SUIVI!#REF! -> #REF! | M85: Parc | N85: Parc | O85: =SUIVI!#REF! -> #REF! | P85: 77
A86: N° de plans | B86: =SUIVI!#REF! -> #REF! | C86: =SUIVI!#REF! -> #REF! | F86: =SUIVI!#REF! -> #REF! | G86: =SUIVI!#REF! -> #REF! | H86: =IF(C86,1,0) -> #REF! | I86: =IF(SUIVI!#REF!,1,0) -> #REF! | J86: =SUIVI!#REF! -> #REF! | K86: =SUIVI!#REF! -> #REF! | L86: =SUIVI!#REF! -> #REF! | M86: Parc | N86: =SUIVI!$V$8 -> LKW | O86: =SUIVI!#REF! -> #REF! | P86: 78
A87: =$A$15 -> 0 | B87: =SUIVI!#REF! -> #REF! | C87: =SUIVI!#REF! -> #REF! | F87: =SUIVI!#REF! -> #REF! | G87: =SUIVI!#REF! -> #REF! | H87: =IF(C87,1,0) -> #REF! | I87: =IF(SUIVI!#REF!,1,0) -> #REF! | J87: =SUIVI!#REF! -> #REF! | K87: =SUIVI!#REF! -> #REF! | L87: =SUIVI!#REF! -> #REF! | M87: Parc | N87: Parc | O87: =SUIVI!#REF! -> #REF! | P87: 79
A88: =$A$16 -> 0 | B88: =SUIVI!#REF! -> #REF! | C88: =SUIVI!#REF! -> #REF! | F88: =SUIVI!#REF! -> #REF! | G88: =SUIVI!#REF! -> #REF! | H88: =IF(C88,1,0) -> #REF! | I88: =IF(SUIVI!#REF!,1,0) -> #REF! | J88: =SUIVI!#REF! -> #REF! | K88: =SUIVI!#REF! -> #REF! | L88: =SUIVI!#REF! -> #REF! | M88: Parc | N88: =SUIVI!$V$8 -> LKW | O88: =SUIVI!#REF! -> #REF! | P88: 80
A89: =$A$17 -> 0 | B89: =SUIVI!#REF! -> #REF! | C89: =SUIVI!#REF! -> #REF! | F89: =SUIVI!#REF! -> #REF! | G89: =SUIVI!#REF! -> #REF! | H89: =IF(C89,1,0) -> #REF! | I89: =IF(SUIVI!#REF!,1,0) -> #REF! | J89: =SUIVI!#REF! -> #REF! | K89: =SUIVI!#REF! -> #REF! | L89: =SUIVI!#REF! -> #REF! | M89: Parc | N89: Parc | O89: =SUIVI!#REF! -> #REF! | P89: 81
A90: =$A$9 -> 1100633635-636 | B90: =SUIVI!#REF! -> #REF! | C90: =SUIVI!#REF! -> #REF! | F90: =SUIVI!#REF! -> #REF! | G90: =SUIVI!#REF! -> #REF! | H90: =IF(C90,1,0) -> #REF! | I90: =IF(SUIVI!#REF!,1,0) -> #REF! | J90: =SUIVI!#REF! -> #REF! | K90: =SUIVI!#REF! -> #REF! | L90: =SUIVI!#REF! -> #REF! | M90: Parc | N90: =SUIVI!$V$8 -> LKW | O90: =SUIVI!#REF! -> #REF! | P90: 82
A91: =$A$10 -> Z128 | B91: =SUIVI!#REF! -> #REF! | C91: =SUIVI!#REF! -> #REF! | F91: =SUIVI!#REF! -> #REF! | G91: =SUIVI!#REF! -> #REF! | H91: =IF(C91,1,0) -> #REF! | I91: =IF(SUIVI!#REF!,1,0) -> #REF! | J91: =SUIVI!#REF! -> #REF! | K91: =SUIVI!#REF! -> #REF! | L91: =SUIVI!#REF! -> #REF! | M91: Parc | N91: Parc | O91: =SUIVI!#REF! -> #REF! | P91: 83
A92: =$A$11 -> 1900015151-15087 | B92: =SUIVI!#REF! -> #REF! | C92: =SUIVI!#REF! -> #REF! | F92: =SUIVI!#REF! -> #REF! | G92: =SUIVI!#REF! -> #REF! | H92: =IF(C92,1,0) -> #REF! | I92: =IF(SUIVI!#REF!,1,0) -> #REF! | J92: =SUIVI!#REF! -> #REF! | K92: =SUIVI!#REF! -> #REF! | L92: =SUIVI!#REF! -> #REF! | M92: Parc | N92: =SUIVI!$V$8 -> LKW | O92: =SUIVI!#REF! -> #REF! | P92: 84
A93: =$A$12 -> CIMOLAI | B93: =SUIVI!#REF! -> #REF! | C93: =SUIVI!#REF! -> #REF! | F93: =SUIVI!#REF! -> #REF! | G93: =SUIVI!#REF! -> #REF! | H93: =IF(C93,1,0) -> #REF! | I93: =IF(SUIVI!#REF!,1,0) -> #REF! | J93: =SUIVI!#REF! -> #REF! | K93: =SUIVI!#REF! -> #REF! | L93: =SUIVI!#REF! -> #REF! | M93: Parc | N93: Parc | O93: =SUIVI!#REF! -> #REF! | P93: 85
A94: =$A$13 -> PASSERELLE DE BELVAL | B94: =SUIVI!#REF! -> #REF! | C94: =SUIVI!#REF! -> #REF! | F94: =SUIVI!#REF! -> #REF! | G94: =SUIVI!#REF! -> #REF! | H94: =IF(C94,1,0) -> #REF! | I94: =IF(SUIVI!#REF!,1,0) -> #REF! | J94: =SUIVI!#REF! -> #REF! | K94: =SUIVI!#REF! -> #REF! | L94: =SUIVI!#REF! -> #REF! | M94: Parc | N94: =SUIVI!$V$8 -> LKW | O94: =SUIVI!#REF! -> #REF! | P94: 86
A95: N° de plans | B95: =SUIVI!#REF! -> #REF! | C95: =SUIVI!#REF! -> #REF! | F95: =SUIVI!#REF! -> #REF! | G95: =SUIVI!#REF! -> #REF! | H95: =IF(C95,1,0) -> #REF! | I95: =IF(SUIVI!#REF!,1,0) -> #REF! | J95: =SUIVI!#REF! -> #REF! | K95: =SUIVI!#REF! -> #REF! | L95: =SUIVI!#REF! -> #REF! | M95: Parc | N95: Parc | O95: =SUIVI!#REF! -> #REF! | P95: 87
A96: =$A$15 -> 0 | B96: =SUIVI!#REF! -> #REF! | C96: =SUIVI!#REF! -> #REF! | F96: =SUIVI!#REF! -> #REF! | G96: =SUIVI!#REF! -> #REF! | H96: =IF(C96,1,0) -> #REF! | I96: =IF(SUIVI!#REF!,1,0) -> #REF! | J96: =SUIVI!#REF! -> #REF! | K96: =SUIVI!#REF! -> #REF! | L96: =SUIVI!#REF! -> #REF! | M96: Parc | N96: =SUIVI!$V$8 -> LKW | O96: =SUIVI!#REF! -> #REF! | P96: 88
A97: =$A$16 -> 0 | B97: =SUIVI!#REF! -> #REF! | C97: =SUIVI!#REF! -> #REF! | F97: =SUIVI!#REF! -> #REF! | G97: =SUIVI!#REF! -> #REF! | H97: =IF(C97,1,0) -> #REF! | I97: =IF(SUIVI!#REF!,1,0) -> #REF! | J97: =SUIVI!#REF! -> #REF! | K97: =SUIVI!#REF! -> #REF! | L97: =SUIVI!#REF! -> #REF! | M97: Parc | N97: Parc | O97: =SUIVI!#REF! -> #REF! | P97: 89
A98: =$A$17 -> 0 | B98: =SUIVI!#REF! -> #REF! | C98: =SUIVI!#REF! -> #REF! | F98: =SUIVI!#REF! -> #REF! | G98: =SUIVI!#REF! -> #REF! | H98: =IF(C98,1,0) -> #REF! | I98: =IF(SUIVI!#REF!,1,0) -> #REF! | J98: =SUIVI!#REF! -> #REF! | K98: =SUIVI!#REF! -> #REF! | L98: =SUIVI!#REF! -> #REF! | M98: Parc | N98: =SUIVI!$V$8 -> LKW | O98: =SUIVI!#REF! -> #REF! | P98: 90
A99: =$A$9 -> 1100633635-636 | B99: =SUIVI!#REF! -> #REF! | C99: =SUIVI!#REF! -> #REF! | F99: =SUIVI!#REF! -> #REF! | G99: =SUIVI!#REF! -> #REF! | H99: =IF(C99,1,0) -> #REF! | I99: =IF(SUIVI!#REF!,1,0) -> #REF! | J99: =SUIVI!#REF! -> #REF! | K99: =SUIVI!#REF! -> #REF! | L99: =SUIVI!#REF! -> #REF! | M99: Parc | N99: Parc | O99: =SUIVI!#REF! -> #REF! | P99: 91
A100: =$A$10 -> Z128 | B100: =SUIVI!#REF! -> #REF! | C100: =SUIVI!#REF! -> #REF! | F100: =SUIVI!#REF! -> #REF! | G100: =SUIVI!#REF! -> #REF! | H100: =IF(C100,1,0) -> #REF! | I100: =IF(SUIVI!#REF!,1,0) -> #REF! | J100: =SUIVI!#REF! -> #REF! | K100: =SUIVI!#REF! -> #REF! | L100: =SUIVI!#REF! -> #REF! | M100: Parc | N100: =SUIVI!$V$8 -> LKW | O100: =SUIVI!#REF! -> #REF! | P100: 92
A101: =$A$11 -> 1900015151-15087 | B101: =SUIVI!#REF! -> #REF! | C101: =SUIVI!#REF! -> #REF! | F101: =SUIVI!#REF! -> #REF! | G101: =SUIVI!#REF! -> #REF! | H101: =IF(C101,1,0) -> #REF! | I101: =IF(SUIVI!#REF!,1,0) -> #REF! | J101: =SUIVI!#REF! -> #REF! | K101: =SUIVI!#REF! -> #REF! | L101: =SUIVI!#REF! -> #REF! | M101: Parc | N101: Parc | O101: =SUIVI!#REF! -> #REF! | P101: 93
A102: =$A$12 -> CIMOLAI | B102: =SUIVI!#REF! -> #REF! | C102: =SUIVI!#REF! -> #REF! | F102: =SUIVI!#REF! -> #REF! | G102: =SUIVI!#REF! -> #REF! | H102: =IF(C102,1,0) -> #REF! | I102: =IF(SUIVI!#REF!,1,0) -> #REF! | J102: =SUIVI!#REF! -> #REF! | K102: =SUIVI!#REF! -> #REF! | L102: =SUIVI!#REF! -> #REF! | M102: Parc | N102: =SUIVI!$V$8 -> LKW | O102: =SUIVI!#REF! -> #REF! | P102: 94
...

Sheet Galva instructions

Sheet SUIVI
AJ1: SCIE
AC2: WAGON | AD2: 80T MAXI POUR PAYS DE L'EST
A3: ArcelorMittal Belval & Differdange S.A. | J3: Parachèvement spécial | Z3: EN 10163-3 | AC3: MAXI CAPACITÉ WAGON POUR LA SUISSE
A4: Site de Differdange | Z4: sous classe 1 : soudage autorisé | AF4: F577 SCIAGE BARRE DE SCHROTT
I5: SUIVI JOURNALIER FSJ 1 | Z5: sous classe 2 : soudage avec dérogation client
E6: =PREVI!A10 -> 1100633635-636 | I6: =PREVI!C10 -> CIMOLAI | R6: 0 | V6: =PREVI!A11 -> Z128 | X6: =PREVI!B11 -> 0 | Z6: sous classe 3 : soudage interdit
E7: =PREVI!A12 -> 1900015151-15087 | I7: =PREVI!C11 -> PASSERELLE DE BELVAL | R7: 0 | T7: =COUNTBLANK(T9:T18) -> 0 | U7: =COUNTBLANK(U9:U18) -> 0 | V7: =COUNTBLANK(V9:V18) -> 0 | Y7: BILAN
A8: PRIOR | B8: KW | C8: Compt | D8: ASIA | E8: POS | F8: R3 | G8: R3 | H8: PROFIL | I8: L-LAM | J8: LONG | K8: P/M | L8: POIDS | M8: N°LAM | N8: FAUTES | O8: NR | P8: U.S. REPARATUR | Q8: TRONÇ | R8: REP | S8: N°LAM | T8: ROBOT | U8: CTR HAUTEUR TÊTE | V8: LKW | W8: A expédier au 6-12-21 | Y8: DATE | Z8: NBRS | AA8: POIDS | AD8: WAGON | AF8: TRI D'ORIGINE | AI8: V.T. | AJ8: P.T. | AK8: M.T. | AL8: U.S.
A9: / | B9: 1 | C9: =IF(J9,1,0) -> 1 | D9: 1900015087 | E9: 1 | F9: 1100633635 | G9: 10 | H9: HL1100A | I9: 11100 | J9: 10300 | K9: 343 | L9: =K9*J9/1000 -> 3532.9 | M9: CZ6 | S9: CZ6 | T9: ok | U9: / | V9: 44594 | W9: X | Y9: =V9 -> 44594 | Z9: =IF(Y9,1,0) -> 1 | AA9: =IF(Y9,L9,0) -> 3532.9 | AD9: LKW | AF9: 1 | AH9: Hacki | AI9: VT2 | AJ9: PT2 | AK9: MT2 | AL9: UT2
A10: / | B10: 2 | C10: =IF(J10,1,0) -> 1 | D10: 1900015087 | E10: 1 | F10: 1100633635 | G10: 10 | H10: HL1100A | I10: 11100 | J10: 10300 | K10: 343 | L10: =K10*J10/1000 -> 3532.9 | M10: CZ7 | S10: CZ7 | T10: ok | U10: / | V10: 44594 | W10: X | Y10: =V10 -> 44594 | Z10: =IF(Y10,1,0) -> 1 | AA10: =IF(Y10,L10,0) -> 3532.9 | AD10: QUAI 3 | AF10: 2 | AH10: Piet | AI10: VT2 | AJ10: - | AK10: MT2 | AL10: -
A11: / | B11: 3 | C11: =IF(J11,1,0) -> 1 | D11: 1900015087 | E11: 9 | F11: 1100633635 | G11: 20 | H11: HL1100A | I11: 11300 | J11: 10400 | K11: 343 | L11: =K11*J11/1000 -> 3567.2 | M11: CZ52 | S11: CZ52 | T11: ok | U11: / | V11: 44594 | W11: X | Y11: =V11 -> 44594 | Z11: =IF(Y11,1,0) -> 1 | AA11: =IF(Y11,L11,0) -> 3567.2 | AD11: HALLE 4 | AF11: 3 | AH11: Mike | AI11: - | AJ11: - | AK11: MT2 | AL11: UT1
A12: / | B12: 4 | C12: =IF(J12,1,0) -> 1 | D12: 1900015087 | E12: 10 | F12: 1100633636 | G12: 10 | H12: HL1100A | I12: 9200 | J12: 9000 | K12: 343 | L12: =K12*J12/1000 -> 3087 | M12: EA15 | S12: EA15 | T12: ok | U12: / | V12: 44594 | W12: X | Y12: =V12 -> 44594 | Z12: =IF(Y12,1,0) -> 1 | AA12: =IF(Y12,L12,0) -> 3087 | AF12: 4
A13: / | B13: 5 | C13: =IF(J13,1,0) -> 1 | D13: 1900015087 | E13: 2 | F13: 1100633636 | G13: 20 | H13: HL1100A | I13: 10700 | J13: 10100 | K13: 343 | L13: =K13*J13/1000 -> 3464.3 | M13: CZ9 oder10 | S13: CZ9 | T13: ok | U13: / | V13: 44594 | W13: X | Y13: =V13 -> 44594 | Z13: =IF(Y13,1,0) -> 1 | AA13: =IF(Y13,L13,0) -> 3464.3 | AF13: 5
A14: / | B14: 6 | C14: =IF(J14,1,0) -> 1 | D14: 1900015151 | E14: 38 | F14: 1100633635 | G14: 20 | H14: HL1100A | I14: 10600 | J14: 10400 | K14: 343 | L14: =K14*J14/1000 -> 3567.2 | M14: EC48 | S14: EC48 | T14: ok | U14: / | V14: 44594 | W14: X | Y14: =V14 -> 44594 | Z14: =IF(Y14,1,0) -> 1 | AA14: =IF(Y14,L14,0) -> 3567.2 | AB14: =IF(Z14,O14,0) -> 0 | AC14: =IF(AA14,N14,0) -> 0 | AD14: =IF(AB14,T14,0) -> 0 | AE14: =IF(AC14,#REF!,0) -> 0 | AF14: 6
A15: / | B15: 7 | C15: =IF(J15,1,0) -> 1 | D15: 1900015151 | E15: 38 | F15: 1100633635 | G15: 20 | H15: HL1100A | I15: 10600 | J15: 10400 | K15: 343 | L15: =K15*J15/1000 -> 3567.2 | M15: EC49 | S15: EC49 | T15: ok | U15: / | V15: 44594 | W15: X | Y15: =V15 -> 44594 | Z15: =IF(Y15,1,0) -> 1 | AA15: =IF(Y15,L15,0) -> 3567.2 | AB15: =IF(Z15,O15,0) -> 0 | AC15: =IF(AA15,N15,0) -> 0 | AD15: =IF(AB15,T15,0) -> 0 | AE15: =IF(AC15,#REF!,0) -> 0 | AF15: 7
A16: / | B16: 8 | C16: =IF(J16,1,0) -> 1 | D16: 1900015151 | E16: 38 | F16: 1100633636 | G16: 30 | H16: HL1100A | I16: 10600 | J16: 10400 | K16: 343 | L16: =K16*J16/1000 -> 3567.2 | M16: EC50 | S16: EC50 | T16: ok | U16: / | V16: 44594 | W16: X | Y16: =V16 -> 44594 | Z16: =IF(Y16,1,0) -> 1 | AA16: =IF(Y16,L16,0) -> 3567.2 | AB16: =IF(Z16,O16,0) -> 0 | AC16: =IF(AA16,N16,0) -> 0 | AD16: =IF(AB16,T16,0) -> 0 | AE16: =IF(AC16,#REF!,0) -> 0 | AF16: 8
A17: / | B17: 9 | C17: =IF(J17,1,0) -> 1 | D17: 1900015151 | E17: 38 | F17: 1100633636 | G17: 30 | H17: HL1100A | I17: 10600 | J17: 10400 | K17: 343 | L17: =K17*J17/1000 -> 3567.2 | M17: EC51 | S17: EC51 | T17: ok | U17: / | V17: 44594 | W17: X | Y17: =V17 -> 44594 | Z17: =IF(Y17,1,0) -> 1 | AA17: =IF(Y17,L17,0) -> 3567.2 | AB17: =IF(Z17,O17,0) -> 0 | AC17: =IF(AA17,N17,0) -> 0 | AD17: =IF(AB17,T17,0) -> 0 | AE17: =IF(AC17,#REF!,0) -> 0 | AF17: 9
A18: / | B18: 10 | C18: =IF(J18,1,0) -> 1 | D18: 1900015151 | E18: 27 | F18: 1100633636 | G18: 40 | H18: HL1100B | I18: 15800 | J18: 5300 | K18: 390 | L18: =K18*J18/1000 -> 2067 | M18: EC406 oder 407 | S18: EC407 | T18: 44589 | U18: / | V18: 44594 | W18: X | Y18: =V18 -> 44594 | Z18: =IF(Y18,1,0) -> 1 | AA18: =IF(Y18,L18,0) -> 2067 | AF18: 10
C19: =IF(J19,1,0) -> 0 | G19: MAXIMUM RECOPIE AUTOMATIQUE | L19: =SUM(L9:L18)/1000 -> 33.5201 | Y19: =V19 -> 0 | Z19: =SUM(Z9:Z18) -> 10 | AA19: =SUM(AA9:AA18)/1000 -> 33.5201 | AF19: 201
C20: =IF(J20,1,0) -> 0 | L20: =K20*J20/1000 -> 0 | Y20: =V20 -> 0 | Z20: =IF(Y20,1,0) -> 0 | AA20: =IF(Y20,L20,0) -> 0 | AF20: 202
C21: =IF(J21,1,0) -> 0 | L21: =K21*J21/1000 -> 0 | Y21: =V21 -> 0 | Z21: =IF(Y21,1,0) -> 0 | AA21: =IF(Y21,L21,0) -> 0 | AF21: 203
C22: =IF(J22,1,0) -> 0 | L22: =K22*J22/1000 -> 0 | Y22: =V22 -> 0 | Z22: =IF(Y22,1,0) -> 0 | AA22: =IF(Y22,L22,0) -> 0 | AF22: 204
C23: =IF(J23,1,0) -> 0 | L23: =K23*J23/1000 -> 0 | Y23: =V23 -> 0 | Z23: =IF(Y23,1,0) -> 0 | AA23: =IF(Y23,L23,0) -> 0 | AF23: 205
C24: =IF(J24,1,0) -> 0 | L24: =K24*J24/1000 -> 0 | Y24: =V24 -> 0 | Z24: =IF(Y24,1,0) -> 0 | AA24: =IF(Y24,L24,0) -> 0 | AF24: 206
C25: =IF(J25,1,0) -> 0 | L25: =K25*J25/1000 -> 0 | Y25: =V25 -> 0 | Z25: =IF(Y25,1,0) -> 0 | AA25: =IF(Y25,L25,0) -> 0 | AF25: 207
C26: =IF(J26,1,0) -> 0 | L26: =K26*J26/1000 -> 0 | Y26: =V26 -> 0 | Z26: =IF(Y26,1,0) -> 0 | AA26: =IF(Y26,L26,0) -> 0 | AF26: 208
C27: =IF(J27,1,0) -> 0 | L27: =K27*J27/1000 -> 0 | Y27: =V27 -> 0 | Z27: =IF(Y27,1,0) -> 0 | AA27: =IF(Y27,L27,0) -> 0 | AF27: 209
C28: =IF(J28,1,0) -> 0 | L28: =K28*J28/1000 -> 0 | Y28: =V28 -> 0 | Z28: =IF(Y28,1,0) -> 0 | AA28: =IF(Y28,L28,0) -> 0 | AF28: 210
C29: =IF(J29,1,0) -> 0 | L29: =K29*J29/1000 -> 0 | Y29: =V29 -> 0 | Z29: =IF(Y29,1,0) -> 0 | AA29: =IF(Y29,L29,0) -> 0 | AF29: 211
C30: =IF(J30,1,0) -> 0 | L30: =K30*J30/1000 -> 0 | Y30: =V30 -> 0 | Z30: =IF(Y30,1,0) -> 0 | AA30: =IF(Y30,L30,0) -> 0 | AF30: 212
C31: =IF(J31,1,0) -> 0 | L31: =K31*J31/1000 -> 0 | Y31: =V31 -> 0 | Z31: =IF(Y31,1,0) -> 0 | AA31: =IF(Y31,L31,0) -> 0 | AF31: 213
... C45: =IF(J45,1,0) -> 0 | L45: =K45*J45/1000 -> 0 | Y45: =V45 -> 0 | Z45: =IF(Y45,1,0) -> 0 | AA45: =IF(Y45,L45,0) -> 0 | AF45: 227
C46: =IF(J46,1,0) -> 0 | L46: =K46*J46/1000 -> 0 | AF46: 228
C47: =IF(J47,1,0) -> 0 | L47: =K47*J47/1000 -> 0 | AF47: 229
C48: =IF(J48,1,0) -> 0 | L48: =K48*J48/1000 -> 0 | AF48: 230
C49: =IF(J49,1,0) -> 0 | L49: =K49*J49/1000 -> 0 | AF49: 231
C50: =IF(J50,1,0) -> 0 | L50: =K50*J50/1000 -> 0 | AF50: 232
C51: =IF(J51,1,0) -> 0 | L51: =K51*J51/1000 -> 0 | AF51: 233
C52: =IF(J52,1,0) -> 0 | L52: =K52*J52/1000 -> 0 | AF52: 234
C53: =IF(J53,1,0) -> 0 | L53: =K53*J53/1000 -> 0 | AF53: 235
C54: =IF(J54,1,0) -> 0 | L54: =K54*J54/1000 -> 0 | AF54: 236
C55: =IF(J55,1,0) -> 0 | L55: =K55*J55/1000 -> 0 | AF55: 237
C56: =IF(J56,1,0) -> 0 | L56: =K56*J56/1000 -> 0 | AF56: 238
C57: =IF(J57,1,0) -> 0 | L57: =K57*J57/1000 -> 0 | AF57: 239
... C142: =IF(J142,1,0) -> 0 | L142: =K142*J142/1000 -> 0 | AF142: 324
L143: =K143*J143/1000 -> 0 | AF143: 325
L144: =K144*J144/1000 -> 0 | AF144: 326
L145: =K145*J145/1000 -> 0 | AF145: 327
L146: =K146*J146/1000 -> 0 | AF146: 328
L147: =K147*J147/1000 -> 0 | AF147: 329
L148: =K148*J148/1000 -> 0 | AF148: 330
L149: =K149*J149/1000 -> 0 | AF149: 331
L150: =K150*J150/1000 -> 0 | AF150: 332
L151: =K151*J151/1000 -> 0 | AF151: 333
L152: =K152*J152/1000 -> 0 | AF152: 334
L153: =K153*J153/1000 -> 0 | AF153: 335
L154: =K154*J154/1000 -> 0 | AF154: 336
... L184: =K184*J184/1000 -> 0 | AF184: 366
AF185: 367
AF186: 368
AF187: 369
AF188: 370
AF189: 371
AF190: 372
AF191: 373
AF192: 374
AF193: 375
AF194: 376
AF195: 377
AF196: 378
... AF818: 1000

Sheet PREVI
W1: SCIE
A3: ArcelorMittal Belval & Differdange S.A. | H3: Parachèvement spécial | X3: PRESSE | Z3: FOR.NUM | AB3: PRESSE | AD3: ROBOT
A4: Site de Differdange | X4: NR
G5: FICHE DE PREVISIONS N° FP1 | U5: SCHLEIDER
A6: DATE: | B6: =TODAY() -> 44594 | C6: OFFRE N° | U6: SCHILS.D
A7: NOM: | B7: SCHLEIDER | C7: PLAN: | G7: NOM: BIEVER R. | J7: ROBOT | L7: FOR.NUM | N7: PRESSE | P7: PRESSE | R7: REMARQUES | X7: F MAN | Z7: SOUDAGE | AB7: MONTAGE
C8: RECEPTION | G8: DATE: | P8: NR SI ECLISSAGE | Z8: + CND | AB8: A BLANC
A9: COMMANDE | C9: CLIENT | E9: SEM | F9: DELAI | G9: NBR | H9: PROFIL | I9: LONG | J9: TOTAL | L9: TOTAL | M9: TEMPS | N9: TOTAL | O9: TEMPS | P9: TOTAL | Q9: TEMPS | R9: LAMINAGE
A10: 1100633635-636 | C10: CIMOLAI | G10: 10 | H10: HL 1100 | I10: 5-11m | J10: =K10*G10 -> 16 | K10: 1.6 | L10: =M10*G10 -> 0 | N10: =O10*G10 -> 0 | P10: =Q10*G10 -> 0 | R10: 5 barres le 15-07 | V10: SCIE | X10: =IF(K10,G10,0) -> 10 | Y10: =IF(L10,G10,0) -> 0 | Z10: =IF(M10,G10,0) -> 0 | AA10: =IF(N10,G10,0) -> 0
A11: Z128 | C11: PASSERELLE DE BELVAL | J11: =K11*G11 -> 0 | L11: =M11*G11 -> 0 | N11: =O11*G11 -> 0 | P11: =Q11*G11 -> 0 | R11: 5 barres le 16-10 | V11: FOR. NUM | X11: =IF(K11,G11,0) -> 0 | Y11: =IF(L11,G11,0) -> 0 | Z11: =IF(M11,G11,0) -> 0 | AA11: =IF(N11,G11,0) -> 0
A12: 1900015151-15087 | J12: =K12*G12 -> 0 | L12: =M12*G12 -> 0 | N12: =O12*G12 -> 0 | P12: =Q12*G12 -> 0 | V12: ROBOT | X12: =IF(K12,G12,0) -> 0 | Y12: =IF(L12,G12,0) -> 0 | Z12: =IF(M12,G12,0) -> 0 | AA12: =IF(N12,G12,0) -> 0
J13: =K13*G13 -> 0 | L13: =M13*G13 -> 0 | N13: =O13*G13 -> 0 | P13: =Q13*G13 -> 0 | V13: NR | X13: =IF(K13,G13,0) -> 0 | Y13: =IF(L13,G13,0) -> 0 | Z13: =IF(M13,G13,0) -> 0 | AA13: =IF(N13,G13,0) -> 0
J14: =K14*G14 -> 0 | L14: =M14*G14 -> 0 | N14: =O14*G14 -> 0 | P14: =Q14*G14 -> 0 | V14: FOR. MAN | X14: =IF(K14,G14,0) -> 0 | Y14: =IF(L14,G14,0) -> 0 | Z14: =IF(M14,G14,0) -> 0 | AA14: =IF(N14,G14,0) -> 0
J15: =K15*G15 -> 0 | L15: =M15*G15 -> 0 | N15: =O15*G15 -> 0 | P15: =Q15*G15 -> 0 | V15: PRESSE | X15: =IF(K15,G15,0) -> 0 | Y15: =IF(L15,G15,0) -> 0 | Z15: =IF(M15,G15,0) -> 0 | AA15: =IF(N15,G15,0) -> 0
J16: =K16*G16 -> 0 | L16: =M16*G16 -> 0 | N16: =O16*G16 -> 0 | P16: =Q16*G16 -> 0 | V16: U.S. | X16: =IF(K16,G16,0) -> 0 | Y16: =IF(L16,G16,0) -> 0 | Z16: =IF(M16,G16,0) -> 0 | AA16: =IF(N16,G16,0) -> 0
J17: =K17*G17 -> 0 | L17: =M17*G17 -> 0 | N17: =O17*G17 -> 0 | P17: =Q17*G17 -> 0 | X17: =IF(K17,G17,0) -> 0 | Y17: =IF(L17,G17,0) -> 0 | Z17: =IF(M17,G17,0) -> 0 | AA17: =IF(N17,G17,0) -> 0
J18: =K18*G18 -> 0 | L18: =M18*G18 -> 0 | N18: =O18*G18 -> 0 | P18: =Q18*G18 -> 0 | X18: =IF(K18,G18,0) -> 0 | Y18: =IF(L18,G18,0) -> 0 | Z18: =IF(M18,G18,0) -> 0 | AA18: =IF(N18,G18,0) -> 0
J19: =K19*G19 -> 0 | L19: =M19*G19 -> 0 | N19: =O19*G19 -> 0 | P19: =Q19*G19 -> 0 | V19: SOUDAGE | X19: =IF(K19,G19,0) -> 0 | Y19: =IF(L19,G19,0) -> 0 | Z19: =IF(M19,G19,0) -> 0 | AA19: =IF(N19,G19,0) -> 0
A20: TOTAL | G20: =SUM(G10:G19) -> 10 | J20: =SUM(J10:J19) -> 16 | K20: =J20/X20 -> 1.6 | L20: =SUM(L10:L19) -> 0 | M20: =L20/Y20 -> #DIV/0! | N20: =SUM(N10:N19) -> 0 | O20: =N20/Z20 -> #DIV/0! | P20: =SUM(P10:P19) -> 0 | Q20: =P20/AA20 -> #DIV/0! | V20: 1.2 à 1.4kg/h | X20: =SUM(X10:X19) -> 10 | Y20: =SUM(Y10:Y19) -> 0 | Z20: =SUM(Z10:Z19) -> 0 | AA20: =SUM(AA10:AA19) -> 0
D21: EX PARA | J21: F MAN | L21: ASSEMBLAGE | N21: SOUDAGE | P21: RESSUAGE | U21: Si forte épaisseur des profils, percer avant trous de l'éclissage à la wagner et contrepercer en FMan
N22: + CND | U22: Si forte épaisseur des profils et barres trop lourdes ou trop déformées (redresseage trop fort pour presse para) pour Wagner, tracer et percer l'éclissage à la FMan
A23: N° DE PLANS | J23: TOTAL | K23: TEMPS | L23: TOTAL | M23: TEMPS | N23: TOTAL | O23: TEMPS | P23: TOTAL | Q23: TEMPS | U23: coupe biaise au robot maxi 45°
G24: =G10 -> 10 | H24: =H10 -> HL 1100 | I24: =I10 -> 5-11m | J24: =K24*G24 -> 0 | L24: =M24*G24 -> 0 | N24: =O24*G24 -> 0 | P24: =Q24*G24 -> 0 | R24: FINANCES | X24: =IF(K24,G24,0) -> 0 | Y24: =IF(L24,G24,0) -> 0 | Z24: =IF(M24,G24,0) -> 0 | AA24: =IF(N24,G24,0) -> 0
G25: =G11 -> 0 | H25: =H11 -> 0 | I25: =I11 -> 0 | J25: =K25*G25 -> 0 | L25: =M25*G25 -> 0 | N25: =O25*G25 -> 0 | P25: =Q25*G25 -> 0 | R25: Taux horaire (€) : | X25: =IF(K25,G25,0) -> 0 | Y25: =IF(L25,G25,0) -> 0 | Z25: =IF(M25,G25,0) -> 0 | AA25: =IF(N25,G25,0) -> 0
G26: =G12 -> 0 | H26: =H12 -> 0 | I26: =I12 -> 0 | J26: =K26*G26 -> 0 | L26: =M26*G26 -> 0 | N26: =O26*G26 -> 0 | P26: =Q26*G26 -> 0 | R26: 75 | X26: =IF(K26,G26,0) -> 0 | Y26: =IF(L26,G26,0) -> 0 | Z26: =IF(M26,G26,0) -> 0 | AA26: =IF(N26,G26,0) -> 0
G27: =G13 -> 0 | H27: =H13 -> 0 | I27: =I13 -> 0 | J27: =K27*G27 -> 0 | L27: =M27*G27 -> 0 | N27: =O27*G27 -> 0 | P27: =Q27*G27 -> 0 | R27: LBB (€/T) | X27: =IF(K27,G27,0) -> 0 | Y27: =IF(L27,G27,0) -> 0 | Z27: =IF(M27,G27,0) -> 0 | AA27: =IF(N27,G27,0) -> 0
G28: =G14 -> 0 | H28: =H14 -> 0 | I28: =I14 -> 0 | J28: =K28*G28 -> 0 | L28: =M28*G28 -> 0 | N28: =O28*G28 -> 0 | P28: =Q28*G28 -> 0 | X28: =IF(K28,G28,0) -> 0 | Y28: =IF(L28,G28,0) -> 0 | Z28: =IF(M28,G28,0) -> 0 | AA28: =IF(N28,G28,0) -> 0
G29: =G15 -> 0 | H29: =H15 -> 0 | I29: =I15 -> 0 | J29: =K29*G29 -> 0 | L29: =M29*G29 -> 0 | N29: =O29*G29 -> 0 | P29: =Q29*G29 -> 0 | R29: Nb d'heures prévues par le para | X29: =IF(K29,G29,0) -> 0 | Y29: =IF(L29,G29,0) -> 0 | Z29: =IF(M29,G29,0) -> 0 | AA29: =IF(N29,G29,0) -> 0
G30: =G16 -> 0 | H30: =H16 -> 0 | I30: =I16 -> 0 | J30: =K30*G30 -> 0 | L30: =M30*G30 -> 0 | N30: =O30*G30 -> 0 | P30: =Q30*G30 -> 0 | R30: =R46 -> 16 | X30: =IF(K30,G30,0) -> 0 | Y30: =IF(L30,G30,0) -> 0 | Z30: =IF(M30,G30,0) -> 0 | AA30: =IF(N30,G30,0) -> 0
G31: =G17 -> 0 | H31: =H17 -> 0 | I31: =I17 -> 0 | J31: =K31*G31 -> 0 | L31: =M31*G31 -> 0 | N31: =O31*G31 -> 0 | P31: =Q31*G31 -> 0 | R31: Nb d'heures vendues par ES | X31: =IF(K31,G31,0) -> 0 | Y31: =IF(L31,G31,0) -> 0 | Z31: =IF(M31,G31,0) -> 0 | AA31: =IF(N31,G31,0) -> 0
G32: =G18 -> 0 | J32: =K32*G32 -> 0 | L32: =M32*G32 -> 0 | N32: =O32*G32 -> 0 | P32: =Q32*G32 -> 0 | R32: =R43*R28/R26 -> 0
G33: =G19 -> 0 | H33: =H19 -> 0 | I33: =I19 -> 0 | J33: =K33*G33 -> 0 | L33: =M33*G33 -> 0 | N33: =O33*G33 -> 0 | P33: =Q33*G33 -> 0 | X33: =IF(K33,G33,0) -> 0 | Y33: =IF(L33,G33,0) -> 0 | Z33: =IF(M33,G33,0) -> 0 | AA33: =IF(N33,G33,0) -> 0
A34: TOTAL | G34: =SUM(G24:G33) -> 10 | J34: =SUM(J24:J33) -> 0 | K34: =J34/X34 -> #DIV/0! | L34: =SUM(L24:L33) -> 0 | M34: =L34/Y34 -> #DIV/0! | N34: =SUM(N24:N33) -> 0 | O34: =N34/Z34 -> #DIV/0! | P34: =SUM(P24:P33) -> 0 | Q34: =P34/AA34 -> #DIV/0! | X34: =SUM(X24:X33) -> 0 | Y34: =SUM(Y24:Y33) -> 0 | Z34: =SUM(Z24:Z33) -> 0 | AA34: =SUM(AA24:AA33) -> 0
J35: TRACAGE | L35: PRESSE | N35: GOUJONNAGE
A36: AUTRES INFOS | J36: TOTAL | K36: TEMPS | L36: TOTAL | M36: TEMPS | N36: TOTAL | O36: TEMPS | P36: NB | Q36: nb total | V36: barre | W36: tôle
A37: EXC 4 | G37: =G10 -> 10 | H37: =H10 -> HL 1100 | I37: =I10 -> 5-11m | J37: =K37*G37 -> 0 | L37: =M37*G37 -> 0 | N37: =O37*G37 -> 0 | O37: =S37*P37*8/600 -> 0 | Q37: =P37*G37 -> 0 | S37: 1.33 | V37: S355 | W37: S355 | X37: =IF(K37,G37,0) -> 0 | Y37: =IF(L37,G37,0) -> 0 | Z37: =IF(M37,G37,0) -> 0 | AA37: =IF(N37,G37,0) -> 0
A38: S355K2+M | B38: Matière barre | G38: =G11 -> 0 | H38: =H11 -> 0 | I38: =I11 -> 0 | J38: =K38*G38 -> 0 | L38: =M38*G38 -> 0 | N38: =O38*G38 -> 0 | O38: =S38*P38*8/600 -> 0 | Q38: =P38*G38 -> 0 | S38: 1.33 | V38: S355M | W38: S355N | X38: =IF(K38,G38,0) -> 0 | Y38: =IF(L38,G38,0) -> 0 | Z38: =IF(M38,G38,0) -> 0 | AA38: =IF(N38,G38,0) -> 0
A39: N°PDS | G39: =G12 -> 0 | H39: =H12 -> 0 | I39: =I12 -> 0 | J39: =K39*G39 -> 0 | L39: =M39*G39 -> 0 | N39: =O39*G39 -> 0 | O39: =S39*P39*8/600 -> 0 | Q39: =P39*G39 -> 0 | R39: RENDEMENT H/T | S39: 1.33 | V39: S355K2+M | W39: S355K2+N | X39: =IF(K39,G39,0) -> 0 | Y39: =IF(L39,G39,0) -> 0 | Z39: =IF(M39,G39,0) -> 0 | AA39: =IF(N39,G39,0) -> 0
A40: N°PDC | G40: =G13 -> 0 | H40: =H13 -> 0 | I40: =I13 -> 0 | J40: =K40*G40 -> 0 | L40: =M40*G40 -> 0 | N40: =O40*G40 -> 0 | O40: =S40*P40*8/600 -> 0 | Q40: =P40*G40 -> 0 | R40: =R46/R43 -> 0.47732554 | S40: 1.33 | V40: S460 | W40: S460 | X40: =IF(K40,G40,0) -> 0 | Y40: =IF(L40,G40,0) -> 0 | Z40: =IF(M40,G40,0) -> 0 | AA40: =IF(N40,G40,0) -> 0
A41: S355K2+N | B41: Matière tôle | G41: =G14 -> 0 | H41: =H14 -> 0 | I41: =I14 -> 0 | J41: =K41*G41 -> 0 | L41: =M41*G41 -> 0 | N41: =O41*G41 -> 0 | O41: =S41*P41*8/600 -> 0 | Q41: =P41*G41 -> 0 | S41: 1.33 | V41: S460M | W41: S460M | X41: =IF(K41,G41,0) -> 0 | Y41: =IF(L41,G41,0) -> 0 | Z41: =IF(M41,G41,0) -> 0 | AA41: =IF(N41,G41,0) -> 0
G42: =G15 -> 0 | H42: =H15 -> 0 | I42: =I15 -> 0 | J42: =K42*G42 -> 0 | L42: =M42*G42 -> 0 | N42: =O42*G42 -> 0 | O42: =S42*P42*8/600 -> 0 | Q42: =P42*G42 -> 0 | R42: POIDS TONNES | S42: 1.33 | X42: =IF(K42,G42,0) -> 0 | Y42: =IF(L42,G42,0) -> 0 | Z42: =IF(M42,G42,0) -> 0 | AA42: =IF(N42,G42,0) -> 0
G43: =G16 -> 0 | H43: =H16 -> 0 | I43: =I16 -> 0 | J43: =K43*G43 -> 0 | L43: =M43*G43 -> 0 | N43: =O43*G43 -> 0 | O43: =S43*P43*8/600 -> 0 | Q43: =P43*G43 -> 0 | R43: =SUIVI!L19 -> 33.5201 | S43: 1.33 | X43: =IF(K43,G43,0) -> 0 | Y43: =IF(L43,G43,0) -> 0 | Z43: =IF(M43,G43,0) -> 0 | AA43: =IF(N43,G43,0) -> 0
G44: =G17 -> 0 | H44: =H17 -> 0 | I44: =I17 -> 0 | J44: =K44*G44 -> 0 | L44: =M44*G44 -> 0 | N44: =O44*G44 -> 0 | O44: =S44*P44*8/600 -> 0 | Q44: =P44*G44 -> 0 | S44: 1.33 | X44: =IF(K44,G44,0) -> 0 | Y44: =IF(L44,G44,0) -> 0 | Z44: =IF(M44,G44,0) -> 0 | AA44: =IF(N44,G44,0) -> 0
G45: =G19 -> 0 | H45: =H19 -> 0 | I45: =I19 -> 0 | J45: =K45*G45 -> 0 | L45: =M45*G45 -> 0 | N45: =O45*G45 -> 0 | O45: =S45*P45*8/600 -> 0 | Q45: =P45*G45 -> 0 | R45: TOTAL HEURES PRÉVUES | S45: 1.33 | X45: =IF(K45,G45,0) -> 0 | Y45: =IF(L45,G45,0) -> 0 | Z45: =IF(M45,G45,0) -> 0 | AA45: =IF(N45,G45,0) -> 0
A46: TOTAL | G46: =SUM(G37:G45) -> 10 | J46: =SUM(J37:J45) -> 0 | K46: =J46/X46 -> #DIV/0! | L46: =SUM(L37:L45) -> 0 | M46: =L46/Y46 -> #DIV/0! | N46: =SUM(N37:N45) -> 0 | O46: =N46/Z46 -> #DIV/0! | Q46: =SUM(Q37:Q45) -> 0 | R46: =J20+L20+N20+P20+J34+L34+N34+J46+L46+N46+P46 -> 16 | X46: =SUM(X37:X45) -> 0 | Y46: =SUM(Y37:Y45) -> 0 | Z46: =SUM(Z37:Z45) -> 0 | AA46: =SUM(AA37:AA45) -> 0
V47: EXC 2
A48: EXC4 | V48: EXC 3
A49: S355K2+M | V49: EXC 4
A50: N°PDS
A51: N°PDC
A52: S355K2+N

Sheet Masse et dimension
A1: Version | B1: 2020-3
A3: Series | B3: Designation | D3: G | F3: Dimensions | M3: Surface | P3: Steel grades | AB3: Delivery conditions | AC3: Section properties | AO3: Classification EN 1993-1-1 | AS3: Section factors Ap/V | AW3: Standards | BS3: Delivery conditions | CF3: Software availability
A4: Dimensions: EN 10365:2017 Tolerances: EN 10034:1993 Surface condition: EN 10163-3:2004, class C, subclass 1 | D4: kg/m | F4: h | G4: b | H4: tw | I4: tf | J4: r | K4: hi | L4: d | M4: A | N4: AL | O4: AG | P4: S355 | U4: S460 | Z4: S 500 | AC4: Iy | AD4: Wel.y | AE4: Wpl.y | AF4: iy | AG4: Avz | AH4: Iz | AI4: Wel.z | AJ4: Wpl.z | AK4: iz | AL4: Ss | AM4: It | AN4: Iw | AO4: Pure bending yy | AQ4: Pure compression | AS4: Contour encasement | AU4: Hollow encasement | AW4: EN 10025-2 | AZ4: EN 10025-4 | BD4: Arcorox EN10025-5 | BF4: HISTAR 355 & 460 (/L) | BG4: EN 10225-2 | BI4: EN10273 | BJ4: A572 / A709 / A992 | BM4: A913 | BO4: A588 | BP4: Fritenar 355 | BQ4: GOST 535-2005 GOST 19281-89 | BR4: CSA G40-21-04 | BS4: section with minimum order: 40t per section and grade or upon agreement. | BT4: Minimum tonnage and delivery conditions upon agreement | BU4: Dimensions: AM Standard | CF4: ABC | CG4: ACB+ | CH4: Acobri | CI4: Angelina | CJ4: Portal+ | CK4: A3C | CL4: ACP | CM4: INERD | CN4: ACoP | CO4: CoP2 | CP4: MACS+ | CQ4: Ozone | CR4: LUCA
F5: mm | G5: mm | H5: mm | I5: mm | J5: mm | K5: mm | L5: mm | M5: cm2 | N5: m2/m | O5: m2/t | P5: JR/J0/J2/K2 | Q5: M | R5: ML | S5: Arcorox & 16Mo3 | T5: MO / MLO / ML1O | U5: JR/J0/J2/K2 | V5: M | W5: ML | X5: J0W/J2W/K2W | Y5: MLO / ML1O | Z5: J0 / M | AA5: ML | AC5: cm4 | AD5: cm3 | AE5: cm3 | AF5: cm | AG5: cm2 | AH5: cm4 | AI5: cm3 | AJ5: cm3 | AK5: cm | AL5: cm | AM5: cm4 | AN5: cm6 | AS5: 3 faces | AT5: 4 faces | AU5: 3 faces | AV5: 4 faces | AW5: S235 to S355 (JR/J0/J2/K2) | AX5: S460 (JR/J0/J2/K2) | AY5: S500 (J0) | AZ5: S275 to S355 (M/ML) | BA5: S420 (M/ML) | BB5: S460 (M/ML) | BC5: S500 (M) | BD5: S355W (J0/J2/K2) | BE5: S460W (J0/J2/K2) | BG5: S355 MO/MLO/ML1O | BH5: S460 MLO / ML1O | BI5: 16Mo3 P265GH | BJ5: Grade 36 to 55 | BK5: Grade 60 | BL5: Grade 65 | BM5: Grade 50 & 65 & 70 | BN5: Grade 80 | BO5: Grade B
F6: hauteur | G6: largeur | H6: ép. âme | I6: ép. aile | K6: lg entre ailes | L6: lg droite âme | AN6: x103 | AO6: S355 | AP6: S460 | AQ6: S355 | AR6: S460 | BI6: P265GH
A7: Parallel flange I sections | B7: IPE
A8: Dimensions: AM Standard | B8: IPE 750 x 220 | D8: 220 | F8: 779 | G8: 266 | H8: 16.5 | I8: 30 | J8: 20 | K8: 719 | L8: 679 | M8: 280.7 | N8: 2.555 | O8: 11.56 | P8: 1 | Q8: HI | R8: HI | S8: 1 | T8: HI | U8: 1 | V8: HI | W8: HI | X8: 1 | Y8: HI | Z8: - | AA8: - | AB8: 40 | AC8: 279390 | AD8: 7173 | AE8: 8231 | AF8: 31.4 | AG8: 139 | AH8: 9443 | AI8: 710 | AJ8: 1114 | AK8: 5.7 | AL8: 9.9 | AM8: 620.5 | AN8: 13190 | AO8: 1 | AP8: 1 | AQ8: 4 | AR8: 4 | AS8: 81 | AT8: 91 | AU8: 65 | AV8: 74 | AW8: 1 | AX8: 1 | AY8: 0 | AZ8: 1 | BA8: 1 | BB8: 1 | BC8: 0 | BD8: 1 | BE8: 1 | BF8: 1 | BG8: 1 | BH8: 1 | BI8: 1 | BJ8: 1 | BK8: 1 | BL8: 1 | BM8: 1 | BN8: 0 | BO8: 1 | BP8: 1 | BQ8: 0 | BR8: 0 | BS8: 1 | BT8: 0 | BU8: 1 | BV8: 0 | BW8: 0 | BX8: 0 | BY8: 0 | BZ8: 0 | CA8: 0 | CB8: 0 | CC8: 0 | CD8: 0 | CE8: 0 | CF8: 1 | CG8: 1 | CH8: 1 | CI8: 1 | CJ8: 1 | CK8: 1 | CL8: 1 | CM8: 1 | CN8: 1 | CO8: 1 | CP8: 1 | CQ8: 1 | CR8: 1 | CS8: 0 | CT8: 0 | CU8: 0 | CV8: 0 | CW8: 0 | CX8: 0 | CY8: 0
B9: IPE 750 x 196 | D9: 196 | F9: 770 | G9: 268 | H9: 15.6 | I9: 25.4 | J9: 20 | K9: 719 | L9: 679 | M9: 250.8 | N9: 2.546 | O9: 12.88 | P9: 1 | Q9: HI | R9: HI | S9: 1 | T9: HI | U9: 1 | V9: HI | W9: HI | X9: 1 | Y9: HI | Z9: - | AA9: - | AC9: 241470 | AD9: 6271 | AE9: 7207 | AF9: 30.9 | AG9: 129.7 | AH9: 8177 | AI9: 610.2 | AJ9: 960.1 | AK9: 5.6 | AL9: 8.9 | AM9: 416.5 | AN9: 11290 | AO9: 1 | AP9: 1 | AQ9: 4 | AR9: 4 | AS9: 90 | AT9: 101 | AU9: 72 | AV9: 82 | AW9: 1 | AX9: 1 | AY9: 0 | AZ9: 1 | BA9: 1 | BB9: 1 | BC9: 0 | BD9: 1 | BE9: 1 | BF9: 1 | BG9: 1 | BH9: 1 | BI9: 1 | BJ9: 1 | BK9: 1 | BL9: 1 | BM9: 1 | BN9: 0 | BO9: 1 | BP9: 1 | BQ9: 0 | BR9: 0 | BS9: 0 | BT9: 0 | BU9: 0 | BV9: 0 | BW9: 0 | BX9: 0 | BY9: 0 | BZ9: 0 | CA9: 0 | CB9: 0 | CC9: 0 | CD9: 0 | CE9: 0 | CF9: 1 | CG9: 1 | CH9: 1 | CI9: 1 | CJ9: 1 | CK9: 1 | CL9: 1 | CM9: 1 | CN9: 1 | CO9: 1 | CP9: 1 | CQ9: 1 | CR9: 1 | CS9: 0 | CT9: 0 | CU9: 0 | CV9: 0 | CW9: 0 | CX9: 0 | CY9: 0
B10: IPE 750 x 173 | D10: 173 | F10: 762 | G10: 267 | H10: 14.4 | I10: 21.6 | J10: 20 | K10: 719 | L10: 679 | M10: 221.3 | N10: 2.529 | O10: 14.49 | P10: 1 | Q10: HI | R10: HI | S10: 1 | T10: HI | U10: 1 | V10: HI | W10: HI | X10: 1 | Y10: HI | Z10: - | AA10: - | AC10: 207010 | AD10: 5433 | AE10: 6251 | AF10: 30.5 | AG10: 118.6 | AH10: 6875 | AI10: 515 | AJ10: 811.1 | AK10: 5.5 | AL10: 8.1 | AM10: 278.7 | AN10: 9390 | AO10: 1 | AP10: 1 | AQ10: 4 | AR10: 4 | AS10: 102 | AT10: 114 | AU10: 81 | AV10: 93 | AW10: 1 | AX10: 1 | AY10: 0 | AZ10: 1 | BA10: 1 | BB10: 1 | BC10: 0 | BD10: 1 | BE10: 1 | BF10: 1 | BG10: 1 | BH10: 1 | BI10: 1 | BJ10: 1 | BK10: 1 | BL10: 1 | BM10: 1 | BN10: 0 | BO10: 1 | BP10: 1 | BQ10: 0 | BR10: 0 | BS10: 0 | BT10: 0 | BU10: 0 | BV10: 0 | BW10: 0 | BX10: 0 | BY10: 0 | BZ10: 0 | CA10: 0 | CB10: 0 | CC10: 0 | CD10: 0 | CE10: 0 | CF10: 1 | CG10: 1 | CH10: 1 | CI10: 1 | CJ10: 1 | CK10: 1 | CL10: 1 | CM10: 1 | CN10: 1 | CO10: 1 | CP10: 1 | CQ10: 1 | CR10: 1 | CS10: 0 | CT10: 0 | CU10: 0 | CV10: 0 | CW10: 0 | CX10: 0 | CY10: 0
B11: IPE 750 x 147 | D11: 147 | F11: 753 | G11: 265 | H11: 13.2 | I11: 17 | J11: 20 | K11: 719 | L11: 679 | M11: 187.5 | N11: 2.505 | O11: 16.93 | P11: 1 | Q11: 1 | R11: - | S11: 1 | T11: 1 | U11: 1 | V11: 1 | W11: - | X11: - | Y11: - | Z11: - | AA11: - | AC11: 167250 | AD11: 4442 | AE11: 5143 | AF11: 29.7 | AG11: 107.3 | AH11: 5291 | AI11: 399.3 | AJ11: 632 | AK11: 5.2 | AL11: 7 | AM11: 163.2 | AN11: 7140 | AO11: 1 | AP11: 1 | AQ11: 4 | AR11: 4 | AS11: 119 | AT11: 133 | AU11: 94 | AV11: 108 | AW11: 1 | AX11: 1 | AY11: 0 | AZ11: 1 | BA11: 1 | BB11: 1 | BC11: 0 | BD11: 1 | BE11: 0 | BF11: 0 | BG11: 1 | BH11: 0 | BI11: 1 | BJ11: 1 | BK11: 1 | BL11: 1 | BM11: 0 | BN11: 0 | BO11: 1 | BP11: 1 | BQ11: 0 | BR11: 0 | BS11: 0 | BT11: 0 | BU11: 0 | BV11: 0 | BW11: 0 | BX11: 0 | BY11: 0 | BZ11: 0 | CA11: 0 | CB11: 0 | CC11: 0 | CD11: 0 | CE11: 0 | CF11: 1 | CG11: 1 | CH11: 1 | CI11: 1 | CJ11: 1 | CK11: 1 | CL11: 1 | CM11: 1 | CN11: 1 | CO11: 1 | CP11: 1 | CQ11: 1 | CR11: 1 | CS11: 0 | CT11: 0 | CU11: 0 | CV11: 0 | CW11: 0 | CX11: 0 | CY11: 0
B12: IPE 750 x 134 | D12: 134 | F12: 750 | G12: 264 | H12: 12 | I12: 15.5 | J12: 20 | K12: 719 | L12: 679 | M12: 170.6 | N12: 2.498 | O12: 18.55 | P12: 1 | Q12: 1 | R12: - | S12: 1 | T12: 1 | U12: 1 | V12: 1 | W12: - | X12: - | Y12: - | Z12: - | AA12: - | AC12: 151890 | AD12: 4050 | AE12: 4678 | AF12: 29.7 | AG12: 97.77 | AH12: 4767 | AI12: 361.2 | AJ12: 569.6 | AK12: 5.2 | AL12: 6.6 | AM12: 124.9 | AN12: 6410 | AO12: 1 | AP12: 2 | AQ12: 4 | AR12: 4 | AS12: 130 | AT12: 146 | AU12: 103 | AV12: 118 | AW12: 1 | AX12: 1 | AY12: 0 | AZ12: 1 | BA12: 1 | BB12: 1 | BC12: 0 | BD12: 1 | BE12: 0 | BF12: 0 | BG12: 1 | BH12: 0 | BI12: 1 | BJ12: 1 | BK12: 1 | BL12: 1 | BM12: 0 | BN12: 0 | BO12: 1 | BP12: 1 | BQ12: 0 | BR12: 0 | BS12: 0 | BT12: 0 | BU12: 0 | BV12: 0 | BW12: 0 | BX12: 0 | BY12: 0 | BZ12: 0 | CA12: 0 | CB12: 0 | CC12: 0 | CD12: 0 | CE12: 0 | CF12: 1 | CG12: 1 | CH12: 1 | CI12: 1 | CJ12: 1 | CK12: 1 | CL12: 1 | CM12: 1 | CN12: 1 | CO12: 1 | CP12: 1 | CQ12: 1 | CR12: 1 | CS12: 0 | CT12: 0 | CU12: 0 | CV12: 0 | CW12: 0 | CX12: 0 | CY12: 0
B13: IPE V 600 | D13: 184 | F13: 618 | G13: 228 | H13: 18 | I13: 28 | J13: 24 | K13: 562 | L13: 514 | M13: 233.8 | N13: 2.071 | O13: 11.28 | P13: 1 | Q13: HI | R13: HI | S13: 1 | T13: HI | U13: 1 | V13: HI | W13: HI | X13: 1 | Y13: HI | Z13: - | AA13: - | AB13: 40 | AC13: 141580 | AD13: 4581 | AE13: 5324 | AF13: 24.6 | AG13: 124.5 | AH13: 5569 | AI13: 488.5 | AJ13: 780.3 | AK13: 4.8 | AL13: 10.2 | AM13: 505.8 | AN13: 4813 | AO13: 1 | AP13: 1 | AQ13: 2 | AR13: 3 | AS13: 79 | AT13: 89 | AU13: 63 | AV13: 72 | AW13: 1 | AX13: 1 | AY13: 0 | AZ13: 1 | BA13: 1 | BB13: 1 | BC13: 0 | BD13: 1 | BE13: 1 | BF13: 1 | BG13: 1 | BH13: 1 | BI13: 1 | BJ13: 1 | BK13: 1 | BL13: 1 | BM13: 1 | BN13: 0 | BO13: 1 | BP13: 1 | BQ13: 0 | BR13: 0 | BS13: 1 | BT13: 0 | BU13: 0 | BV13: 0 | BW13: 0 | BX13: 0 | BY13: 0 | BZ13: 0 | CA13: 0 | CB13: 0 | CC13: 0 | CD13: 0 | CE13: 0 | CF13: 1 | CG13: 1 | CH13: 1 | CI13: 1 | CJ13: 1 | CK13: 1 | CL13: 1 | CM13: 1 | CN13: 1 | CO13: 1 | CP13: 1 | CQ13: 1 | CR13: 1 | CS13: 0 | CT13: 0 | CU13: 0 | CV13: 0 | CW13: 0 | CX13: 0 | CY13: 0
B14: IPE O 600 | D14: 154 | F14: 610 | G14: 224 | H14: 15 | I14: 24 | J14: 24 | K14: 562 | L14: 514 | M14: 196.8 | N14: 2.045 | O14: 13.24 | P14: 1 | Q14: HI | R14: HI | S14: 1 | T14: HI | U14: 1 | V14: HI | W14: HI | X14: 1 | Y14: HI | Z14: - | AA14: - | AB14: 40 | AC14: 118300 | AD14: 3878 | AE14: 4471 | AF14: 24.5 | AG14: 104.3 | AH14: 4520 | AI14: 403.6 | AJ14: 640 | AK14: 4.7 | AL14: 9.1 | AM14: 316.3 | AN14: 3859 | AO14: 1 | AP14: 1 | AQ14: 4 | AR14: 4 | AS14: 93 | AT14: 104 | AU14: 73 | AV14: 85 | AW14: 1 | AX14: 1 | AY14: 0 | AZ14: 1 | BA14: 1 | BB14: 1 | BC14: 0 | BD14: 1 | BE14: 1 | BF14: 1 | BG14: 1 | BH14: 1 | BI14: 1 | BJ14: 1 | BK14: 1 | BL14: 1 | BM14: 1 | BN14: 0 | BO14: 1 | BP14: 1 | BQ14: 0 | BR14: 0 | BS14: 1 | BT14: 0 | BU14: 0 | BV14: 0 | BW14: 0 | BX14: 0 | BY14: 0 | BZ14: 0 | CA14: 0 | CB14: 0 | CC14: 0 | CD14: 0 | CE14: 0 | CF14: 1 | CG14: 1 | CH14: 1 | CI14: 1 | CJ14: 1 | CK14: 1 | CL14: 1 | CM14: 1 | CN14: 1 | CO14: 1 | CP14: 1 | CQ14: 1 | CR14: 1 | CS14: 0 | CT14: 0 | CU14: 0 | CV14: 0 | CW14: 0 | CX14: 0 | CY14: 0
B15: IPE 600 | D15: 122 | F15: 600 | G15: 220 | H15: 12 | I15: 19 | J15: 24 | K15: 562 | L15: 514 | M15: 156 | N15: 2.015 | O15: 16.46 | P15: 1 | Q15: HI | R15: HI | S15: 1 | T15: HI | U15: 1 | V15: HI | W15: HI | X15: 1 | Y15: HI | Z15: - | AA15: - | AC15: 92080 | AD15: 3069 | AE15: 3512 | AF15: 24.2 | AG15: 83.78 | AH15: 3387 | AI15: 307.9 | AJ15: 485.6 | AK15: 4.6 | AL15: 7.8 | AM15: 165.2 | AN15: 2845 | AO15: 1 | AP15: 1 | AQ15: 4 | AR15: 4 | AS15: 115 | AT15: 129 | AU15: 91 | AV15: 105 | AW15: 1 | AX15: 1 | AY15: 0 | AZ15: 1 | BA15: 1 | BB15: 1 | BC15: 0 | BD15: 1 | BE15: 1 | BF15: 1 | BG15: 1 | BH15: 1 | BI15: 1 | BJ15: 1 | BK15: 1 | BL15: 1 | BM15: 1 | BN15: 0 | BO15: 1 | BP15: 1 | BQ15: 0 | BR15: 0 | BS15: 0 | BT15: 0 | BU15: 0 | BV15: 0 | BW15: 0 | BX15: 0 | BY15: 0 | BZ15: 0 | CA15: 0 | CB15: 0 | CC15: 0 | CD15: 0 | CE15: 0 | CF15: 1 | CG15: 1 | CH15: 1 | CI15: 1 | CJ15: 1 | CK15: 1 | CL15: 1 | CM15: 1 | CN15: 1 | CO15: 1 | CP15: 1 | CQ15: 1 | CR15: 1 | CS15: 0 | CT15: 0 | CU15: 0 | CV15: 0 | CW15: 0 | CX15: 0 | CY15: 0
B16: IPE A 600 | D16: 108 | F16: 597 | G16: 220 | H16: 9.8 | I16: 17.5 | J16: 24 | K16: 562 | L16: 514 | M16: 137 | N16: 2.013 | O16: 18.71 | P16: 1 | Q16: 1 | R16: - | S16: 1 | T16: 1 | U16: 1 | V16: 1 | W16: - | X16: - | Y16: - | Z16: - | AA16: - | AB16: 40 | AC16: 82910 | AD16: 2777 | AE16: 3141 | AF16: 24.5 | AG16: 70.13 | AH16: 3116 | AI16: 283.2 | AJ16: 442 | AK16: 4.7 | AL16: 7.2 | AM16: 122.1 | AN16: 2607 | AO16: 1 | AP16: 2 | AQ16: 4 | AR16: 4 | AS16: 131 | AT16: 147 | AU16: 103 | AV16: 119 | AW16: 1 | AX16: 1 | AY16: 0 | AZ16: 1 | BA16: 1 | BB16: 1 | BC16: 0 | BD16: 1 | BE16: 0 | BF16: 0 | BG16: 1 | BH16: 0 | BI16: 1 | BJ16: 1 | BK16: 1 | BL16: 1 | BM16: 0 | BN16: 0 | BO16: 1 | BP16: 1 | BQ16: 0 | BR16: 0 | BS16: 1 | BT16: 0 | BU16: 0 | BV16: 0 | BW16: 0 | BX16: 0 | BY16: 0 | BZ16: 0 | CA16: 0 | CB16: 0 | CC16: 0 | CD16: 0 | CE16: 0 | CF16: 1 | CG16: 1 | CH16: 1 | CI16: 1 | CJ16: 1 | CK16: 1 | CL16: 1 | CM16: 1 | CN16: 1 | CO16: 1 | CP16: 1 | CQ16: 1 | CR16: 1 | CS16: 0 | CT16: 0 | CU16: 0 | CV16: 0 | CW16: 0 | CX16: 0 | CY16: 0
B17: IPE V 550 | D17: 159 | F17: 566 | G17: 216 | H17: 17.1 | I17: 25.2 | J17: 24 | K17: 515.6 | L17: 467.6 | M17: 202 | N17: 1.921 | O17: 12.12 | P17: 1 | Q17: 1 | R17: - | S17: 1 | T17: 1 | U17: 1 | V17: - | W17: - | X17: - | Y17: - | Z17: - | AA17: - | AB17: T | AC17: 102330 | AD17: 3616 | AE17: 4204 | AF17: 22.5 | AG17: 109.5 | AH17: 4264 | AI17: 394.8 | AJ17: 632.4 | AK17: 4.5 | AL17: 9.5 | AM17: 372.4 | AN17: 3094 | AO17: 1 | AP17: - | AQ17: 2 | AR17: - | AS17: 84 | AT17: 95 | AU17: 67 | AV17: 77 | AW17: 1 | AX17: 1 | AY17: 0 | AZ17: 1 | BA17: 0 | BB17: 0 | BC17: 0 | BD17: 1 | BE17: 0 | BF17: 0 | BG17: 1 | BH17: 0 | BI17: 1 | BJ17: 1 | BK17: 1 | BL17: 1 | BM17: 0 | BN17: 0 | BO17: 1 | BP17: 1 | BQ17: 0 | BR17: 0 | BS17: 0 | BT17: 1 | BU17: 0 | BV17: 0 | BW17: 0 | BX17: 0 | BY17: 0 | BZ17: 0 | CA17: 0 | CB17: 0 | CC17: 0 | CD17: 0 | CE17: 0 | CF17: 1 | CG17: 1 | CH17: 1 | CI17: 1 | CJ17: 1 | CK17: 1 | CL17: 1 | CM17: 1 | CN17: 1 | CO17: 1 | CP17: 1 | CQ17: 1 | CR17: 1 | CS17: 0 | CT17: 0 | CU17: 0 | CV17: 0 | CW17: 0 | CX17: 0 | CY17: 0
B18: IPE O 550 | D18: 123 | F18: 556 | G18: 212 | H18: 12.7 | I18: 20.2 | J18: 24 | K18: 515.6 | L18: 467.6 | M18: 156.1 | N18: 1.893 | O18: 15.45 | P18: 1 | Q18: 1 | R18: 1 | S18: 1 | T18: 1 | U18: 1 | V18: 1 | W18: - | X18: - | Y18: 1 | Z18: - | AA18: - | AB18: 40 | AC18: 79150 | AD18: 2847 | AE18: 3263 | AF18: 22.5 | AG18: 82.68 | AH18: 3224 | AI18: 304.1 | AJ18: 480.5 | AK18: 4.5 | AL18: 8.1 | AM18: 187.1 | AN18: 2302 | AO18: 1 | AP18: 1 | AQ18: 4 | AR18: 4 | AS18: 108 | AT18: 121 | AU18: 85 | AV18: 98 | AW18: 1 | AX18: 1 | AY18: 0 | AZ18: 1 | BA18: 1 | BB18: 1 | BC18: 0 | BD18: 1 | BE18: 0 | BF18: 0 | BG18: 1 | BH18: 0 | BI18: 1 | BJ18: 1 | BK18: 1 | BL18: 1 | BM18: 0 | BN18: 0 | BO18: 1 | BP18: 1 | BQ18: 0 | BR18: 0 | BS18: 1 | BT18: 0 | BU18: 0 | BV18: 0 | BW18: 0 | BX18: 0 | BY18: 0 | BZ18: 0 | CA18: 0 | CB18: 0 | CC18: 0 | CD18: 0 | CE18: 0 | CF18: 1 | CG18: 1 | CH18: 1 | CI18: 1 | CJ18: 1 | CK18: 1 | CL18: 1 | CM18: 1 | CN18: 1 | CO18: 1 | CP18: 1 | CQ18: 1 | CR18: 1 | CS18: 0 | CT18: 0 | CU18: 0 | CV18: 0 | CW18: 0 | CX18: 0 | CY18: 0
B19: IPE 550 | D19: 106 | F19: 550 | G19: 210 | H19: 11.1 | I19: 17.2 | J19: 24 | K19: 515.6 | L19: 467.6 | M19: 134.4 | N19: 1.877 | O19: 17.79 | P19: 1 | Q19: 1 | R19: 1 | S19: 1 | T19: 1 | U19: 1 | V19: 1 | W19: 1 | X19: - | Y19: 1 | Z19: - | AA19: - | AC19: 67110 | AD19: 2440 | AE19: 2787 | AF19: 22.3 | AG19: 72.34 | AH19: 2667 | AI19: 254 | AJ19: 400.5 | AK19: 4.4 | AL19: 7.3 | AM19: 122.8 | AN19: 1884 | AO19: 1 | AP19: 1 | AQ19: 4 | AR19: 4 | AS19: 124 | AT19: 140 | AU19: 97 | AV19: 113 | AW19: 1 | AX19: 1 | AY19: 0 | AZ19: 1 | BA19: 1 | BB19: 1 | BC19: 0 | BD19: 1 | BE19: 0 | BF19: 0 | BG19: 1 | BH19: 0 | BI19: 1 | BJ19: 1 | BK19: 1 | BL19: 1 | BM19: 0 | BN19: 0 | BO19: 1 | BP19: 1 | BQ19: 0 | BR19: 0 | BS19: 0 | BT19: 0 | BU19: 0 | BV19: 0 | BW19: 0 | BX19: 0 | BY19: 0 | BZ19: 0 | CA19: 0 | CB19: 0 | CC19: 0 | CD19: 0 | CE19: 0 | CF19: 1 | CG19: 1 | CH19: 1 | CI19: 1 | CJ19: 1 | CK19: 1 | CL19: 1 | CM19: 1 | CN19: 1 | CO19: 1 | CP19: 1 | CQ19: 1 | CR19: 1 | CS19: 0 | CT19: 0 | CU19: 0 | CV19: 0 | CW19: 0 | CX19: 0 | CY19: 0
B20: IPE A 550 | D20: 92.1 | F20: 547 | G20: 210 | H20: 9 | I20: 15.7 | J20: 24 | K20: 515.6 | L20: 467.6 | M20: 117.3 | N20: 1.875 | O20: 20.36 | P20: 1 | Q20: 1 | R20: 1 | S20: 1 | T20: 1 | U20: 1 | V20: 1 | W20: 1 | X20: - | Y20: 1 | Z20: - | AA20: - | AC20: 59970 | AD20: 2193 | AE20: 2474 | AF20: 22.6 | AG20: 60.29 | AH20: 2432 | AI20: 231.6 | AJ20: 361.5 | AK20: 4.5 | AL20: 6.8 | AM20: 89.29 | AN20: 1710 | AO20: 1 | AP20: 2 | AQ20: 4 | AR20: 4 | AS20: 142 | AT20: 160 | AU20: 111 | AV20: 129 | AW20: 1 | AX20: 1 | AY20: 0 | AZ20: 1 | BA20: 1 | BB20: 1 | BC20: 0 | BD20: 1 | BE20: 0 | BF20: 0 | BG20: 1 | BH20: 0 | BI20: 1 | BJ20: 1 | BK20: 1 | BL20: 1 | BM20: 0 | BN20: 0 | BO20: 1 | BP20: 1 | BQ20: 0 | BR20: 0 | BS20: 0 | BT20: 0 | BU20: 0 | BV20: 0 | BW20: 0 | BX20: 0 | BY20: 0 | BZ20: 0 | CA20: 0 | CB20: 0 | CC20: 0 | CD20: 0 | CE20: 0 | CF20: 1 | CG20: 1 | CH20: 1 | CI20: 1 | CJ20: 1 | CK20: 1 | CL20: 1 | CM20: 1 | CN20: 1 | CO20: 1 | CP20: 1 | CQ20: 1 | CR20: 1 | CS20: 0 | CT20: 0 | CU20: 0 | CV20: 0 | CW20: 0 | CX20: 0 | CY20: 0
A21: Dimensions: AM Standard | B21: IPE AA 550 | D21: 79.5 | F21: 541 | G21: 210 | H21: 8.5 | I21: 12.5 | J21: 24 | K21: 515.6 | L21: 467.6 | M21: 101.3 | N21: 1.864 | O21: 23.44 | P21: 1 | Q21: 1 | R21: 1 | S21: 1 | T21: 1 | U21: - | V21: 1 | W21: 1 | X21: - | Y21: - | Z21: - | AA21: - | AB21: T | AC21: 49550 | AD21: 1831 | AE21: 2078 | AF21: 22.1 | AG21: 55.86 | AH21: 1937 | AI21: 184.5 | AJ21: 289.6 | AK21: 4.3 | AL21: 6.1 | AM21: 56.18 | AN21: 1347 | AO21: 1 | AP21: 2 | AQ21: 4 | AR21: 4 | AS21: 163 | AT21: 184 | AU21: 128 | AV21: 148 | AW21: 1 | AX21: 0 | AY21: 0 | AZ21: 1 | BA21: 1 | BB21: 1 | BC21: 0 | BD21: 1 | BE21: 0 | BF21: 0 | BG21: 0 | BH21: 0 | BI21: 1 | BJ21: 0 | BK21: 0 | BL21: 0 | BM21: 0 | BN21: 0 | BO21: 0 | BP21: 1 | BQ21: 0 | BR21: 0 | BS21: 0 | BT21: 1 | BU21: 1 | BV21: 0 | BW21: 0 | BX21: 0 | BY21: 0 | BZ21: 0 | CA21: 0 | CB21: 0 | CC21: 0 | CD21: 0 | CE21: 0 | CF21: 1 | CG21: 1 | CH21: 1 | CI21: 1 | CJ21: 1 | CK21: 1 | CL21: 1 | CM21: 1 | CN21: 1 | CO21: 1 | CP21: 1 | CQ21: 1 | CR21: 1 | CS21: 0 | CT21: 0 | CU21: 0 | CV21: 0 | CW21: 0 | CX21: 0 | CY21: 0
B22: IPE V 500 | D22: 129 | F22: 514 | G22: 204 | H22: 14.2 | I22: 23 | J22: 21 | K22: 468 | L22: 426 | M22: 164.1 | N22: 1.78 | O22: 13.82 | P22: 1 | Q22: 1 | R22: 1 | S22: 1 | T22: 1 | U22: - | V22: 1 | W22: 1 | X22: - | Y22: - | Z22: - | AA22: - | AB22: T | AC22: 70710 | AD22: 2751 | AE22: 3168 | AF22: 20.7 | AG22: 83.16 | AH22: 3271 | AI22: 320.7 | AJ22: 506.6 | AK22: 4.4 | AL22: 8.4 | AM22: 241.5 | AN22: 1961 | AO22: 1 | AP22: 1 | AQ22: 2 | AR22: 3 | AS22: 96 | AT22: 108 | AU22: 75 | AV22: 88 | AW22: 1 | AX22: 0 | AY22: 0 | AZ22: 1 | BA22: 1 | BB22: 1 | BC22: 0 | BD22: 1 | BE22: 0 | BF22: 0 | BG22: 0 | BH22: 0 | BI22: 1 | BJ22: 0 | BK22: 0 | BL22: 0 | BM22: 0 | BN22: 0 | BO22: 0 | BP22: 1 | BQ22: 0 | BR22: 0 | BS22: 0 | BT22: 1 | BU22: 0 | BV22: 0 | BW22: 0 | BX22: 0 | BY22: 0 | BZ22: 0 | CA22: 0 | CB22: 0 | CC22: 0 | CD22: 0 | CE22: 0 | CF22: 1 | CG22: 1 | CH22: 1 | CI22: 1 | CJ22: 1 | CK22: 1 | CL22: 1 | CM22: 1 | CN22: 1 | CO22: 1 | CP22: 1 | CQ22: 1 | CR22: 1 | CS22: 0 | CT22: 0 | CU22: 0 | CV22: 0 | CW22: 0 | CX22: 0 | CY22: 0
B23: IPE O 500 | D23: 107 | F23: 506 | G23: 202 | H23: 12 | I23: 19 | J23: 21 | K23: 468 | L23: 426 | M23: 136.7 | N23: 1.76 | O23: 16.4 | P23: 1 | Q23: 1 | R23: 1 | S23: 1 | T23: 1 | U23: - | V23: 1 | W23: - | X23: - | Y23: 1 | Z23: - | AA23: - | AB23: 40 | AC23: 57770 | AD23: 2283 | AE23: 2612 | AF23: 20.5 | AG23: 70.2 | AH23: 2621 | AI23: 259.5 | AJ23: 408.5 | AK23: 4.3 | AL23: 7.4 | AM23: 142.7 | AN23: 1547 | AO23: 1 | AP23: 1 | AQ23: 4 | AR23: 4 | AS23: 114 | AT23: 129 | AU23: 89 | AV23: 104 | AW23: 1 | AX23: 0 | AY23: 0 | AZ23: 1 | BA23: 1 | BB23: 1 | BC23: 0 | BD23: 1 | BE23: 0 | BF23: 0 | BG23: 1 | BH23: 0 | BI23: 1 | BJ23: 1 | BK23: 1 | BL23: 1 | BM23: 0 | BN23: 0 | BO23: 1 | BP23: 1 | BQ23: 0 | BR23: 0 | BS23: 1 | BT23: 0 | BU23: 0 | BV23: 0 | BW23: 0 | BX23: 0 | BY23: 0 | BZ23: 0 | CA23: 0 | CB23: 0 | CC23: 0 | CD23: 0 | CE23: 0 | CF23: 1 | CG23: 1 | CH23: 1 | CI23: 1 | CJ23: 1 | CK23: 1 | CL23: 1 | CM23: 1 | CN23: 1 | CO23: 1 | CP23: 1 | CQ23: 1 | CR23: 1 | CS23: 0 | CT23: 0 | CU23: 0 | CV23: 0 | CW23: 0 | CX23: 0 | CY23: 0
B24: IPE 500 | D24: 90.7 | F24: 500 | G24: 200 | H24: 10.2 | I24: 16 | J24: 21 | K24: 468 | L24: 426 | M24: 115.5 | N24: 1.744 | O24: 19.23 | P24: 1 | Q24: 1 | R24: 1 | S24: 1 | T24: 1 | U24: - | V24: 1 | W24: 1 | X24: - | Y24: 1 | Z24: - | AA24: - | AC24: 48190 | AD24: 1927 | AE24: 2194 | AF24: 20.4 | AG24: 59.87 | AH24: 2141 | AI24: 214.1 | AJ24: 335.8 | AK24: 4.3 | AL24: 6.6 | AM24: 89.09 | AN24: 1249 | AO24: 1 | AP24: 1 | AQ24: 4 | AR24: 4 | AS24: 134 | AT24: 151 | AU24: 104 | AV24: 121 | AW24: 1 | AX24: 0 | AY24: 0 | AZ24: 1 | BA24: 1 | BB24: 1 | BC24: 0 | BD24: 1 | BE24: 0 | BF24: 0 | BG24: 1 | BH24: 0 | BI24: 1 | BJ24: 1 | BK24: 1 | BL24: 1 | BM24: 0 | BN24: 0 | BO24: 1 | BP24: 1 | BQ24: 0 | BR24: 0 | BS24: 0 | BT24: 0 | BU24: 0 | BV24: 0 | BW24: 0 | BX24: 0 | BY24: 0 | BZ24: 0 | CA24: 0 | CB24: 0 | CC24: 0 | CD24: 0 | CE24: 0 | CF24: 1 | CG24: 1 | CH24: 1 | CI24: 1 | CJ24: 1 | CK24: 1 | CL24: 1 | CM24: 1 | CN24: 1 | CO24: 1 | CP24: 1 | CQ24: 1 | CR24: 1 | CS24: 0 | CT24: 0 | CU24: 0 | CV24: 0 | CW24: 0 | CX24: 0 | CY24: 0
B25: IPE A 500 | D25: 79.4 | F25: 497 | G25: 200 | H25: 8.4 | I25: 14.5 | J25: 21 | K25: 468 | L25: 426 | M25: 101.1 | N25: 1.741 | O25: 21.94 | P25: 1 | Q25: 1 | R25: 1 | S25: 1 | T25: 1 | U25: - | V25: 1 | W25: 1 | X25: - | Y25: 1 | Z25: - | AA25: - | AC25: 42930 | AD25: 1727 | AE25: 1946 | AF25: 20.6 | AG25: 50.4 | AH25: 1939 | AI25: 193.9 | AJ25: 301.6 | AK25: 4.3 | AL25: 6.2 | AM25: 64.28 | AN25: 1125 | AO25: 1 | AP25: 1 | AQ25: 4 | AR25: 4 | AS25: 152 | AT25: 172 | AU25: 118 | AV25: 138 | AW25: 1 | AX25: 0 | AY25: 0 | AZ25: 1 | BA25: 1 | BB25: 1 | BC25: 0 | BD25: 1 | BE25: 0 | BF25: 0 | BG25: 1 | BH25: 0 | BI25: 1 | BJ25: 1 | BK25: 1 | BL25: 1 | BM25: 0 | BN25: 0 | BO25: 1 | BP25: 1 | BQ25: 0 | BR25: 0 | BS25: 0 | BT25: 0 | BU25: 0 | BV25: 0 | BW25: 0 | BX25: 0 | BY25: 0 | BZ25: 0 | CA25: 0 | CB25: 0 | CC25: 0 | CD25: 0 | CE25: 0 | CF25: 1 | CG25: 1 | CH25: 1 | CI25: 1 | CJ25: 1 | CK25: 1 | CL25: 1 | CM25: 1 | CN25: 1 | CO25: 1 | CP25: 1 | CQ25: 1 | CR25: 1 | CS25: 0 | CT25: 0 | CU25: 0 | CV25: 0 | CW25: 0 | CX25: 0 | CY25: 0
A26: Dimensions: AM Standard | B26: IPE AA 500 | D26: 73.2 | F26: 495.2 | G26: 200 | H26: 7.5 | I26: 13.6 | J26: 21 | K26: 468 | L26: 426 | M26: 93.3 | N26: 1.739 | O26: 23.75 | P26: 1 | Q26: 1 | R26: 1 | S26: 1 | T26: 1 | U26: - | V26: 1 | W26: 1 | X26: - | Y26: - | Z26: - | AA26: - | AB26: T | AC26: 39940 | AD26: 1613 | AE26: 1807 | AF26: 20.6 | AG26: 45.61 | AH26: 1818 | AI26: 181.8 | AJ26: 281.7 | AK26: 4.4 | AL26: 5.9 | AM26: 52.86 | AN26: 1051 | AO26: 1 | AP26: 2 | AQ26: 4 | AR26: 4 | AS26: 165 | AT26: 186 | AU26: 128 | AV26: 149 | AW26: 1 | AX26: 0 | AY26: 0 | AZ26: 1 | BA26: 1 | BB26: 1 | BC26: 0 | BD26: 1 | BE26: 0 | BF26: 0 | BG26: 0 | BH26: 0 | BI26: 1 | BJ26: 0 | BK26: 0 | BL26: 0 | BM26: 0 | BN26: 0 | BO26: 0 | BP26: 1 | BQ26: 0 | BR26: 0 | BS26: 0 | BT26: 1 | BU26: 1 | BV26: 0 | BW26: 0 | BX26: 0 | BY26: 0 | BZ26: 0 | CA26: 0 | CB26: 0 | CC26: 0 | CD26: 0 | CE26: 0 | CF26: 1 | CG26: 1 | CH26: 1 | CI26: 1 | CJ26: 1 | CK26: 1 | CL26: 1 | CM26: 1 | CN26: 1 | CO26: 1 | CP26: 1 | CQ26: 1 | CR26: 1 | CS26: 0 | CT26: 0 | CU26: 0 | CV26: 0 | CW26: 0 | CX26: 0 | CY26: 0
B27: IPE V 450 | D27: 107 | F27: 460 | G27: 194 | H27: 12.4 | I27: 19.6 | J27: 21 | K27: 420.8 | L27: 378.8 | M27: 132 | N27: 1.635 | O27: 15.78 | P27: 1 | Q27: 1 | R27: 1 | S27: 1 | T27: 1 | U27: - | V27: 1 | W27: - | X27: - | Y27: 1 | Z27: - | AA27: - | AB27: 40 | AC27: 46200 | AD27: 2008 | AE27: 2301 | AF27: 18.7 | AG27: 66.62 | AH27: 2396 | AI27: 247.1 | AJ27: 389.1 | AK27: 4.2 | AL27: 7.6 | AM27: 148.8 | AN27: 1156 | AO27: 1 | AP27: 1 | AQ27: 2 | AR27: 4 | AS27: 109 | AT27: 124 | AU27: 84 | AV27: 99 | AW27: 1 | AX27: 0 | AY27: 0 | AZ27: 1 | BA27: 0 | BB27: 1 | BC27: 0 | BD27: 1 | BE27: 0 | BF27: 0 | BG27: 1 | BH27: 0 | BI27: 1 | BJ27: 1 | BK27: 1 | BL27: 1 | BM27: 0 | BN27: 0 | BO27: 1 | BP27: 1 | BQ27: 0 | BR27: 0 | BS27: 1 | BT27: 0 | BU27: 0 | BV27: 0 | BW27: 0 | BX27: 0 | BY27: 0 | BZ27: 0 | CA27: 0 | CB27: 0 | CC27: 0 | CD27: 0 | CE27: 0 | CF27: 1 | CG27: 1 | CH27: 1 | CI27: 1 | CJ27: 1 | CK27: 1 | CL27: 1 | CM27: 1 | CN27: 1 | CO27: 1 | CP27: 1 | CQ27: 1 | CR27: 1 | CS27: 0 | CT27: 0 | CU27: 0 | CV27: 0 | CW27: 0 | CX27: 0 | CY27: 0
B28: IPE O 450 | D28: 92.4 | F28: 456 | G28: 192 | H28: 11 | I28: 17.6 | J28: 21 | K28: 420.8 | L28: 378.8 | M28: 117.7 | N28: 1.622 | O28: 17.56 | P28: 1 | Q28: 1 | R28: 1 | S28: 1 | T28: 1 | U28: - | V28: 1 | W28: - | X28: - | Y28: 1 | Z28: - | AA28: - | AB28: 40 | AC28: 40920 | AD28: 1794 | AE28: 2046 | AF28: 18.6 | AG28: 59.4 | AH28: 2085 | AI28: 217.2 | AJ28: 340.9 | AK28: 4.2 | AL28: 7 | AM28: 108.9 | AN28: 997.5 | AO28: 1 | AP28: 1 | AQ28: 4 | AR28: 4 | AS28: 122 | AT28: 138 | AU28: 94 | AV28: 110 | AW28: 1 | AX28: 0 | AY28: 0 | AZ28: 1 | BA28: 1 | BB28: 1 | BC28: 0 | BD28: 1 | BE28: 0 | BF28: 0 | BG28: 1 | BH28: 0 | BI28: 1 | BJ28: 1 | BK28: 1 | BL28: 1 | BM28: 0 | BN28: 0 | BO28: 1 | BP28: 1 | BQ28: 0 | BR28: 0 | BS28: 1 | BT28: 0 | BU28: 0 | BV28: 0 | BW28: 0 | BX28: 0 | BY28: 0 | BZ28: 0 | CA28: 0 | CB28: 0 | CC28: 0 | CD28: 0 | CE28: 0 | CF28: 1 | CG28: 1 | CH28: 1 | CI28: 1 | CJ28: 1 | CK28: 1 | CL28: 1 | CM28: 1 | CN28: 1 | CO28: 1 | CP28: 1 | CQ28: 1 | CR28: 1 | CS28: 0 | CT28: 0 | CU28: 0 | CV28: 0 | CW28: 0 | CX28: 0 | CY28: 0
B29: IPE 450 | D29: 77.6 | F29: 450 | G29: 190 | H29: 9.4 | I29: 14.6 | J29: 21 | K29: 420.8 | L29: 378.8 | M29: 98.8 | N29: 1.605 | O29: 20.69 | P29: 1 | Q29: 1 | R29: 1 | S29: 1 | T29: 1 | U29: - | V29: 1 | W29: 1 | X29: - | Y29: 1 | Z29: - | AA29: - | AC29: 33740 | AD29: 1499 | AE29: 1701 | AF29: 18.4 | AG29: 50.84 | AH29: 1675 | AI29: 176.4 | AJ29: 276.3 | AK29: 4.1 | AL29: 6.3 | AM29: 66.74 | AN29: 791 | AO29: 1 | AP29: 1 | AQ29: 4 | AR29: 4 | AS29: 143 | AT29: 162 | AU29: 110 | AV29: 130 | AW29: 1 | AX29: 0 | AY29: 0 | AZ29: 1 | BA29: 1 | BB29: 1 | BC29: 0 | BD29: 1 | BE29: 0 | BF29: 0 | BG29: 1 | BH29: 0 | BI29: 1 | BJ29: 1 | BK29: 1 | BL29: 1 | BM29: 0 | BN29: 0 | BO29: 1 | BP29: 1 | BQ29: 0 | BR29: 0 | BS29: 0 | BT29: 0 | BU29: 0 | BV29: 0 | BW29: 0 | BX29: 0 | BY29: 0 | BZ29: 0 | CA29: 0 | CB29: 0 | CC29: 0 | CD29: 0 | CE29: 0 | CF29: 1 | CG29: 1 | CH29: 1 | CI29: 1 | CJ29: 1 | CK29: 1 | CL29: 1 | CM29: 1 | CN29: 1 | CO29: 1 | CP29: 1 | CQ29: 1 | CR29: 1 | CS29: 0 | CT29: 0 | CU29: 0 | CV29: 0 | CW29: 0 | CX29: 0 | CY29: 0
B30: IPE A 450 | D30: 67.2 | F30: 447 | G30: 190 | H30: 7.6 | I30: 13.1 | J30: 21 | K30: 420.8 | L30: 378.8 | M30: 85.6 | N30: 1.603 | O30: 23.87 | P30: 1 | Q30: 1 | R30: 1 | S30: 1 | T30: 1 | U30: - | V30: 1 | W30: 1 | X30: - | Y30: 1 | Z30: - | AA30: - | AC30: 29750 | AD30: 1331 | AE30: 1494 | AF30: 18.6 | AG30: 42.26 | AH30: 1502 | AI30: 158.1 | AJ30: 245.7 | AK30: 4.1 | AL30: 5.8 | AM30: 47.13 | AN30: 704.8 | AO30: 1 | AP30: 1 | AQ30: 4 | AR30: 4 | AS30: 165 | AT30: 187 | AU30: 127 | AV30: 149 | AW30: 1 | AX30: 0 | AY30: 0 | AZ30: 1 | BA30: 1 | BB30: 1 | BC30: 0 | BD30: 1 | BE30: 0 | BF30: 0 | BG30: 1 | BH30: 0 | BI30: 1 | BJ30: 1 | BK30: 1 | BL30: 1 | BM30: 0 | BN30: 0 | BO30: 1 | BP30: 1 | BQ30: 0 | BR30: 0 | BS30: 0 | BT30: 0 | BU30: 0 | BV30: 0 | BW30: 0 | BX30: 0 | BY30: 0 | BZ30: 0 | CA30: 0 | CB30: 0 | CC30: 0 | CD30: 0 | CE30: 0 | CF30: 1 | CG30: 1 | CH30: 1 | CI30: 1 | CJ30: 1 | CK30: 1 | CL30: 1 | CM30: 1 | CN30: 1 | CO30: 1 | CP30: 1 | CQ30: 1 | CR30: 1 | CS30: 0 | CT30: 0 | CU30: 0 | CV30: 0 | CW30: 0 | CX30: 0 | CY30: 0
A31: Dimensions: AM Standard | B31: IPE AA 450 | D31: 62.1 | F31: 445.4 | G31: 190 | H31: 6.8 | I31: 12.3 | J31: 21 | K31: 420.8 | L31: 378.8 | M31: 79.1 | N31: 1.601 | O31: 25.77 | P31: 1 | Q31: 1 | R31: 1 | S31: 1 | T31: 1 | U31: - | V31: 1 | W31: 1 | X31: - | Y31: - | Z31: - | AA31: - | AB31: T | AC31: 27740 | AD31: 1246 | AE31: 1391 | AF31: 18.7 | AG31: 38.4 | AH31: 1410 | AI31: 148.4 | AJ31: 229.9 | AK31: 4.2 | AL31: 5.6 | AM31: 39.16 | AN31: 659.3 | AO31: 1 | AP31: 2 | AQ31: 4 | AR31: 4 | AS31: 178 | AT31: 202 | AU31: 137 | AV31: 161 | AW31: 1 | AX31: 0 | AY31: 0 | AZ31: 1 | BA31: 1 | BB31: 1 | BC31: 0 | BD31: 1 | BE31: 0 | BF31: 0 | BG31: 0 | BH31: 0 | BI31: 1 | BJ31: 0 | BK31: 0 | BL31: 0 | BM31: 0 | BN31: 0 | BO31: 0 | BP31: 1 | BQ31: 0 | BR31: 0 | BS31: 0 | BT31: 1 | BU31: 1 | BV31: 0 | BW31: 0 | BX31: 0 | BY31: 0 | BZ31: 0 | CA31: 0 | CB31: 0 | CC31: 0 | CD31: 0 | CE31: 0 | CF31: 1 | CG31: 1 | CH31: 1 | CI31: 1 | CJ31: 1 | CK31: 1 | CL31: 1 | CM31: 1 | CN31: 1 | CO31: 1 | CP31: 1 | CQ31: 1 | CR31: 1 | CS31: 0 | CT31: 0 | CU31: 0 | CV31: 0 | CW31: 0 | CX31: 0 | CY31: 0
B32: IPE V 400 | D32: 84 | F32: 408 | G32: 182 | H32: 10.6 | I32: 17.5 | J32: 21 | K32: 373 | L32: 331 | M32: 107 | N32: 1.487 | O32: 17.7 | P32: 1 | Q32: 1 | R32: 1 | S32: 1 | T32: 1 | U32: - | V32: 1 | W32: - | X32: - | Y32: 1 | Z32: - | AA32: - | AB32: 40 | AC32: 30130 | AD32: 1477 | AE32: 1681 | AF32: 16.7 | AG32: 52.52 | AH32: 1766 | AI32: 194.1 | AJ32: 304 | AK32: 4 | AL32: 7 | AM32: 99.58 | AN32: 670.3 | AO32: 1 | AP32: 1 | AQ32: 3 | AR32: 4 | AS32: 122 | AT32: 139 | AU32: 93 | AV32: 110 | AW32: 1 | AX32: 0 | AY32: 0 | AZ32: 1 | BA32: 0 | BB32: 1 | BC32: 0 | BD32: 1 | BE32: 0 | BF32: 0 | BG32: 1 | BH32: 0 | BI32: 1 | BJ32: 1 | BK32: 1 | BL32: 1 | BM32: 0 | BN32: 0 | BO32: 1 | BP32: 1 | BQ32: 0 | BR32: 0 | BS32: 1 | BT32: 0 | BU32: 0 | BV32: 0 | BW32: 0 | BX32: 0 | BY32: 0 | BZ32: 0 | CA32: 0 | CB32: 0 | CC32: 0 | CD32: 0 | CE32: 0 | CF32: 1 | CG32: 1 | CH32: 1 | CI32: 1 | CJ32: 1 | CK32: 1 | CL32: 1 | CM32: 1 | CN32: 1 | CO32: 1 | CP32: 1 | CQ32: 1 | CR32: 1 | CS32: 0 | CT32: 0 | CU32: 0 | CV32: 0 | CW32: 0 | CX32: 0 | CY32: 0
B33: IPE O 400 | D33: 75.7 | F33: 404 | G33: 182 | H33: 9.7 | I33: 15.5 | J33: 21 | K33: 373 | L33: 331 | M33: 96.4 | N33: 1.481 | O33: 19.57 | P33: 1 | Q33: 1 | R33: 1 | S33: 1 | T33: 1 | U33: - | V33: 1 | W33: - | X33: - | Y33: 1 | Z33: - | AA33: - | AB33: 40 | AC33: 26740 | AD33: 1324 | AE33: 1502 | AF33: 16.6 | AG33: 47.98 | AH33: 1564 | AI33: 171.8 | AJ33: 269 | AK33: 4 | AL33: 6.5 | AM33: 73.34 | AN33: 587.6 | AO33: 1 | AP33: 1 | AQ33: 3 | AR33: 4 | AS33: 135 | AT33: 154 | AU33: 103 | AV33: 122 | AW33: 1 | AX33: 0 | AY33: 0 | AZ33: 1 | BA33: 1 | BB33: 1 | BC33: 0 | BD33: 1 | BE33: 0 | BF33: 0 | BG33: 1 | BH33: 0 | BI33: 1 | BJ33: 1 | BK33: 1 | BL33: 1 | BM33: 0 | BN33: 0 | BO33: 1 | BP33: 1 | BQ33: 0 | BR33: 0 | BS33: 1 | BT33: 0 | BU33: 0 | BV33: 0 | BW33: 0 | BX33: 0 | BY33: 0 | BZ33: 0 | CA33: 0 | CB33: 0 | CC33: 0 | CD33: 0 | CE33: 0 | CF33: 1 | CG33: 1 | CH33: 1 | CI33: 1 | CJ33: 1 | CK33: 1 | CL33: 1 | CM33: 1 | CN33: 1 | CO33: 1 | CP33: 1 | CQ33: 1 | CR33: 1 | CS33: 0 | CT33: 0 | CU33: 0 | CV33: 0 | CW33: 0 | CX33: 0 | CY33: 0
